Workbook

Sheet INICIO
C1: CONTROL DE PROYECTO | F1: Hoja de inicio: diligencie las celdas amarillas. Todo lo demás se calcula solo.
B2: ● INICIO | C2: TABLERO | D2: CRONOGRAMA | E2: PRESUPUESTO | F2: CORTES CLIENTE | H2: MANO DE OBRA | I2: GASTOS | K2: MATERIALES | M2: GUÍA
B4: DATOS DEL PROYECTO | G4: VALOR DEL CONTRATO (calculado)
B5: Nombre del proyecto | G5: Costo directo (valor de venta de ítems) | H5: =PRESUPUESTO!G5 -> 0
B6: Cliente | G6: Administración | H6: =v_CD*p_Admin -> 0
B7: Ciudad | G7: Imprevistos | H7: =v_CD*p_Imprev -> 0
B8: N° cotización / referencia | G8: Utilidad | H8: =v_CD*p_Util -> 0
B9: Fecha de cotización | G9: IVA sobre utilidad | H9: =v_CD*p_Util*p_IVA -> 0
B10: Fecha de inicio de obra | G10: TOTAL CONTRATO | H10: =SUM(H5:H9) -> 0
B11: Fecha fin contractual | G11: Ingreso del proyecto sin IVA (CD + A + I + U) | H11: =SUM(H5:H8) -> 0
B12: Director de proyecto | G12: Valor del anticipo | H12: =v_Total*p_Anticipo -> 0
B13: Comercial responsable
B14: Contratista de mano de obra | G14: TARIFAS TÉCNICOS PROPIOS
B15: Estado del proyecto | G15: Cargo | H15: Valor hora | I15: Horas / día | J15: Valor día
G16: Técnico electricista | H16: 12000 | I16: 8 | J16: =IF(G16="","",H16*I16) -> 96000
B17: PARÁMETROS FINANCIEROS | G17: Técnico de redes / CCTV | H17: 12000 | I17: 8 | J17: =IF(G17="","",H17*I17) -> 96000
B18: Administración (A) | C18: 0.08 | D18: Sobre costo directo de venta | G18: Auxiliar técnico | H18: 8500 | I18: 8 | J18: =IF(G18="","",H18*I18) -> 68000
B19: Imprevistos (I) | C19: 0.03 | G19: Supervisor / Ingeniero residente | H19: 25000 | I19: 8 | J19: =IF(G19="","",H19*I19) -> 200000
B20: Utilidad (U) | C20: 0.05 | J20: =IF(G20="","",H20*I20)
B21: IVA | C21: 0.19 | D21: Se cobra sobre la utilidad (esquema AIU) | J21: =IF(G21="","",H21*I21)
B22: ¿Sumar IVA al costo de materiales? | C22: Sí | D22: En AIU el IVA de compras es costo | J22: =IF(G22="","",H22*I22)
B23: Anticipo pactado | C23: 0.3 | D23: Se amortiza en cada acta | J23: =IF(G23="","",H23*I23)
B24: Impuestos (% sobre costo directo) | C24: 0.051 | D24: Tomado del cotizador | G24: Valores de EJEMPLO: reemplace por las tarifas reales de la empresa.
B25: Pólizas (% sobre total contrato) | C25: 0.015 | D25: Tomado del cotizador
B26: Gastos legales (% sobre costo directo) | C26: 0.001 | D26: Tomado del cotizador (abogado) | G26: CÓMO SE USA (código de colores)
B27: Recargo hora extra técnicos | C27: 0.25 | D27: Supuesto — confirmar | G27: Celda amarilla, letra azul | H27: Dato que USTED digita
B28: Anticipo recibido ($) | D28: Digite el valor cuando entre | G28: Celda blanca, letra negra | H28: Fórmula: no se toca
G29: Fila azul claro | H29: Capítulo / agrupador
B30: ÍNDICE DEL LIBRO | G30: Rojo / ámbar / verde | H30: Semáforo de alertas
B31: TABLERO | C31: Tablero: margen, avance, facturación y alertas
B32: CRONOGRAMA | C32: Hitos y frentes con fechas, Gantt y alertas de atraso | G32: • Para un proyecto nuevo: guarde una copia de la PLANTILLA, llene INICIO y pegue los ítems de la cotización en PRESUPUESTO.
B33: PRESUPUESTO | C33: Ítems de la cotización con costos (base de todo)
B34: CORTES CLIENTE | C34: Avance de obra, actas y facturación al cliente | G34: • Agregue ítems en las filas vacías al final del PRESUPUESTO; no inserte filas en medio (las demás hojas se alinean por fila).
B35: MANO DE OBRA | C35: Contratista (contrato y cortes) + horas de técnicos propios
B36: GASTOS | C36: ÚNICA hoja de registro: compras, suministros, alquileres, transporte y pagos | G36: • Todo gasto (compras, alquileres, transporte, pagos al contratista) se escribe UNA sola vez en GASTOS: una fila por ítem comprado o por pago.
B37: CONTROL DE MATERIALES | C37: Por ítem: comprado, faltante, precio promedio y alertas (solo lectura)
B38: GUÍA APP | C38: Cómo pasar este modelo al desarrollo web

Sheet TABLERO
D1: TABLERO DEL PROYECTO | H1: Se actualiza solo con lo que se digita en las demás hojas.
B2: INICIO | C2: ● TABLERO | D2: CRONOGRAMA | E2: PRESUPUESTO | F2: CORTES CLIENTE | G2: MANO DE OBRA | H2: GASTOS | I2: MATERIALES | J2: GUÍA
B3: =n_Proyecto&" · Cliente: "&n_Cliente&" · "&n_Cotizacion&" · Corte al "&TEXT(TODAY(),"dd/mm/yyyy") -> · Cliente: · · Corte al 17/10/2026
B5: VALOR DEL CONTRATO | E5: AVANCE FÍSICO | H5: FACTURADO (neto) | K5: COSTO REAL A LA FECHA | N5: MARGEN BRUTO PROYECTADO
B6: =v_Total -> 0 | E6: ='CORTES CLIENTE'!$N$18 | H6: =(SUMIF('CORTES CLIENTE'!$F$16:$K$16,"Facturado",'CORTES CLIENTE'!$F$13:$K$13)+SUMIF('CORTES CLIENTE'!$F$16:$K$16,"Pagado",'CORTES CLIENTE'!$F$13:$K$13))+N(p_AntRecibido) -> 0 | K6: =E16 -> 0 | N6: =F24
B7: ="Ingreso sin IVA: "&TEXT(v_Ingreso,"$#,##0") -> Ingreso sin IVA: $0 | E7: ="Ejecutado: "&TEXT('CORTES CLIENTE'!$O$18,"$#,##0") -> Ejecutado: $0 | H7: ="Incluye anticipo recibido · "&TEXT(IF(v_Total=0,0,((SUMIF('CORTES CLIENTE'!$F$16:$K$16,"Facturado",'CORTES CLIENTE'!$F$13:$K$13)+SUMIF('CORTES CLIENTE'!$F$16:$K$16,"Pagado",'CORTES CLIENTE'!$F$13:$K$13))+N(p_AntRecibido))/v_Total),"0%")&" del contrato" -> Incluye anticipo recibido · 0% del contrato | K7: ="Consumido: "&TEXT(IF(D16=0,0,E16/D16),"0.0%")&" del presupuesto" -> Consumido: 0.0% del presupuesto | N7: ="Al cierre: "&TEXT(E24,"$#,##0") -> Al cierre: $0
B9: CONTROL DE COSTOS POR CATEGORÍA
B10: Categoría | D10: Presupuesto | E10: Real a la fecha | F10: % consumido | G10: Saldo disponible | H10: Proyección al cierre | I10: Desviación | J10: Estado | K10: Regla de proyección
B11: Materiales y equipos | D11: =PRESUPUESTO!O5 -> 0 | E11: =SUMIFS(GASTOS!$J$7:$J$5000,GASTOS!$L$7:$L$5000,"Materiales y equipos") -> 0 | F11: =IF(D11=0,"",E11/D11) | G11: =D11-E11 -> 0 | H11: =E11+v_FaltMat -> 0 | I11: =H11-D11 -> 0 | J11: =IF(H11>D11+1,"Sobrecosto",IF(IF(D11>0,E11/D11,0)>N('CORTES CLIENTE'!$N$18)+0.15,"Atención","En control")) -> En control | K11: Real + faltante valorizado (CONTROL DE MATERIALES)
B12: Mano de obra | D12: =PRESUPUESTO!P5 -> 0 | E12: =SUMIFS(GASTOS!$J$7:$J$5000,GASTOS!$L$7:$L$5000,"Mano de obra contratista")+v_MOPropia -> 0 | F12: =IF(D12=0,"",E12/D12) | G12: =D12-E12 -> 0 | H12: =MAX(E12,'MANO DE OBRA'!$H$11+v_MOPropia) -> 0 | I12: =H12-D12 -> 0 | J12: =IF(H12>D12+1,"Sobrecosto",IF(IF(D12>0,E12/D12,0)>N('CORTES CLIENTE'!$N$18)+0.15,"Atención","En control")) -> En control | K12: Contrato contratista + MO propia
B13: Transporte y otros | D13: =PRESUPUESTO!Q5 -> 0 | E13: =SUMIFS(GASTOS!$J$7:$J$5000,GASTOS!$L$7:$L$5000,"Transporte y otros") -> 0 | F13: =IF(D13=0,"",E13/D13) | G13: =D13-E13 -> 0 | H13: =MAX(D13,E13) -> 0 | I13: =H13-D13 -> 0 | J13: =IF(H13>D13+1,"Sobrecosto",IF(IF(D13>0,E13/D13,0)>N('CORTES CLIENTE'!$N$18)+0.15,"Atención","En control")) -> En control | K13: Mayor entre real y presupuesto
B14: Alquileres | D14: =PRESUPUESTO!R5 -> 0 | E14: =SUMIFS(GASTOS!$J$7:$J$5000,GASTOS!$L$7:$L$5000,"Alquileres") -> 0 | F14: =IF(D14=0,"",E14/D14) | G14: =D14-E14 -> 0 | H14: =MAX(D14,E14) -> 0 | I14: =H14-D14 -> 0 | J14: =IF(H14>D14+1,"Sobrecosto",IF(IF(D14>0,E14/D14,0)>N('CORTES CLIENTE'!$N$18)+0.15,"Atención","En control")) -> En control | K14: Mayor entre real y presupuesto
B15: Impuestos y pólizas | D15: =v_CD*(p_Impuestos+p_Legales)+v_Total*p_Polizas -> 0 | E15: =D15*N('CORTES CLIENTE'!$N$18) -> 0 | F15: =IF(D15=0,"",E15/D15) | G15: =D15-E15 -> 0 | H15: =D15 -> 0 | I15: =H15-D15 -> 0 | J15: En control | K15: Se causan según avance
B16: TOTAL | D16: =SUM(D11:D15) -> 0 | E16: =SUM(E11:E15) -> 0 | F16: =IF(D16=0,"",E16/D16) | G16: =SUM(G11:G15) -> 0 | H16: =SUM(H11:H15) -> 0 | I16: =SUM(I11:I15) -> 0 | J16: =IF(H16>D16+1,"Sobrecosto","En control") -> En control
B18: MARGEN BRUTO | H18: FACTURACIÓN Y CARTERA
B19: Concepto | E19: Valor | F19: % | H19: Concepto | K19: Valor
B20: Ingreso del contrato (sin IVA) | E20: =v_Ingreso -> 0 | H20: Valor total del contrato (con IVA) | K20: =v_Total -> 0
B21: Costo presupuestado total | E21: =D16 -> 0 | H21: Anticipo pactado | K21: =v_Anticipo -> 0
B22: MARGEN BRUTO PRESUPUESTADO | E22: =E20-E21 -> 0 | F22: =IF(E20=0,"",E22/E20) | H22: Anticipo recibido | K22: =N(p_AntRecibido) -> 0
B23: Costo proyectado al cierre | E23: =H16 -> 0 | H23: Total actas generadas | K23: ='CORTES CLIENTE'!L11 -> 0
B24: MARGEN BRUTO PROYECTADO | E24: =E20-E23 -> 0 | F24: =IF(E20=0,"",E24/E20) | H24: Facturado en actas (neto) | K24: =(SUMIF('CORTES CLIENTE'!$F$16:$K$16,"Facturado",'CORTES CLIENTE'!$F$13:$K$13)+SUMIF('CORTES CLIENTE'!$F$16:$K$16,"Pagado",'CORTES CLIENTE'!$F$13:$K$13)) -> 0
B25: Ingreso causado a la fecha (actas sin IVA) | E25: =SUM('CORTES CLIENTE'!L6:L9) -> 0 | H25: Recaudado (actas + anticipo) | K25: ='CORTES CLIENTE'!L17+N(p_AntRecibido) -> 0
B26: Costo real a la fecha | E26: =E16 -> 0 | H26: SALDO DEL CONTRATO POR EJECUTAR | K26: =v_Total-'CORTES CLIENTE'!L11 -> 0
B27: MARGEN REAL A LA FECHA | E27: =E25-E26 -> 0 | F27: =IF(E25=0,"",E27/E25) | H27: CARTERA POR COBRAR | K27: =K24-'CORTES CLIENTE'!L17 -> 0
B29: PRESUPUESTO vs REAL vs PROYECCIÓN | I29: GASTOS POR TIPO (desde GASTOS)
I30: Tipo | L30: Valor | M30: % del total | N30: N° registros
I31: Material | L31: =SUMIFS(GASTOS!$J$7:$J$5000,GASTOS!$C$7:$C$5000,I31) -> 0 | M31: =IF(L$37=0,"",L31/L$37) | N31: =COUNTIF(GASTOS!$C$7:$C$5000,I31) -> 0
I32: Equipo | L32: =SUMIFS(GASTOS!$J$7:$J$5000,GASTOS!$C$7:$C$5000,I32) -> 0 | M32: =IF(L$37=0,"",L32/L$37) | N32: =COUNTIF(GASTOS!$C$7:$C$5000,I32) -> 0
I33: Suministro | L33: =SUMIFS(GASTOS!$J$7:$J$5000,GASTOS!$C$7:$C$5000,I33) -> 0 | M33: =IF(L$37=0,"",L33/L$37) | N33: =COUNTIF(GASTOS!$C$7:$C$5000,I33) -> 0
I34: Alquiler | L34: =SUMIFS(GASTOS!$J$7:$J$5000,GASTOS!$C$7:$C$5000,I34) -> 0 | M34: =IF(L$37=0,"",L34/L$37) | N34: =COUNTIF(GASTOS!$C$7:$C$5000,I34) -> 0
I35: Transporte | L35: =SUMIFS(GASTOS!$J$7:$J$5000,GASTOS!$C$7:$C$5000,I35) -> 0 | M35: =IF(L$37=0,"",L35/L$37) | N35: =COUNTIF(GASTOS!$C$7:$C$5000,I35) -> 0
I36: Mano de obra contratista | L36: =SUMIFS(GASTOS!$J$7:$J$5000,GASTOS!$C$7:$C$5000,I36) -> 0 | M36: =IF(L$37=0,"",L36/L$37) | N36: =COUNTIF(GASTOS!$C$7:$C$5000,I36) -> 0
I37: TOTAL GASTADO | L37: =SUM(L31:L36) -> 0 | M37: =IF(L37=0,"",SUM(M31:M36)) | N37: =SUM(N31:N36) -> 0

Sheet CRONOGRAMA
D1: CRONOGRAMA DE OBRA | G1: Fases separadas por color. Digite duración y predecesora (o inicio fijo); al poner fechas REALES todo lo que depende se corre solo. Use los botones [-]/[+] de la izquierda para contraer o expandir cada fase.
B2: INICIO | D2: TABLERO | F2: ● CRONOGRAMA | G2: PRESUPUESTO | I2: CORTES CLIENTE | K2: MANO DE OBRA | M2: GASTOS | O2: MATERIALES | Q2: GUÍA
B3: INICIO | D3: FIN PROYECTADO | F3: FIN CONTRACTUAL | H3: HOLGURA (días) | J3: AVANCE FÍSICO | M3: HITOS CUMPLIDOS | O3: ATRASADAS
B4: =IF(COUNT($J$8:$J$36)=0,"",MIN($J$8:$J$36)) -> 46312 | D4: =IF(COUNT($K$8:$K$36)=0,"",MAX($K$8:$K$36)) -> 46348 | F4: =IF(n_FFin="","Sin definir",n_FFin) -> Sin definir | H4: =IF(OR(n_FFin="",COUNT($K$8:$K$36)=0),"",n_FFin-MAX($K$8:$K$36)) | J4: ='CORTES CLIENTE'!N18 | M4: =COUNTIFS($D$8:$D$36,"Hito",$P$8:$P$36,"Cumplido")&" / "&COUNTIF($D$8:$D$36,"Hito") -> 0 / 6 | O4: =COUNTIF($P$8:$P$36,"Atrasada")+COUNTIF($P$8:$P$36,"Vencido") -> 0
Y5: =TEXT(Y7,"yyyy") -> 2026 | Z5: =IF(1=0,TEXT(Z7,"yyyy"),IF(YEAR(Z7)<>YEAR(Y7),TEXT(Z7,"yyyy"),"")) | AA5: =IF(2=0,TEXT(AA7,"yyyy"),IF(YEAR(AA7)<>YEAR(Z7),TEXT(AA7,"yyyy"),"")) | AB5: =IF(3=0,TEXT(AB7,"yyyy"),IF(YEAR(AB7)<>YEAR(AA7),TEXT(AB7,"yyyy"),"")) | AC5: =IF(4=0,TEXT(AC7,"yyyy"),IF(YEAR(AC7)<>YEAR(AB7),TEXT(AC7,"yyyy"),"")) | AD5: =IF(5=0,TEXT(AD7,"yyyy"),IF(YEAR(AD7)<>YEAR(AC7),TEXT(AD7,"yyyy"),"")) | AE5: =IF(6=0,TEXT(AE7,"yyyy"),IF(YEAR(AE7)<>YEAR(AD7),TEXT(AE7,"yyyy"),"")) | AF5: =IF(7=0,TEXT(AF7,"yyyy"),IF(YEAR(AF7)<>YEAR(AE7),TEXT(AF7,"yyyy"),"")) | AG5: =IF(8=0,TEXT(AG7,"yyyy"),IF(YEAR(AG7)<>YEAR(AF7),TEXT(AG7,"yyyy"),"")) | AH5: =IF(9=0,TEXT(AH7,"yyyy"),IF(YEAR(AH7)<>YEAR(AG7),TEXT(AH7,"yyyy"),"")) | AI5: =IF(10=0,TEXT(AI7,"yyyy"),IF(YEAR(AI7)<>YEAR(AH7),TEXT(AI7,"yyyy"),"")) | AJ5: =IF(11=0,TEXT(AJ7,"yyyy"),IF(YEAR(AJ7)<>YEAR(AI7),TEXT(AJ7,"yyyy"),"")) | AK5: =IF(12=0,TEXT(AK7,"yyyy"),IF(YEAR(AK7)<>YEAR(AJ7),TEXT(AK7,"yyyy"),"")) -> 2027 | AL5: =IF(13=0,TEXT(AL7,"yyyy"),IF(YEAR(AL7)<>YEAR(AK7),TEXT(AL7,"yyyy"),"")) | AM5: =IF(14=0,TEXT(AM7,"yyyy"),IF(YEAR(AM7)<>YEAR(AL7),TEXT(AM7,"yyyy"),"")) | AN5: =IF(15=0,TEXT(AN7,"yyyy"),IF(YEAR(AN7)<>YEAR(AM7),TEXT(AN7,"yyyy"),"")) | AO5: =IF(16=0,TEXT(AO7,"yyyy"),IF(YEAR(AO7)<>YEAR(AN7),TEXT(AO7,"yyyy"),"")) | AP5: =IF(17=0,TEXT(AP7,"yyyy"),IF(YEAR(AP7)<>YEAR(AO7),TEXT(AP7,"yyyy"),"")) | AQ5: =IF(18=0,TEXT(AQ7,"yyyy"),IF(YEAR(AQ7)<>YEAR(AP7),TEXT(AQ7,"yyyy"),"")) | AR5: =IF(19=0,TEXT(AR7,"yyyy"),IF(YEAR(AR7)<>YEAR(AQ7),TEXT(AR7,"yyyy"),"")) | AS5: =IF(20=0,TEXT(AS7,"yyyy"),IF(YEAR(AS7)<>YEAR(AR7),TEXT(AS7,"yyyy"),"")) | AT5: =IF(21=0,TEXT(AT7,"yyyy"),IF(YEAR(AT7)<>YEAR(AS7),TEXT(AT7,"yyyy"),"")) | AU5: =IF(22=0,TEXT(AU7,"yyyy"),IF(YEAR(AU7)<>YEAR(AT7),TEXT(AU7,"yyyy"),"")) | AV5: =IF(23=0,TEXT(AV7,"yyyy"),IF(YEAR(AV7)<>YEAR(AU7),TEXT(AV7,"yyyy"),"")) | AW5: =IF(24=0,TEXT(AW7,"yyyy"),IF(YEAR(AW7)<>YEAR(AV7),TEXT(AW7,"yyyy"),"")) | AX5: =IF(25=0,TEXT(AX7,"yyyy"),IF(YEAR(AX7)<>YEAR(AW7),TEXT(AX7,"yyyy"),"")) | AY5: =IF(26=0,TEXT(AY7,"yyyy"),IF(YEAR(AY7)<>YEAR(AX7),TEXT(AY7,"yyyy"),"")) | AZ5: =IF(27=0,TEXT(AZ7,"yyyy"),IF(YEAR(AZ7)<>YEAR(AY7),TEXT(AZ7,"yyyy"),"")) | BA5: =IF(28=0,TEXT(BA7,"yyyy"),IF(YEAR(BA7)<>YEAR(AZ7),TEXT(BA7,"yyyy"),"")) | BB5: =IF(29=0,TEXT(BB7,"yyyy"),IF(YEAR(BB7)<>YEAR(BA7),TEXT(BB7,"yyyy"),"")) | BC5: =IF(30=0,TEXT(BC7,"yyyy"),IF(YEAR(BC7)<>YEAR(BB7),TEXT(BC7,"yyyy"),"")) | BD5: =IF(31=0,TEXT(BD7,"yyyy"),IF(YEAR(BD7)<>YEAR(BC7),TEXT(BD7,"yyyy"),"")) | BE5: =IF(32=0,TEXT(BE7,"yyyy"),IF(YEAR(BE7)<>YEAR(BD7),TEXT(BE7,"yyyy"),"")) | BF5: =IF(33=0,TEXT(BF7,"yyyy"),IF(YEAR(BF7)<>YEAR(BE7),TEXT(BF7,"yyyy"),"")) | BG5: =IF(34=0,TEXT(BG7,"yyyy"),IF(YEAR(BG7)<>YEAR(BF7),TEXT(BG7,"yyyy"),"")) | BH5: =IF(35=0,TEXT(BH7,"yyyy"),IF(YEAR(BH7)<>YEAR(BG7),TEXT(BH7,"yyyy"),"")) | BI5: =IF(36=0,TEXT(BI7,"yyyy"),IF(YEAR(BI7)<>YEAR(BH7),TEXT(BI7,"yyyy"),"")) | BJ5: =IF(37=0,TEXT(BJ7,"yyyy"),IF(YEAR(BJ7)<>YEAR(BI7),TEXT(BJ7,"yyyy"),"")) | BK5: =IF(38=0,TEXT(BK7,"yyyy"),IF(YEAR(BK7)<>YEAR(BJ7),TEXT(BK7,"yyyy"),"")) | BL5: =IF(39=0,TEXT(BL7,"yyyy"),IF(YEAR(BL7)<>YEAR(BK7),TEXT(BL7,"yyyy"),"")) | BM5: =IF(40=0,TEXT(BM7,"yyyy"),IF(YEAR(BM7)<>YEAR(BL7),TEXT(BM7,"yyyy"),"")) | BN5: =IF(41=0,TEXT(BN7,"yyyy"),IF(YEAR(BN7)<>YEAR(BM7),TEXT(BN7,"yyyy"),"")) | BO5: =IF(42=0,TEXT(BO7,"yyyy"),IF(YEAR(BO7)<>YEAR(BN7),TEXT(BO7,"yyyy"),"")) | BP5: =IF(43=0,TEXT(BP7,"yyyy"),IF(YEAR(BP7)<>YEAR(BO7),TEXT(BP7,"yyyy"),"")) | BQ5: =IF(44=0,TEXT(BQ7,"yyyy"),IF(YEAR(BQ7)<>YEAR(BP7),TEXT(BQ7,"yyyy"),"")) | BR5: =IF(45=0,TEXT(BR7,"yyyy"),IF(YEAR(BR7)<>YEAR(BQ7),TEXT(BR7,"yyyy"),"")) | BS5: =IF(46=0,TEXT(BS7,"yyyy"),IF(YEAR(BS7)<>YEAR(BR7),TEXT(BS7,"yyyy"),"")) | BT5: =IF(47=0,TEXT(BT7,"yyyy"),IF(YEAR(BT7)<>YEAR(BS7),TEXT(BT7,"yyyy"),"")) | BU5: =IF(48=0,TEXT(BU7,"yyyy"),IF(YEAR(BU7)<>YEAR(BT7),TEXT(BU7,"yyyy"),"")) | BV5: =IF(49=0,TEXT(BV7,"yyyy"),IF(YEAR(BV7)<>YEAR(BU7),TEXT(BV7,"yyyy"),"")) | BW5: =IF(50=0,TEXT(BW7,"yyyy"),IF(YEAR(BW7)<>YEAR(BV7),TEXT(BW7,"yyyy"),"")) | BX5: =IF(51=0,TEXT(BX7,"yyyy"),IF(YEAR(BX7)<>YEAR(BW7),TEXT(BX7,"yyyy"),""))
Y6: =TEXT(Y7,"mmm") -> Oct | Z6: =IF(MONTH(Z7)<>MONTH(Y7),TEXT(Z7,"mmm"),"") | AA6: =IF(MONTH(AA7)<>MONTH(Z7),TEXT(AA7,"mmm"),"") | AB6: =IF(MONTH(AB7)<>MONTH(AA7),TEXT(AB7,"mmm"),"") -> Nov | AC6: =IF(MONTH(AC7)<>MONTH(AB7),TEXT(AC7,"mmm"),"") | AD6: =IF(MONTH(AD7)<>MONTH(AC7),TEXT(AD7,"mmm"),"") | AE6: =IF(MONTH(AE7)<>MONTH(AD7),TEXT(AE7,"mmm"),"") | AF6: =IF(MONTH(AF7)<>MONTH(AE7),TEXT(AF7,"mmm"),"") | AG6: =IF(MONTH(AG7)<>MONTH(AF7),TEXT(AG7,"mmm"),"") -> Dec | ... BX6: =IF(MONTH(BX7)<>MONTH(BW7),TEXT(BX7,"mmm"),"") -> Oct
B7: ID | C7: FASE / ACTIVIDAD | D7: Tipo | E7: Responsable | F7: Frente vinculado (presupuesto) | G7: Pred. | H7: Inicio fijo (opcional) | I7: Días | J7: Inicio | K7: Fin | L7: Inicio REAL | M7: Fin REAL | N7: % manual | O7: Avance | P7: Estado | Q7: Días atraso | Y7: =IF(COUNT($J$8:$J$36)=0,TODAY(),MIN($J$8:$J$36))-WEEKDAY(IF(COUNT($J$8:$J$36)=0,TODAY(),MIN($J$8:$J$36)),2)+1 -> 46307 | Z7: =Y7+7 -> 46314 | AA7: =Z7+7 -> 46321 | AB7: =AA7+7 -> 46328 | AC7: =AB7+7 -> 46335 | AD7: =AC7+7 -> 46342 | AE7: =AD7+7 -> 46349 | AF7: =AE7+7 -> 46356 | AG7: =AF7+7 -> 46363 | ... BX7: =BW7+7 -> 46664
B8: ="F"&R8 -> F1 | C8: INICIO Y PLANEACIÓN | D8: Fase | I8: =IF(OR(J8="",K8=""),"",K8-J8+1) -> 6 | J8: =IFERROR(1/(1/_xlfn.MINIFS($S$8:$S$36,$R$8:$R$36,R8)),"") -> 46312 | K8: =IFERROR(1/(1/_xlfn.MAXIFS($T$8:$T$36,$R$8:$R$36,R8)),"") -> 46317 | O8: =IFERROR(SUMIFS($V$8:$V$36,$R$8:$R$36,R8)/SUMIFS($U$8:$U$36,$R$8:$R$36,R8),"") -> 0 | P8: =IF(COUNTIFS($R$8:$R$36,R8,$U$8:$U$36,">0")=0,"",IF(COUNTIFS($R$8:$R$36,R8,$W$8:$W$36,"Atrasada")+COUNTIFS($R$8:$R$36,R8,$W$8:$W$36,"Vencido")>0,"Con atraso",IF(N(O8)>=1,"Terminada",IF(N(O8)>0,"En curso","Por iniciar")))) -> Por iniciar | Q8: =IF(N(_xlfn.MAXIFS($X$8:$X$36,$R$8:$R$36,R8))>0,_xlfn.MAXIFS($X$8:$X$36,$R$8:$R$36,R8),"") | R8: =COUNTIF($D$8:D8,"Fase") -> 1
B9: 1 | C9: Firma de contrato / orden de compra | D9: Hito | E9: Gerencia | I9: 0 | J9: =IF(C9="","",IF(L9<>"",L9,IF(H9<>"",H9,IF(G9<>"",IFERROR(INDEX($T$8:$T$36,MATCH(G9,$B$8:$B$36,0))+IF(D9="Hito",0,1),IF(n_FInicio="",TODAY(),n_FInicio)),IF(n_FInicio="",TODAY(),n_FInicio))))) -> 46312 | K9: =IF(C9="","",IF(M9<>"",M9,IF(D9="Hito",J9,J9+MAX(N(I9),1)-1))) -> 46312 | O9: =IF(C9="","",IF(N9<>"",N9,IF(M9<>"",1,IF(F9="",0,IF(D9="Instalación",MIN(1,IFERROR(SUMIFS('CORTES CLIENTE'!$O$20:$O$219,PRESUPUESTO!$V$7:$V$206,F9)/SUMIFS(PRESUPUESTO!$G$7:$G$206,PRESUPUESTO!$V$7:$V$206,F9),0)),IF(D9="Compra",MIN(1,IFERROR(SUMIFS('CONTROL DE MATERIALES'!$U$11:$U$210,PRESUPUESTO!$V$7:$V$206,F9)/SUMIFS('CONTROL DE MATERIALES'!$V$11:$V$210,PRESUPUESTO!$V$7:$V$206,F9),0)),0)))))) -> 0 | P9: =IF(C9="","",IF(D9="Hito",IF(O9>=1,"Cumplido",IF(TODAY()>K9,"Vencido","Pendiente")),IF(O9>=1,"Terminada",IF(TODAY()>K9,"Atrasada",IF(OR(O9>0,L9<>""),"En curso",IF(TODAY()>=J9,"Debe iniciar","Por iniciar")))))) -> Pendiente | Q9: =IF(OR(C9="",N(O9)>=1),"",IF(TODAY()>K9,TODAY()-K9,0)) -> 0 | R9: =COUNTIF($D$8:D9,"Fase") -> 1 | S9: =IF(C9="","",J9) -> 46312 | T9: =IF(C9="","",K9) -> 46312 | U9: =IF(C9="","",MAX(N(I9),1)) -> 1 | V9: =IF(C9="","",U9*N(O9)) -> 0 | W9: =P9 -> Pendiente | X9: =IF(Q9="","",N(Q9)) -> 0 | Y9: =IF(AND($D9="Hito",ISNUMBER($K9)),IF(AND($K9>=Y$7,$K9<Y$7+7),"◆",""),"") -> ◆ | Z9: =IF(AND($D9="Hito",ISNUMBER($K9)),IF(AND($K9>=Z$7,$K9<Z$7+7),"◆",""),"") | AA9: =IF(AND($D9="Hito",ISNUMBER($K9)),IF(AND($K9>=AA$7,$K9<AA$7+7),"◆",""),"") | AB9: =IF(AND($D9="Hito",ISNUMBER($K9)),IF(AND($K9>=AB$7,$K9<AB$7+7),"◆",""),"") | AC9: =IF(AND($D9="Hito",ISNUMBER($K9)),IF(AND($K9>=AC$7,$K9<AC$7+7),"◆",""),"") | AD9: =IF(AND($D9="Hito",ISNUMBER($K9)),IF(AND($K9>=AD$7,$K9<AD$7+7),"◆",""),"") | AE9: =IF(AND($D9="Hito",ISNUMBER($K9)),IF(AND($K9>=AE$7,$K9<AE$7+7),"◆",""),"") | AF9: =IF(AND($D9="Hito",ISNUMBER($K9)),IF(AND($K9>=AF$7,$K9<AF$7+7),"◆",""),"") | ... BX9: =IF(AND($D9="Hito",ISNUMBER($K9)),IF(AND($K9>=BX$7,$K9<BX$7+7),"◆",""),"")
B10: 2 | C10: Socialización del proyecto con el cliente | D10: Hito | E10: Dir. proyectos | G10: 1 | I10: 0 | J10: =IF(C10="","",IF(L10<>"",L10,IF(H10<>"",H10,IF(G10<>"",IFERROR(INDEX($T$8:$T$36,MATCH(G10,$B$8:$B$36,0))+IF(D10="Hito",0,1),IF(n_FInicio="",TODAY(),n_FInicio)),IF(n_FInicio="",TODAY(),n_FInicio))))) -> 46312 | K10: =IF(C10="","",IF(M10<>"",M10,IF(D10="Hito",J10,J10+MAX(N(I10),1)-1))) -> 46312 | O10: =IF(C10="","",IF(N10<>"",N10,IF(M10<>"",1,IF(F10="",0,IF(D10="Instalación",MIN(1,IFERROR(SUMIFS('CORTES CLIENTE'!$O$20:$O$219,PRESUPUESTO!$V$7:$V$206,F10)/SUMIFS(PRESUPUESTO!$G$7:$G$206,PRESUPUESTO!$V$7:$V$206,F10),0)),IF(D10="Compra",MIN(1,IFERROR(SUMIFS('CONTROL DE MATERIALES'!$U$11:$U$210,PRESUPUESTO!$V$7:$V$206,F10)/SUMIFS('CONTROL DE MATERIALES'!$V$11:$V$210,PRESUPUESTO!$V$7:$V$206,F10),0)),0)))))) -> 0 | P10: =IF(C10="","",IF(D10="Hito",IF(O10>=1,"Cumplido",IF(TODAY()>K10,"Vencido","Pendiente")),IF(O10>=1,"Terminada",IF(TODAY()>K10,"Atrasada",IF(OR(O10>0,L10<>""),"En curso",IF(TODAY()>=J10,"Debe iniciar","Por iniciar")))))) -> Pendiente | Q10: =IF(OR(C10="",N(O10)>=1),"",IF(TODAY()>K10,TODAY()-K10,0)) -> 0 | R10: =COUNTIF($D$8:D10,"Fase") -> 1 | S10: =IF(C10="","",J10) -> 46312 | T10: =IF(C10="","",K10) -> 46312 | U10: =IF(C10="","",MAX(N(I10),1)) -> 1 | V10: =IF(C10="","",U10*N(O10)) -> 0 | W10: =P10 -> Pendiente | X10: =IF(Q10="","",N(Q10)) -> 0 | Y10: =IF(AND($D10="Hito",ISNUMBER($K10)),IF(AND($K10>=Y$7,$K10<Y$7+7),"◆",""),"") -> ◆ | Z10: =IF(AND($D10="Hito",ISNUMBER($K10)),IF(AND($K10>=Z$7,$K10<Z$7+7),"◆",""),"") | AA10: =IF(AND($D10="Hito",ISNUMBER($K10)),IF(AND($K10>=AA$7,$K10<AA$7+7),"◆",""),"") | AB10: =IF(AND($D10="Hito",ISNUMBER($K10)),IF(AND($K10>=AB$7,$K10<AB$7+7),"◆",""),"") | AC10: =IF(AND($D10="Hito",ISNUMBER($K10)),IF(AND($K10>=AC$7,$K10<AC$7+7),"◆",""),"") | AD10: =IF(AND($D10="Hito",ISNUMBER($K10)),IF(AND($K10>=AD$7,$K10<AD$7+7),"◆",""),"") | AE10: =IF(AND($D10="Hito",ISNUMBER($K10)),IF(AND($K10>=AE$7,$K10<AE$7+7),"◆",""),"") | AF10: =IF(AND($D10="Hito",ISNUMBER($K10)),IF(AND($K10>=AF$7,$K10<AF$7+7),"◆",""),"") | ... BX10: =IF(AND($D10="Hito",ISNUMBER($K10)),IF(AND($K10>=BX$7,$K10<BX$7+7),"◆",""),"")
B11: 3 | C11: Planeación, programación y pedidos iniciales | D11: Gestión | E11: Dir. proyectos | G11: 2 | I11: 5 | J11: =IF(C11="","",IF(L11<>"",L11,IF(H11<>"",H11,IF(G11<>"",IFERROR(INDEX($T$8:$T$36,MATCH(G11,$B$8:$B$36,0))+IF(D11="Hito",0,1),IF(n_FInicio="",TODAY(),n_FInicio)),IF(n_FInicio="",TODAY(),n_FInicio))))) -> 46313 | K11: =IF(C11="","",IF(M11<>"",M11,IF(D11="Hito",J11,J11+MAX(N(I11),1)-1))) -> 46317 | O11: =IF(C11="","",IF(N11<>"",N11,IF(M11<>"",1,IF(F11="",0,IF(D11="Instalación",MIN(1,IFERROR(SUMIFS('CORTES CLIENTE'!$O$20:$O$219,PRESUPUESTO!$V$7:$V$206,F11)/SUMIFS(PRESUPUESTO!$G$7:$G$206,PRESUPUESTO!$V$7:$V$206,F11),0)),IF(D11="Compra",MIN(1,IFERROR(SUMIFS('CONTROL DE MATERIALES'!$U$11:$U$210,PRESUPUESTO!$V$7:$V$206,F11)/SUMIFS('CONTROL DE MATERIALES'!$V$11:$V$210,PRESUPUESTO!$V$7:$V$206,F11),0)),0)))))) -> 0 | P11: =IF(C11="","",IF(D11="Hito",IF(O11>=1,"Cumplido",IF(TODAY()>K11,"Vencido","Pendiente")),IF(O11>=1,"Terminada",IF(TODAY()>K11,"Atrasada",IF(OR(O11>0,L11<>""),"En curso",IF(TODAY()>=J11,"Debe iniciar","Por iniciar")))))) -> Por iniciar | Q11: =IF(OR(C11="",N(O11)>=1),"",IF(TODAY()>K11,TODAY()-K11,0)) -> 0 | R11: =COUNTIF($D$8:D11,"Fase") -> 1 | S11: =IF(C11="","",J11) -> 46313 | T11: =IF(C11="","",K11) -> 46317 | U11: =IF(C11="","",MAX(N(I11),1)) -> 5 | V11: =IF(C11="","",U11*N(O11)) -> 0 | W11: =P11 -> Por iniciar | X11: =IF(Q11="","",N(Q11)) -> 0 | Y11: =IF(AND($D11="Hito",ISNUMBER($K11)),IF(AND($K11>=Y$7,$K11<Y$7+7),"◆",""),"") | Z11: =IF(AND($D11="Hito",ISNUMBER($K11)),IF(AND($K11>=Z$7,$K11<Z$7+7),"◆",""),"") | AA11: =IF(AND($D11="Hito",ISNUMBER($K11)),IF(AND($K11>=AA$7,$K11<AA$7+7),"◆",""),"") | AB11: =IF(AND($D11="Hito",ISNUMBER($K11)),IF(AND($K11>=AB$7,$K11<AB$7+7),"◆",""),"") | AC11: =IF(AND($D11="Hito",ISNUMBER($K11)),IF(AND($K11>=AC$7,$K11<AC$7+7),"◆",""),"") | AD11: =IF(AND($D11="Hito",ISNUMBER($K11)),IF(AND($K11>=AD$7,$K11<AD$7+7),"◆",""),"") | AE11: =IF(AND($D11="Hito",ISNUMBER($K11)),IF(AND($K11>=AE$7,$K11<AE$7+7),"◆",""),"") | AF11: =IF(AND($D11="Hito",ISNUMBER($K11)),IF(AND($K11>=AF$7,$K11<AF$7+7),"◆",""),"") | ... BX11: =IF(AND($D11="Hito",ISNUMBER($K11)),IF(AND($K11>=BX$7,$K11<BX$7+7),"◆",""),"")
B12: 4 | C12: Acta de inicio de obra | D12: Hito | E12: Dir. proyectos | G12: 3 | I12: 0 | J12: =IF(C12="","",IF(L12<>"",L12,IF(H12<>"",H12,IF(G12<>"",IFERROR(INDEX($T$8:$T$36,MATCH(G12,$B$8:$B$36,0))+IF(D12="Hito",0,1),IF(n_FInicio="",TODAY(),n_FInicio)),IF(n_FInicio="",TODAY(),n_FInicio))))) -> 46317 | K12: =IF(C12="","",IF(M12<>"",M12,IF(D12="Hito",J12,J12+MAX(N(I12),1)-1))) -> 46317 | O12: =IF(C12="","",IF(N12<>"",N12,IF(M12<>"",1,IF(F12="",0,IF(D12="Instalación",MIN(1,IFERROR(SUMIFS('CORTES CLIENTE'!$O$20:$O$219,PRESUPUESTO!$V$7:$V$206,F12)/SUMIFS(PRESUPUESTO!$G$7:$G$206,PRESUPUESTO!$V$7:$V$206,F12),0)),IF(D12="Compra",MIN(1,IFERROR(SUMIFS('CONTROL DE MATERIALES'!$U$11:$U$210,PRESUPUESTO!$V$7:$V$206,F12)/SUMIFS('CONTROL DE MATERIALES'!$V$11:$V$210,PRESUPUESTO!$V$7:$V$206,F12),0)),0)))))) -> 0 | P12: =IF(C12="","",IF(D12="Hito",IF(O12>=1,"Cumplido",IF(TODAY()>K12,"Vencido","Pendiente")),IF(O12>=1,"Terminada",IF(TODAY()>K12,"Atrasada",IF(OR(O12>0,L12<>""),"En curso",IF(TODAY()>=J12,"Debe iniciar","Por iniciar")))))) -> Pendiente | Q12: =IF(OR(C12="",N(O12)>=1),"",IF(TODAY()>K12,TODAY()-K12,0)) -> 0 | R12: =COUNTIF($D$8:D12,"Fase") -> 1 | S12: =IF(C12="","",J12) -> 46317 | T12: =IF(C12="","",K12) -> 46317 | U12: =IF(C12="","",MAX(N(I12),1)) -> 1 | V12: =IF(C12="","",U12*N(O12)) -> 0 | W12: =P12 -> Pendiente | X12: =IF(Q12="","",N(Q12)) -> 0 | Y12: =IF(AND($D12="Hito",ISNUMBER($K12)),IF(AND($K12>=Y$7,$K12<Y$7+7),"◆",""),"") | Z12: =IF(AND($D12="Hito",ISNUMBER($K12)),IF(AND($K12>=Z$7,$K12<Z$7+7),"◆",""),"") -> ◆ | AA12: =IF(AND($D12="Hito",ISNUMBER($K12)),IF(AND($K12>=AA$7,$K12<AA$7+7),"◆",""),"") | AB12: =IF(AND($D12="Hito",ISNUMBER($K12)),IF(AND($K12>=AB$7,$K12<AB$7+7),"◆",""),"") | AC12: =IF(AND($D12="Hito",ISNUMBER($K12)),IF(AND($K12>=AC$7,$K12<AC$7+7),"◆",""),"") | AD12: =IF(AND($D12="Hito",ISNUMBER($K12)),IF(AND($K12>=AD$7,$K12<AD$7+7),"◆",""),"") | AE12: =IF(AND($D12="Hito",ISNUMBER($K12)),IF(AND($K12>=AE$7,$K12<AE$7+7),"◆",""),"") | AF12: =IF(AND($D12="Hito",ISNUMBER($K12)),IF(AND($K12>=AF$7,$K12<AF$7+7),"◆",""),"") | ... BX12: =IF(AND($D12="Hito",ISNUMBER($K12)),IF(AND($K12>=BX$7,$K12<BX$7+7),"◆",""),"")
B13: ="F"&R13 -> F2 | C13: FRENTE 1 (cambie el nombre) | D13: Fase | I13: =IF(OR(J13="",K13=""),"",K13-J13+1) -> 28 | J13: =IFERROR(1/(1/_xlfn.MINIFS($S$8:$S$36,$R$8:$R$36,R13)),"") -> 46318 | K13: =IFERROR(1/(1/_xlfn.MAXIFS($T$8:$T$36,$R$8:$R$36,R13)),"") -> 46345 | O13: =IFERROR(SUMIFS($V$8:$V$36,$R$8:$R$36,R13)/SUMIFS($U$8:$U$36,$R$8:$R$36,R13),"") -> 0 | P13: =IF(COUNTIFS($R$8:$R$36,R13,$U$8:$U$36,">0")=0,"",IF(COUNTIFS($R$8:$R$36,R13,$W$8:$W$36,"Atrasada")+COUNTIFS($R$8:$R$36,R13,$W$8:$W$36,"Vencido")>0,"Con atraso",IF(N(O13)>=1,"Terminada",IF(N(O13)>0,"En curso","Por iniciar")))) -> Por iniciar | Q13: =IF(N(_xlfn.MAXIFS($X$8:$X$36,$R$8:$R$36,R13))>0,_xlfn.MAXIFS($X$8:$X$36,$R$8:$R$36,R13),"") | R13: =COUNTIF($D$8:D13,"Fase") -> 2
B14: 5 | C14: Compra materiales — lote 1 | D14: Compra | E14: Compras | G14: 4 | I14: 10 | J14: =IF(C14="","",IF(L14<>"",L14,IF(H14<>"",H14,IF(G14<>"",IFERROR(INDEX($T$8:$T$36,MATCH(G14,$B$8:$B$36,0))+IF(D14="Hito",0,1),IF(n_FInicio="",TODAY(),n_FInicio)),IF(n_FInicio="",TODAY(),n_FInicio))))) -> 46318 | K14: =IF(C14="","",IF(M14<>"",M14,IF(D14="Hito",J14,J14+MAX(N(I14),1)-1))) -> 46327 | O14: =IF(C14="","",IF(N14<>"",N14,IF(M14<>"",1,IF(F14="",0,IF(D14="Instalación",MIN(1,IFERROR(SUMIFS('CORTES CLIENTE'!$O$20:$O$219,PRESUPUESTO!$V$7:$V$206,F14)/SUMIFS(PRESUPUESTO!$G$7:$G$206,PRESUPUESTO!$V$7:$V$206,F14),0)),IF(D14="Compra",MIN(1,IFERROR(SUMIFS('CONTROL DE MATERIALES'!$U$11:$U$210,PRESUPUESTO!$V$7:$V$206,F14)/SUMIFS('CONTROL DE MATERIALES'!$V$11:$V$210,PRESUPUESTO!$V$7:$V$206,F14),0)),0)))))) -> 0 | P14: =IF(C14="","",IF(D14="Hito",IF(O14>=1,"Cumplido",IF(TODAY()>K14,"Vencido","Pendiente")),IF(O14>=1,"Terminada",IF(TODAY()>K14,"Atrasada",IF(OR(O14>0,L14<>""),"En curso",IF(TODAY()>=J14,"Debe iniciar","Por iniciar")))))) -> Por iniciar | Q14: =IF(OR(C14="",N(O14)>=1),"",IF(TODAY()>K14,TODAY()-K14,0)) -> 0 | R14: =COUNTIF($D$8:D14,"Fase") -> 2 | S14: =IF(C14="","",J14) -> 46318 | T14: =IF(C14="","",K14) -> 46327 | U14: =IF(C14="","",MAX(N(I14),1)) -> 10 | V14: =IF(C14="","",U14*N(O14)) -> 0 | W14: =P14 -> Por iniciar | X14: =IF(Q14="","",N(Q14)) -> 0 | Y14: =IF(AND($D14="Hito",ISNUMBER($K14)),IF(AND($K14>=Y$7,$K14<Y$7+7),"◆",""),"") | Z14: =IF(AND($D14="Hito",ISNUMBER($K14)),IF(AND($K14>=Z$7,$K14<Z$7+7),"◆",""),"") | AA14: =IF(AND($D14="Hito",ISNUMBER($K14)),IF(AND($K14>=AA$7,$K14<AA$7+7),"◆",""),"") | AB14: =IF(AND($D14="Hito",ISNUMBER($K14)),IF(AND($K14>=AB$7,$K14<AB$7+7),"◆",""),"") | AC14: =IF(AND($D14="Hito",ISNUMBER($K14)),IF(AND($K14>=AC$7,$K14<AC$7+7),"◆",""),"") | AD14: =IF(AND($D14="Hito",ISNUMBER($K14)),IF(AND($K14>=AD$7,$K14<AD$7+7),"◆",""),"") | AE14: =IF(AND($D14="Hito",ISNUMBER($K14)),IF(AND($K14>=AE$7,$K14<AE$7+7),"◆",""),"") | AF14: =IF(AND($D14="Hito",ISNUMBER($K14)),IF(AND($K14>=AF$7,$K14<AF$7+7),"◆",""),"") | ... BX14: =IF(AND($D14="Hito",ISNUMBER($K14)),IF(AND($K14>=BX$7,$K14<BX$7+7),"◆",""),"")
B15: 6 | C15: Instalación | D15: Instalación | E15: Contratista | G15: 5 | I15: 15 | J15: =IF(C15="","",IF(L15<>"",L15,IF(H15<>"",H15,IF(G15<>"",IFERROR(INDEX($T$8:$T$36,MATCH(G15,$B$8:$B$36,0))+IF(D15="Hito",0,1),IF(n_FInicio="",TODAY(),n_FInicio)),IF(n_FInicio="",TODAY(),n_FInicio))))) -> 46328 | K15: =IF(C15="","",IF(M15<>"",M15,IF(D15="Hito",J15,J15+MAX(N(I15),1)-1))) -> 46342 | O15: =IF(C15="","",IF(N15<>"",N15,IF(M15<>"",1,IF(F15="",0,IF(D15="Instalación",MIN(1,IFERROR(SUMIFS('CORTES CLIENTE'!$O$20:$O$219,PRESUPUESTO!$V$7:$V$206,F15)/SUMIFS(PRESUPUESTO!$G$7:$G$206,PRESUPUESTO!$V$7:$V$206,F15),0)),IF(D15="Compra",MIN(1,IFERROR(SUMIFS('CONTROL DE MATERIALES'!$U$11:$U$210,PRESUPUESTO!$V$7:$V$206,F15)/SUMIFS('CONTROL DE MATERIALES'!$V$11:$V$210,PRESUPUESTO!$V$7:$V$206,F15),0)),0)))))) -> 0 | P15: =IF(C15="","",IF(D15="Hito",IF(O15>=1,"Cumplido",IF(TODAY()>K15,"Vencido","Pendiente")),IF(O15>=1,"Terminada",IF(TODAY()>K15,"Atrasada",IF(OR(O15>0,L15<>""),"En curso",IF(TODAY()>=J15,"Debe iniciar","Por iniciar")))))) -> Por iniciar | Q15: =IF(OR(C15="",N(O15)>=1),"",IF(TODAY()>K15,TODAY()-K15,0)) -> 0 | R15: =COUNTIF($D$8:D15,"Fase") -> 2 | S15: =IF(C15="","",J15) -> 46328 | T15: =IF(C15="","",K15) -> 46342 | U15: =IF(C15="","",MAX(N(I15),1)) -> 15 | V15: =IF(C15="","",U15*N(O15)) -> 0 | W15: =P15 -> Por iniciar | X15: =IF(Q15="","",N(Q15)) -> 0 | Y15: =IF(AND($D15="Hito",ISNUMBER($K15)),IF(AND($K15>=Y$7,$K15<Y$7+7),"◆",""),"") | Z15: =IF(AND($D15="Hito",ISNUMBER($K15)),IF(AND($K15>=Z$7,$K15<Z$7+7),"◆",""),"") | AA15: =IF(AND($D15="Hito",ISNUMBER($K15)),IF(AND($K15>=AA$7,$K15<AA$7+7),"◆",""),"") | AB15: =IF(AND($D15="Hito",ISNUMBER($K15)),IF(AND($K15>=AB$7,$K15<AB$7+7),"◆",""),"") | AC15: =IF(AND($D15="Hito",ISNUMBER($K15)),IF(AND($K15>=AC$7,$K15<AC$7+7),"◆",""),"") | AD15: =IF(AND($D15="Hito",ISNUMBER($K15)),IF(AND($K15>=AD$7,$K15<AD$7+7),"◆",""),"") | AE15: =IF(AND($D15="Hito",ISNUMBER($K15)),IF(AND($K15>=AE$7,$K15<AE$7+7),"◆",""),"") | AF15: =IF(AND($D15="Hito",ISNUMBER($K15)),IF(AND($K15>=AF$7,$K15<AF$7+7),"◆",""),"") | ... BX15: =IF(AND($D15="Hito",ISNUMBER($K15)),IF(AND($K15>=BX$7,$K15<BX$7+7),"◆",""),"")
B16: 7 | C16: Pruebas / certificación | D16: Pruebas | E16: Técnico | G16: 6 | I16: 3 | J16: =IF(C16="","",IF(L16<>"",L16,IF(H16<>"",H16,IF(G16<>"",IFERROR(INDEX($T$8:$T$36,MATCH(G16,$B$8:$B$36,0))+IF(D16="Hito",0,1),IF(n_FInicio="",TODAY(),n_FInicio)),IF(n_FInicio="",TODAY(),n_FInicio))))) -> 46343 | K16: =IF(C16="","",IF(M16<>"",M16,IF(D16="Hito",J16,J16+MAX(N(I16),1)-1))) -> 46345 | O16: =IF(C16="","",IF(N16<>"",N16,IF(M16<>"",1,IF(F16="",0,IF(D16="Instalación",MIN(1,IFERROR(SUMIFS('CORTES CLIENTE'!$O$20:$O$219,PRESUPUESTO!$V$7:$V$206,F16)/SUMIFS(PRESUPUESTO!$G$7:$G$206,PRESUPUESTO!$V$7:$V$206,F16),0)),IF(D16="Compra",MIN(1,IFERROR(SUMIFS('CONTROL DE MATERIALES'!$U$11:$U$210,PRESUPUESTO!$V$7:$V$206,F16)/SUMIFS('CONTROL DE MATERIALES'!$V$11:$V$210,PRESUPUESTO!$V$7:$V$206,F16),0)),0)))))) -> 0 | P16: =IF(C16="","",IF(D16="Hito",IF(O16>=1,"Cumplido",IF(TODAY()>K16,"Vencido","Pendiente")),IF(O16>=1,"Terminada",IF(TODAY()>K16,"Atrasada",IF(OR(O16>0,L16<>""),"En curso",IF(TODAY()>=J16,"Debe iniciar","Por iniciar")))))) -> Por iniciar | Q16: =IF(OR(C16="",N(O16)>=1),"",IF(TODAY()>K16,TODAY()-K16,0)) -> 0 | R16: =COUNTIF($D$8:D16,"Fase") -> 2 | S16: =IF(C16="","",J16) -> 46343 | T16: =IF(C16="","",K16) -> 46345 | U16: =IF(C16="","",MAX(N(I16),1)) -> 3 | V16: =IF(C16="","",U16*N(O16)) -> 0 | W16: =P16 -> Por iniciar | X16: =IF(Q16="","",N(Q16)) -> 0 | Y16: =IF(AND($D16="Hito",ISNUMBER($K16)),IF(AND($K16>=Y$7,$K16<Y$7+7),"◆",""),"") | Z16: =IF(AND($D16="Hito",ISNUMBER($K16)),IF(AND($K16>=Z$7,$K16<Z$7+7),"◆",""),"") | AA16: =IF(AND($D16="Hito",ISNUMBER($K16)),IF(AND($K16>=AA$7,$K16<AA$7+7),"◆",""),"") | AB16: =IF(AND($D16="Hito",ISNUMBER($K16)),IF(AND($K16>=AB$7,$K16<AB$7+7),"◆",""),"") | AC16: =IF(AND($D16="Hito",ISNUMBER($K16)),IF(AND($K16>=AC$7,$K16<AC$7+7),"◆",""),"") | AD16: =IF(AND($D16="Hito",ISNUMBER($K16)),IF(AND($K16>=AD$7,$K16<AD$7+7),"◆",""),"") | AE16: =IF(AND($D16="Hito",ISNUMBER($K16)),IF(AND($K16>=AE$7,$K16<AE$7+7),"◆",""),"") | AF16: =IF(AND($D16="Hito",ISNUMBER($K16)),IF(AND($K16>=AF$7,$K16<AF$7+7),"◆",""),"") | ... BX16: =IF(AND($D16="Hito",ISNUMBER($K16)),IF(AND($K16>=BX$7,$K16<BX$7+7),"◆",""),"")
J17: =IF(C17="","",IF(L17<>"",L17,IF(H17<>"",H17,IF(G17<>"",IFERROR(INDEX($T$8:$T$36,MATCH(G17,$B$8:$B$36,0))+IF(D17="Hito",0,1),IF(n_FInicio="",TODAY(),n_FInicio)),IF(n_FInicio="",TODAY(),n_FInicio))))) | K17: =IF(C17="","",IF(M17<>"",M17,IF(D17="Hito",J17,J17+MAX(N(I17),1)-1))) | O17: =IF(C17="","",IF(N17<>"",N17,IF(M17<>"",1,IF(F17="",0,IF(D17="Instalación",MIN(1,IFERROR(SUMIFS('CORTES CLIENTE'!$O$20:$O$219,PRESUPUESTO!$V$7:$V$206,F17)/SUMIFS(PRESUPUESTO!$G$7:$G$206,PRESUPUESTO!$V$7:$V$206,F17),0)),IF(D17="Compra",MIN(1,IFERROR(SUMIFS('CONTROL DE MATERIALES'!$U$11:$U$210,PRESUPUESTO!$V$7:$V$206,F17)/SUMIFS('CONTROL DE MATERIALES'!$V$11:$V$210,PRESUPUESTO!$V$7:$V$206,F17),0)),0)))))) | P17: =IF(C17="","",IF(D17="Hito",IF(O17>=1,"Cumplido",IF(TODAY()>K17,"Vencido","Pendiente")),IF(O17>=1,"Terminada",IF(TODAY()>K17,"Atrasada",IF(OR(O17>0,L17<>""),"En curso",IF(TODAY()>=J17,"Debe iniciar","Por iniciar")))))) | Q17: =IF(OR(C17="",N(O17)>=1),"",IF(TODAY()>K17,TODAY()-K17,0)) | R17: =COUNTIF($D$8:D17,"Fase") -> 2 | S17: =IF(C17="","",J17) | T17: =IF(C17="","",K17) | U17: =IF(C17="","",MAX(N(I17),1)) | V17: =IF(C17="","",U17*N(O17)) | W17: =P17 | X17: =IF(Q17="","",N(Q17)) | Y17: =IF(AND($D17="Hito",ISNUMBER($K17)),IF(AND($K17>=Y$7,$K17<Y$7+7),"◆",""),"") | Z17: =IF(AND($D17="Hito",ISNUMBER($K17)),IF(AND($K17>=Z$7,$K17<Z$7+7),"◆",""),"") | AA17: =IF(AND($D17="Hito",ISNUMBER($K17)),IF(AND($K17>=AA$7,$K17<AA$7+7),"◆",""),"") | AB17: =IF(AND($D17="Hito",ISNUMBER($K17)),IF(AND($K17>=AB$7,$K17<AB$7+7),"◆",""),"") | AC17: =IF(AND($D17="Hito",ISNUMBER($K17)),IF(AND($K17>=AC$7,$K17<AC$7+7),"◆",""),"") | AD17: =IF(AND($D17="Hito",ISNUMBER($K17)),IF(AND($K17>=AD$7,$K17<AD$7+7),"◆",""),"") | AE17: =IF(AND($D17="Hito",ISNUMBER($K17)),IF(AND($K17>=AE$7,$K17<AE$7+7),"◆",""),"") | AF17: =IF(AND($D17="Hito",ISNUMBER($K17)),IF(AND($K17>=AF$7,$K17<AF$7+7),"◆",""),"") | ... BX17: =IF(AND($D17="Hito",ISNUMBER($K17)),IF(AND($K17>=BX$7,$K17<BX$7+7),"◆",""),"")
J18: =IF(C18="","",IF(L18<>"",L18,IF(H18<>"",H18,IF(G18<>"",IFERROR(INDEX($T$8:$T$36,MATCH(G18,$B$8:$B$36,0))+IF(D18="Hito",0,1),IF(n_FInicio="",TODAY(),n_FInicio)),IF(n_FInicio="",TODAY(),n_FInicio))))) | K18: =IF(C18="","",IF(M18<>"",M18,IF(D18="Hito",J18,J18+MAX(N(I18),1)-1))) | O18: =IF(C18="","",IF(N18<>"",N18,IF(M18<>"",1,IF(F18="",0,IF(D18="Instalación",MIN(1,IFERROR(SUMIFS('CORTES CLIENTE'!$O$20:$O$219,PRESUPUESTO!$V$7:$V$206,F18)/SUMIFS(PRESUPUESTO!$G$7:$G$206,PRESUPUESTO!$V$7:$V$206,F18),0)),IF(D18="Compra",MIN(1,IFERROR(SUMIFS('CONTROL DE MATERIALES'!$U$11:$U$210,PRESUPUESTO!$V$7:$V$206,F18)/SUMIFS('CONTROL DE MATERIALES'!$V$11:$V$210,PRESUPUESTO!$V$7:$V$206,F18),0)),0)))))) | P18: =IF(C18="","",IF(D18="Hito",IF(O18>=1,"Cumplido",IF(TODAY()>K18,"Vencido","Pendiente")),IF(O18>=1,"Terminada",IF(TODAY()>K18,"Atrasada",IF(OR(O18>0,L18<>""),"En curso",IF(TODAY()>=J18,"Debe iniciar","Por iniciar")))))) | Q18: =IF(OR(C18="",N(O18)>=1),"",IF(TODAY()>K18,TODAY()-K18,0)) | R18: =COUNTIF($D$8:D18,"Fase") -> 2 | S18: =IF(C18="","",J18) | T18: =IF(C18="","",K18) | U18: =IF(C18="","",MAX(N(I18),1)) | V18: =IF(C18="","",U18*N(O18)) | W18: =P18 | X18: =IF(Q18="","",N(Q18)) | Y18: =IF(AND($D18="Hito",ISNUMBER($K18)),IF(AND($K18>=Y$7,$K18<Y$7+7),"◆",""),"") | Z18: =IF(AND($D18="Hito",ISNUMBER($K18)),IF(AND($K18>=Z$7,$K18<Z$7+7),"◆",""),"") | AA18: =IF(AND($D18="Hito",ISNUMBER($K18)),IF(AND($K18>=AA$7,$K18<AA$7+7),"◆",""),"") | AB18: =IF(AND($D18="Hito",ISNUMBER($K18)),IF(AND($K18>=AB$7,$K18<AB$7+7),"◆",""),"") | AC18: =IF(AND($D18="Hito",ISNUMBER($K18)),IF(AND($K18>=AC$7,$K18<AC$7+7),"◆",""),"") | AD18: =IF(AND($D18="Hito",ISNUMBER($K18)),IF(AND($K18>=AD$7,$K18<AD$7+7),"◆",""),"") | AE18: =IF(AND($D18="Hito",ISNUMBER($K18)),IF(AND($K18>=AE$7,$K18<AE$7+7),"◆",""),"") | AF18: =IF(AND($D18="Hito",ISNUMBER($K18)),IF(AND($K18>=AF$7,$K18<AF$7+7),"◆",""),"") | ... BX18: =IF(AND($D18="Hito",ISNUMBER($K18)),IF(AND($K18>=BX$7,$K18<BX$7+7),"◆",""),"")
B19: ="F"&R19 -> F3 | C19: FRENTE 2 (cambie el nombre) | D19: Fase | I19: =IF(OR(J19="",K19=""),"",K19-J19+1) -> 28 | J19: =IFERROR(1/(1/_xlfn.MINIFS($S$8:$S$36,$R$8:$R$36,R19)),"") -> 46318 | K19: =IFERROR(1/(1/_xlfn.MAXIFS($T$8:$T$36,$R$8:$R$36,R19)),"") -> 46345 | O19: =IFERROR(SUMIFS($V$8:$V$36,$R$8:$R$36,R19)/SUMIFS($U$8:$U$36,$R$8:$R$36,R19),"") -> 0 | P19: =IF(COUNTIFS($R$8:$R$36,R19,$U$8:$U$36,">0")=0,"",IF(COUNTIFS($R$8:$R$36,R19,$W$8:$W$36,"Atrasada")+COUNTIFS($R$8:$R$36,R19,$W$8:$W$36,"Vencido")>0,"Con atraso",IF(N(O19)>=1,"Terminada",IF(N(O19)>0,"En curso","Por iniciar")))) -> Por iniciar | Q19: =IF(N(_xlfn.MAXIFS($X$8:$X$36,$R$8:$R$36,R19))>0,_xlfn.MAXIFS($X$8:$X$36,$R$8:$R$36,R19),"") | R19: =COUNTIF($D$8:D19,"Fase") -> 3
B20: 8 | C20: Compra materiales — lote 1 | D20: Compra | E20: Compras | G20: 4 | I20: 10 | J20: =IF(C20="","",IF(L20<>"",L20,IF(H20<>"",H20,IF(G20<>"",IFERROR(INDEX($T$8:$T$36,MATCH(G20,$B$8:$B$36,0))+IF(D20="Hito",0,1),IF(n_FInicio="",TODAY(),n_FInicio)),IF(n_FInicio="",TODAY(),n_FInicio))))) -> 46318 | K20: =IF(C20="","",IF(M20<>"",M20,IF(D20="Hito",J20,J20+MAX(N(I20),1)-1))) -> 46327 | O20: =IF(C20="","",IF(N20<>"",N20,IF(M20<>"",1,IF(F20="",0,IF(D20="Instalación",MIN(1,IFERROR(SUMIFS('CORTES CLIENTE'!$O$20:$O$219,PRESUPUESTO!$V$7:$V$206,F20)/SUMIFS(PRESUPUESTO!$G$7:$G$206,PRESUPUESTO!$V$7:$V$206,F20),0)),IF(D20="Compra",MIN(1,IFERROR(SUMIFS('CONTROL DE MATERIALES'!$U$11:$U$210,PRESUPUESTO!$V$7:$V$206,F20)/SUMIFS('CONTROL DE MATERIALES'!$V$11:$V$210,PRESUPUESTO!$V$7:$V$206,F20),0)),0)))))) -> 0 | P20: =IF(C20="","",IF(D20="Hito",IF(O20>=1,"Cumplido",IF(TODAY()>K20,"Vencido","Pendiente")),IF(O20>=1,"Terminada",IF(TODAY()>K20,"Atrasada",IF(OR(O20>0,L20<>""),"En curso",IF(TODAY()>=J20,"Debe iniciar","Por iniciar")))))) -> Por iniciar | Q20: =IF(OR(C20="",N(O20)>=1),"",IF(TODAY()>K20,TODAY()-K20,0)) -> 0 | R20: =COUNTIF($D$8:D20,"Fase") -> 3 | S20: =IF(C20="","",J20) -> 46318 | T20: =IF(C20="","",K20) -> 46327 | U20: =IF(C20="","",MAX(N(I20),1)) -> 10 | V20: =IF(C20="","",U20*N(O20)) -> 0 | W20: =P20 -> Por iniciar | X20: =IF(Q20="","",N(Q20)) -> 0 | Y20: =IF(AND($D20="Hito",ISNUMBER($K20)),IF(AND($K20>=Y$7,$K20<Y$7+7),"◆",""),"") | Z20: =IF(AND($D20="Hito",ISNUMBER($K20)),IF(AND($K20>=Z$7,$K20<Z$7+7),"◆",""),"") | AA20: =IF(AND($D20="Hito",ISNUMBER($K20)),IF(AND($K20>=AA$7,$K20<AA$7+7),"◆",""),"") | AB20: =IF(AND($D20="Hito",ISNUMBER($K20)),IF(AND($K20>=AB$7,$K20<AB$7+7),"◆",""),"") | AC20: =IF(AND($D20="Hito",ISNUMBER($K20)),IF(AND($K20>=AC$7,$K20<AC$7+7),"◆",""),"") | AD20: =IF(AND($D20="Hito",ISNUMBER($K20)),IF(AND($K20>=AD$7,$K20<AD$7+7),"◆",""),"") | AE20: =IF(AND($D20="Hito",ISNUMBER($K20)),IF(AND($K20>=AE$7,$K20<AE$7+7),"◆",""),"") | AF20: =IF(AND($D20="Hito",ISNUMBER($K20)),IF(AND($K20>=AF$7,$K20<AF$7+7),"◆",""),"") | ... BX20: =IF(AND($D20="Hito",ISNUMBER($K20)),IF(AND($K20>=BX$7,$K20<BX$7+7),"◆",""),"")
B21: 9 | C21: Instalación | D21: Instalación | E21: Contratista | G21: 8 | I21: 15 | J21: =IF(C21="","",IF(L21<>"",L21,IF(H21<>"",H21,IF(G21<>"",IFERROR(INDEX($T$8:$T$36,MATCH(G21,$B$8:$B$36,0))+IF(D21="Hito",0,1),IF(n_FInicio="",TODAY(),n_FInicio)),IF(n_FInicio="",TODAY(),n_FInicio))))) -> 46328 | K21: =IF(C21="","",IF(M21<>"",M21,IF(D21="Hito",J21,J21+MAX(N(I21),1)-1))) -> 46342 | O21: =IF(C21="","",IF(N21<>"",N21,IF(M21<>"",1,IF(F21="",0,IF(D21="Instalación",MIN(1,IFERROR(SUMIFS('CORTES CLIENTE'!$O$20:$O$219,PRESUPUESTO!$V$7:$V$206,F21)/SUMIFS(PRESUPUESTO!$G$7:$G$206,PRESUPUESTO!$V$7:$V$206,F21),0)),IF(D21="Compra",MIN(1,IFERROR(SUMIFS('CONTROL DE MATERIALES'!$U$11:$U$210,PRESUPUESTO!$V$7:$V$206,F21)/SUMIFS('CONTROL DE MATERIALES'!$V$11:$V$210,PRESUPUESTO!$V$7:$V$206,F21),0)),0)))))) -> 0 | P21: =IF(C21="","",IF(D21="Hito",IF(O21>=1,"Cumplido",IF(TODAY()>K21,"Vencido","Pendiente")),IF(O21>=1,"Terminada",IF(TODAY()>K21,"Atrasada",IF(OR(O21>0,L21<>""),"En curso",IF(TODAY()>=J21,"Debe iniciar","Por iniciar")))))) -> Por iniciar | Q21: =IF(OR(C21="",N(O21)>=1),"",IF(TODAY()>K21,TODAY()-K21,0)) -> 0 | R21: =COUNTIF($D$8:D21,"Fase") -> 3 | S21: =IF(C21="","",J21) -> 46328 | T21: =IF(C21="","",K21) -> 46342 | U21: =IF(C21="","",MAX(N(I21),1)) -> 15 | V21: =IF(C21="","",U21*N(O21)) -> 0 | W21: =P21 -> Por iniciar | X21: =IF(Q21="","",N(Q21)) -> 0 | Y21: =IF(AND($D21="Hito",ISNUMBER($K21)),IF(AND($K21>=Y$7,$K21<Y$7+7),"◆",""),"") | Z21: =IF(AND($D21="Hito",ISNUMBER($K21)),IF(AND($K21>=Z$7,$K21<Z$7+7),"◆",""),"") | AA21: =IF(AND($D21="Hito",ISNUMBER($K21)),IF(AND($K21>=AA$7,$K21<AA$7+7),"◆",""),"") | AB21: =IF(AND($D21="Hito",ISNUMBER($K21)),IF(AND($K21>=AB$7,$K21<AB$7+7),"◆",""),"") | AC21: =IF(AND($D21="Hito",ISNUMBER($K21)),IF(AND($K21>=AC$7,$K21<AC$7+7),"◆",""),"") | AD21: =IF(AND($D21="Hito",ISNUMBER($K21)),IF(AND($K21>=AD$7,$K21<AD$7+7),"◆",""),"") | AE21: =IF(AND($D21="Hito",ISNUMBER($K21)),IF(AND($K21>=AE$7,$K21<AE$7+7),"◆",""),"") | AF21: =IF(AND($D21="Hito",ISNUMBER($K21)),IF(AND($K21>=AF$7,$K21<AF$7+7),"◆",""),"") | ... BX21: =IF(AND($D21="Hito",ISNUMBER($K21)),IF(AND($K21>=BX$7,$K21<BX$7+7),"◆",""),"")
B22: 10 | C22: Pruebas / certificación | D22: Pruebas | E22: Técnico | G22: 9 | I22: 3 | J22: =IF(C22="","",IF(L22<>"",L22,IF(H22<>"",H22,IF(G22<>"",IFERROR(INDEX($T$8:$T$36,MATCH(G22,$B$8:$B$36,0))+IF(D22="Hito",0,1),IF(n_FInicio="",TODAY(),n_FInicio)),IF(n_FInicio="",TODAY(),n_FInicio))))) -> 46343 | K22: =IF(C22="","",IF(M22<>"",M22,IF(D22="Hito",J22,J22+MAX(N(I22),1)-1))) -> 46345 | O22: =IF(C22="","",IF(N22<>"",N22,IF(M22<>"",1,IF(F22="",0,IF(D22="Instalación",MIN(1,IFERROR(SUMIFS('CORTES CLIENTE'!$O$20:$O$219,PRESUPUESTO!$V$7:$V$206,F22)/SUMIFS(PRESUPUESTO!$G$7:$G$206,PRESUPUESTO!$V$7:$V$206,F22),0)),IF(D22="Compra",MIN(1,IFERROR(SUMIFS('CONTROL DE MATERIALES'!$U$11:$U$210,PRESUPUESTO!$V$7:$V$206,F22)/SUMIFS('CONTROL DE MATERIALES'!$V$11:$V$210,PRESUPUESTO!$V$7:$V$206,F22),0)),0)))))) -> 0 | P22: =IF(C22="","",IF(D22="Hito",IF(O22>=1,"Cumplido",IF(TODAY()>K22,"Vencido","Pendiente")),IF(O22>=1,"Terminada",IF(TODAY()>K22,"Atrasada",IF(OR(O22>0,L22<>""),"En curso",IF(TODAY()>=J22,"Debe iniciar","Por iniciar")))))) -> Por iniciar | Q22: =IF(OR(C22="",N(O22)>=1),"",IF(TODAY()>K22,TODAY()-K22,0)) -> 0 | R22: =COUNTIF($D$8:D22,"Fase") -> 3 | S22: =IF(C22="","",J22) -> 46343 | T22: =IF(C22="","",K22) -> 46345 | U22: =IF(C22="","",MAX(N(I22),1)) -> 3 | V22: =IF(C22="","",U22*N(O22)) -> 0 | W22: =P22 -> Por iniciar | X22: =IF(Q22="","",N(Q22)) -> 0 | Y22: =IF(AND($D22="Hito",ISNUMBER($K22)),IF(AND($K22>=Y$7,$K22<Y$7+7),"◆",""),"") | Z22: =IF(AND($D22="Hito",ISNUMBER($K22)),IF(AND($K22>=Z$7,$K22<Z$7+7),"◆",""),"") | AA22: =IF(AND($D22="Hito",ISNUMBER($K22)),IF(AND($K22>=AA$7,$K22<AA$7+7),"◆",""),"") | AB22: =IF(AND($D22="Hito",ISNUMBER($K22)),IF(AND($K22>=AB$7,$K22<AB$7+7),"◆",""),"") | AC22: =IF(AND($D22="Hito",ISNUMBER($K22)),IF(AND($K22>=AC$7,$K22<AC$7+7),"◆",""),"") | AD22: =IF(AND($D22="Hito",ISNUMBER($K22)),IF(AND($K22>=AD$7,$K22<AD$7+7),"◆",""),"") | AE22: =IF(AND($D22="Hito",ISNUMBER($K22)),IF(AND($K22>=AE$7,$K22<AE$7+7),"◆",""),"") | AF22: =IF(AND($D22="Hito",ISNUMBER($K22)),IF(AND($K22>=AF$7,$K22<AF$7+7),"◆",""),"") | ... BX22: =IF(AND($D22="Hito",ISNUMBER($K22)),IF(AND($K22>=BX$7,$K22<BX$7+7),"◆",""),"")
J23: =IF(C23="","",IF(L23<>"",L23,IF(H23<>"",H23,IF(G23<>"",IFERROR(INDEX($T$8:$T$36,MATCH(G23,$B$8:$B$36,0))+IF(D23="Hito",0,1),IF(n_FInicio="",TODAY(),n_FInicio)),IF(n_FInicio="",TODAY(),n_FInicio))))) | K23: =IF(C23="","",IF(M23<>"",M23,IF(D23="Hito",J23,J23+MAX(N(I23),1)-1))) | O23: =IF(C23="","",IF(N23<>"",N23,IF(M23<>"",1,IF(F23="",0,IF(D23="Instalación",MIN(1,IFERROR(SUMIFS('CORTES CLIENTE'!$O$20:$O$219,PRESUPUESTO!$V$7:$V$206,F23)/SUMIFS(PRESUPUESTO!$G$7:$G$206,PRESUPUESTO!$V$7:$V$206,F23),0)),IF(D23="Compra",MIN(1,IFERROR(SUMIFS('CONTROL DE MATERIALES'!$U$11:$U$210,PRESUPUESTO!$V$7:$V$206,F23)/SUMIFS('CONTROL DE MATERIALES'!$V$11:$V$210,PRESUPUESTO!$V$7:$V$206,F23),0)),0)))))) | P23: =IF(C23="","",IF(D23="Hito",IF(O23>=1,"Cumplido",IF(TODAY()>K23,"Vencido","Pendiente")),IF(O23>=1,"Terminada",IF(TODAY()>K23,"Atrasada",IF(OR(O23>0,L23<>""),"En curso",IF(TODAY()>=J23,"Debe iniciar","Por iniciar")))))) | Q23: =IF(OR(C23="",N(O23)>=1),"",IF(TODAY()>K23,TODAY()-K23,0)) | R23: =COUNTIF($D$8:D23,"Fase") -> 3 | S23: =IF(C23="","",J23) | T23: =IF(C23="","",K23) | U23: =IF(C23="","",MAX(N(I23),1)) | V23: =IF(C23="","",U23*N(O23)) | W23: =P23 | X23: =IF(Q23="","",N(Q23)) | Y23: =IF(AND($D23="Hito",ISNUMBER($K23)),IF(AND($K23>=Y$7,$K23<Y$7+7),"◆",""),"") | Z23: =IF(AND($D23="Hito",ISNUMBER($K23)),IF(AND($K23>=Z$7,$K23<Z$7+7),"◆",""),"") | AA23: =IF(AND($D23="Hito",ISNUMBER($K23)),IF(AND($K23>=AA$7,$K23<AA$7+7),"◆",""),"") | AB23: =IF(AND($D23="Hito",ISNUMBER($K23)),IF(AND($K23>=AB$7,$K23<AB$7+7),"◆",""),"") | AC23: =IF(AND($D23="Hito",ISNUMBER($K23)),IF(AND($K23>=AC$7,$K23<AC$7+7),"◆",""),"") | AD23: =IF(AND($D23="Hito",ISNUMBER($K23)),IF(AND($K23>=AD$7,$K23<AD$7+7),"◆",""),"") | AE23: =IF(AND($D23="Hito",ISNUMBER($K23)),IF(AND($K23>=AE$7,$K23<AE$7+7),"◆",""),"") | AF23: =IF(AND($D23="Hito",ISNUMBER($K23)),IF(AND($K23>=AF$7,$K23<AF$7+7),"◆",""),"") | ... BX23: =IF(AND($D23="Hito",ISNUMBER($K23)),IF(AND($K23>=BX$7,$K23<BX$7+7),"◆",""),"")
J24: =IF(C24="","",IF(L24<>"",L24,IF(H24<>"",H24,IF(G24<>"",IFERROR(INDEX($T$8:$T$36,MATCH(G24,$B$8:$B$36,0))+IF(D24="Hito",0,1),IF(n_FInicio="",TODAY(),n_FInicio)),IF(n_FInicio="",TODAY(),n_FInicio))))) | K24: =IF(C24="","",IF(M24<>"",M24,IF(D24="Hito",J24,J24+MAX(N(I24),1)-1))) | O24: =IF(C24="","",IF(N24<>"",N24,IF(M24<>"",1,IF(F24="",0,IF(D24="Instalación",MIN(1,IFERROR(SUMIFS('CORTES CLIENTE'!$O$20:$O$219,PRESUPUESTO!$V$7:$V$206,F24)/SUMIFS(PRESUPUESTO!$G$7:$G$206,PRESUPUESTO!$V$7:$V$206,F24),0)),IF(D24="Compra",MIN(1,IFERROR(SUMIFS('CONTROL DE MATERIALES'!$U$11:$U$210,PRESUPUESTO!$V$7:$V$206,F24)/SUMIFS('CONTROL DE MATERIALES'!$V$11:$V$210,PRESUPUESTO!$V$7:$V$206,F24),0)),0)))))) | P24: =IF(C24="","",IF(D24="Hito",IF(O24>=1,"Cumplido",IF(TODAY()>K24,"Vencido","Pendiente")),IF(O24>=1,"Terminada",IF(TODAY()>K24,"Atrasada",IF(OR(O24>0,L24<>""),"En curso",IF(TODAY()>=J24,"Debe iniciar","Por iniciar")))))) | Q24: =IF(OR(C24="",N(O24)>=1),"",IF(TODAY()>K24,TODAY()-K24,0)) | R24: =COUNTIF($D$8:D24,"Fase") -> 3 | S24: =IF(C24="","",J24) | T24: =IF(C24="","",K24) | U24: =IF(C24="","",MAX(N(I24),1)) | V24: =IF(C24="","",U24*N(O24)) | W24: =P24 | X24: =IF(Q24="","",N(Q24)) | Y24: =IF(AND($D24="Hito",ISNUMBER($K24)),IF(AND($K24>=Y$7,$K24<Y$7+7),"◆",""),"") | Z24: =IF(AND($D24="Hito",ISNUMBER($K24)),IF(AND($K24>=Z$7,$K24<Z$7+7),"◆",""),"") | AA24: =IF(AND($D24="Hito",ISNUMBER($K24)),IF(AND($K24>=AA$7,$K24<AA$7+7),"◆",""),"") | AB24: =IF(AND($D24="Hito",ISNUMBER($K24)),IF(AND($K24>=AB$7,$K24<AB$7+7),"◆",""),"") | AC24: =IF(AND($D24="Hito",ISNUMBER($K24)),IF(AND($K24>=AC$7,$K24<AC$7+7),"◆",""),"") | AD24: =IF(AND($D24="Hito",ISNUMBER($K24)),IF(AND($K24>=AD$7,$K24<AD$7+7),"◆",""),"") | AE24: =IF(AND($D24="Hito",ISNUMBER($K24)),IF(AND($K24>=AE$7,$K24<AE$7+7),"◆",""),"") | AF24: =IF(AND($D24="Hito",ISNUMBER($K24)),IF(AND($K24>=AF$7,$K24<AF$7+7),"◆",""),"") | ... BX24: =IF(AND($D24="Hito",ISNUMBER($K24)),IF(AND($K24>=BX$7,$K24<BX$7+7),"◆",""),"")
B25: ="F"&R25 -> F4 | C25: CORTES Y FACTURACIÓN | D25: Fase | I25: =IF(OR(J25="",K25=""),"",K25-J25+1) -> 1 | J25: =IFERROR(1/(1/_xlfn.MINIFS($S$8:$S$36,$R$8:$R$36,R25)),"") -> 46312 | K25: =IFERROR(1/(1/_xlfn.MAXIFS($T$8:$T$36,$R$8:$R$36,R25)),"") -> 46312 | O25: =IFERROR(SUMIFS($V$8:$V$36,$R$8:$R$36,R25)/SUMIFS($U$8:$U$36,$R$8:$R$36,R25),"") -> 0 | P25: =IF(COUNTIFS($R$8:$R$36,R25,$U$8:$U$36,">0")=0,"",IF(COUNTIFS($R$8:$R$36,R25,$W$8:$W$36,"Atrasada")+COUNTIFS($R$8:$R$36,R25,$W$8:$W$36,"Vencido")>0,"Con atraso",IF(N(O25)>=1,"Terminada",IF(N(O25)>0,"En curso","Por iniciar")))) -> Por iniciar | Q25: =IF(N(_xlfn.MAXIFS($X$8:$X$36,$R$8:$R$36,R25))>0,_xlfn.MAXIFS($X$8:$X$36,$R$8:$R$36,R25),"") | R25: =COUNTIF($D$8:D25,"Fase") -> 4
B26: 11 | C26: Acta de corte 1 al cliente | D26: Hito | E26: Dir. proyectos | I26: 0 | J26: =IF(C26="","",IF(L26<>"",L26,IF(H26<>"",H26,IF(G26<>"",IFERROR(INDEX($T$8:$T$36,MATCH(G26,$B$8:$B$36,0))+IF(D26="Hito",0,1),IF(n_FInicio="",TODAY(),n_FInicio)),IF(n_FInicio="",TODAY(),n_FInicio))))) -> 46312 | K26: =IF(C26="","",IF(M26<>"",M26,IF(D26="Hito",J26,J26+MAX(N(I26),1)-1))) -> 46312 | O26: =IF(C26="","",IF(N26<>"",N26,IF(M26<>"",1,IF(F26="",0,IF(D26="Instalación",MIN(1,IFERROR(SUMIFS('CORTES CLIENTE'!$O$20:$O$219,PRESUPUESTO!$V$7:$V$206,F26)/SUMIFS(PRESUPUESTO!$G$7:$G$206,PRESUPUESTO!$V$7:$V$206,F26),0)),IF(D26="Compra",MIN(1,IFERROR(SUMIFS('CONTROL DE MATERIALES'!$U$11:$U$210,PRESUPUESTO!$V$7:$V$206,F26)/SUMIFS('CONTROL DE MATERIALES'!$V$11:$V$210,PRESUPUESTO!$V$7:$V$206,F26),0)),0)))))) -> 0 | P26: =IF(C26="","",IF(D26="Hito",IF(O26>=1,"Cumplido",IF(TODAY()>K26,"Vencido","Pendiente")),IF(O26>=1,"Terminada",IF(TODAY()>K26,"Atrasada",IF(OR(O26>0,L26<>""),"En curso",IF(TODAY()>=J26,"Debe iniciar","Por iniciar")))))) -> Pendiente | Q26: =IF(OR(C26="",N(O26)>=1),"",IF(TODAY()>K26,TODAY()-K26,0)) -> 0 | R26: =COUNTIF($D$8:D26,"Fase") -> 4 | S26: =IF(C26="","",J26) -> 46312 | T26: =IF(C26="","",K26) -> 46312 | U26: =IF(C26="","",MAX(N(I26),1)) -> 1 | V26: =IF(C26="","",U26*N(O26)) -> 0 | W26: =P26 -> Pendiente | X26: =IF(Q26="","",N(Q26)) -> 0 | Y26: =IF(AND($D26="Hito",ISNUMBER($K26)),IF(AND($K26>=Y$7,$K26<Y$7+7),"◆",""),"") -> ◆ | Z26: =IF(AND($D26="Hito",ISNUMBER($K26)),IF(AND($K26>=Z$7,$K26<Z$7+7),"◆",""),"") | AA26: =IF(AND($D26="Hito",ISNUMBER($K26)),IF(AND($K26>=AA$7,$K26<AA$7+7),"◆",""),"") | AB26: =IF(AND($D26="Hito",ISNUMBER($K26)),IF(AND($K26>=AB$7,$K26<AB$7+7),"◆",""),"") | AC26: =IF(AND($D26="Hito",ISNUMBER($K26)),IF(AND($K26>=AC$7,$K26<AC$7+7),"◆",""),"") | AD26: =IF(AND($D26="Hito",ISNUMBER($K26)),IF(AND($K26>=AD$7,$K26<AD$7+7),"◆",""),"") | AE26: =IF(AND($D26="Hito",ISNUMBER($K26)),IF(AND($K26>=AE$7,$K26<AE$7+7),"◆",""),"") | AF26: =IF(AND($D26="Hito",ISNUMBER($K26)),IF(AND($K26>=AF$7,$K26<AF$7+7),"◆",""),"") | ... BX26: =IF(AND($D26="Hito",ISNUMBER($K26)),IF(AND($K26>=BX$7,$K26<BX$7+7),"◆",""),"")
J27: =IF(C27="","",IF(L27<>"",L27,IF(H27<>"",H27,IF(G27<>"",IFERROR(INDEX($T$8:$T$36,MATCH(G27,$B$8:$B$36,0))+IF(D27="Hito",0,1),IF(n_FInicio="",TODAY(),n_FInicio)),IF(n_FInicio="",TODAY(),n_FInicio))))) | K27: =IF(C27="","",IF(M27<>"",M27,IF(D27="Hito",J27,J27+MAX(N(I27),1)-1))) | O27: =IF(C27="","",IF(N27<>"",N27,IF(M27<>"",1,IF(F27="",0,IF(D27="Instalación",MIN(1,IFERROR(SUMIFS('CORTES CLIENTE'!$O$20:$O$219,PRESUPUESTO!$V$7:$V$206,F27)/SUMIFS(PRESUPUESTO!$G$7:$G$206,PRESUPUESTO!$V$7:$V$206,F27),0)),IF(D27="Compra",MIN(1,IFERROR(SUMIFS('CONTROL DE MATERIALES'!$U$11:$U$210,PRESUPUESTO!$V$7:$V$206,F27)/SUMIFS('CONTROL DE MATERIALES'!$V$11:$V$210,PRESUPUESTO!$V$7:$V$206,F27),0)),0)))))) | P27: =IF(C27="","",IF(D27="Hito",IF(O27>=1,"Cumplido",IF(TODAY()>K27,"Vencido","Pendiente")),IF(O27>=1,"Terminada",IF(TODAY()>K27,"Atrasada",IF(OR(O27>0,L27<>""),"En curso",IF(TODAY()>=J27,"Debe iniciar","Por iniciar")))))) | Q27: =IF(OR(C27="",N(O27)>=1),"",IF(TODAY()>K27,TODAY()-K27,0)) | R27: =COUNTIF($D$8:D27,"Fase") -> 4 | S27: =IF(C27="","",J27) | T27: =IF(C27="","",K27) | U27: =IF(C27="","",MAX(N(I27),1)) | V27: =IF(C27="","",U27*N(O27)) | W27: =P27 | X27: =IF(Q27="","",N(Q27)) | Y27: =IF(AND($D27="Hito",ISNUMBER($K27)),IF(AND($K27>=Y$7,$K27<Y$7+7),"◆",""),"") | Z27: =IF(AND($D27="Hito",ISNUMBER($K27)),IF(AND($K27>=Z$7,$K27<Z$7+7),"◆",""),"") | AA27: =IF(AND($D27="Hito",ISNUMBER($K27)),IF(AND($K27>=AA$7,$K27<AA$7+7),"◆",""),"") | AB27: =IF(AND($D27="Hito",ISNUMBER($K27)),IF(AND($K27>=AB$7,$K27<AB$7+7),"◆",""),"") | AC27: =IF(AND($D27="Hito",ISNUMBER($K27)),IF(AND($K27>=AC$7,$K27<AC$7+7),"◆",""),"") | AD27: =IF(AND($D27="Hito",ISNUMBER($K27)),IF(AND($K27>=AD$7,$K27<AD$7+7),"◆",""),"") | AE27: =IF(AND($D27="Hito",ISNUMBER($K27)),IF(AND($K27>=AE$7,$K27<AE$7+7),"◆",""),"") | AF27: =IF(AND($D27="Hito",ISNUMBER($K27)),IF(AND($K27>=AF$7,$K27<AF$7+7),"◆",""),"") | ... BX27: =IF(AND($D27="Hito",ISNUMBER($K27)),IF(AND($K27>=BX$7,$K27<BX$7+7),"◆",""),"")
B28: ="F"&R28 -> F5 | C28: CIERRE Y ENTREGA | D28: Fase | I28: =IF(OR(J28="",K28=""),"",K28-J28+1) -> 3 | J28: =IFERROR(1/(1/_xlfn.MINIFS($S$8:$S$36,$R$8:$R$36,R28)),"") -> 46346 | K28: =IFERROR(1/(1/_xlfn.MAXIFS($T$8:$T$36,$R$8:$R$36,R28)),"") -> 46348 | O28: =IFERROR(SUMIFS($V$8:$V$36,$R$8:$R$36,R28)/SUMIFS($U$8:$U$36,$R$8:$R$36,R28),"") -> 0 | P28: =IF(COUNTIFS($R$8:$R$36,R28,$U$8:$U$36,">0")=0,"",IF(COUNTIFS($R$8:$R$36,R28,$W$8:$W$36,"Atrasada")+COUNTIFS($R$8:$R$36,R28,$W$8:$W$36,"Vencido")>0,"Con atraso",IF(N(O28)>=1,"Terminada",IF(N(O28)>0,"En curso","Por iniciar")))) -> Por iniciar | Q28: =IF(N(_xlfn.MAXIFS($X$8:$X$36,$R$8:$R$36,R28))>0,_xlfn.MAXIFS($X$8:$X$36,$R$8:$R$36,R28),"") | R28: =COUNTIF($D$8:D28,"Fase") -> 5
B29: 12 | C29: Pruebas integrales y capacitación al cliente | D29: Pruebas | E29: Dir. proyectos | G29: 10 | I29: 3 | J29: =IF(C29="","",IF(L29<>"",L29,IF(H29<>"",H29,IF(G29<>"",IFERROR(INDEX($T$8:$T$36,MATCH(G29,$B$8:$B$36,0))+IF(D29="Hito",0,1),IF(n_FInicio="",TODAY(),n_FInicio)),IF(n_FInicio="",TODAY(),n_FInicio))))) -> 46346 | K29: =IF(C29="","",IF(M29<>"",M29,IF(D29="Hito",J29,J29+MAX(N(I29),1)-1))) -> 46348 | O29: =IF(C29="","",IF(N29<>"",N29,IF(M29<>"",1,IF(F29="",0,IF(D29="Instalación",MIN(1,IFERROR(SUMIFS('CORTES CLIENTE'!$O$20:$O$219,PRESUPUESTO!$V$7:$V$206,F29)/SUMIFS(PRESUPUESTO!$G$7:$G$206,PRESUPUESTO!$V$7:$V$206,F29),0)),IF(D29="Compra",MIN(1,IFERROR(SUMIFS('CONTROL DE MATERIALES'!$U$11:$U$210,PRESUPUESTO!$V$7:$V$206,F29)/SUMIFS('CONTROL DE MATERIALES'!$V$11:$V$210,PRESUPUESTO!$V$7:$V$206,F29),0)),0)))))) -> 0 | P29: =IF(C29="","",IF(D29="Hito",IF(O29>=1,"Cumplido",IF(TODAY()>K29,"Vencido","Pendiente")),IF(O29>=1,"Terminada",IF(TODAY()>K29,"Atrasada",IF(OR(O29>0,L29<>""),"En curso",IF(TODAY()>=J29,"Debe iniciar","Por iniciar")))))) -> Por iniciar | Q29: =IF(OR(C29="",N(O29)>=1),"",IF(TODAY()>K29,TODAY()-K29,0)) -> 0 | R29: =COUNTIF($D$8:D29,"Fase") -> 5 | S29: =IF(C29="","",J29) -> 46346 | T29: =IF(C29="","",K29) -> 46348 | U29: =IF(C29="","",MAX(N(I29),1)) -> 3 | V29: =IF(C29="","",U29*N(O29)) -> 0 | W29: =P29 -> Por iniciar | X29: =IF(Q29="","",N(Q29)) -> 0 | Y29: =IF(AND($D29="Hito",ISNUMBER($K29)),IF(AND($K29>=Y$7,$K29<Y$7+7),"◆",""),"") | Z29: =IF(AND($D29="Hito",ISNUMBER($K29)),IF(AND($K29>=Z$7,$K29<Z$7+7),"◆",""),"") | AA29: =IF(AND($D29="Hito",ISNUMBER($K29)),IF(AND($K29>=AA$7,$K29<AA$7+7),"◆",""),"") | AB29: =IF(AND($D29="Hito",ISNUMBER($K29)),IF(AND($K29>=AB$7,$K29<AB$7+7),"◆",""),"") | AC29: =IF(AND($D29="Hito",ISNUMBER($K29)),IF(AND($K29>=AC$7,$K29<AC$7+7),"◆",""),"") | AD29: =IF(AND($D29="Hito",ISNUMBER($K29)),IF(AND($K29>=AD$7,$K29<AD$7+7),"◆",""),"") | AE29: =IF(AND($D29="Hito",ISNUMBER($K29)),IF(AND($K29>=AE$7,$K29<AE$7+7),"◆",""),"") | AF29: =IF(AND($D29="Hito",ISNUMBER($K29)),IF(AND($K29>=AF$7,$K29<AF$7+7),"◆",""),"") | ... BX29: =IF(AND($D29="Hito",ISNUMBER($K29)),IF(AND($K29>=BX$7,$K29<BX$7+7),"◆",""),"")
B30: 13 | C30: Entrega y acta de recibo final | D30: Hito | E30: Dir. proyectos | G30: 12 | I30: 0 | J30: =IF(C30="","",IF(L30<>"",L30,IF(H30<>"",H30,IF(G30<>"",IFERROR(INDEX($T$8:$T$36,MATCH(G30,$B$8:$B$36,0))+IF(D30="Hito",0,1),IF(n_FInicio="",TODAY(),n_FInicio)),IF(n_FInicio="",TODAY(),n_FInicio))))) -> 46348 | K30: =IF(C30="","",IF(M30<>"",M30,IF(D30="Hito",J30,J30+MAX(N(I30),1)-1))) -> 46348 | O30: =IF(C30="","",IF(N30<>"",N30,IF(M30<>"",1,IF(F30="",0,IF(D30="Instalación",MIN(1,IFERROR(SUMIFS('CORTES CLIENTE'!$O$20:$O$219,PRESUPUESTO!$V$7:$V$206,F30)/SUMIFS(PRESUPUESTO!$G$7:$G$206,PRESUPUESTO!$V$7:$V$206,F30),0)),IF(D30="Compra",MIN(1,IFERROR(SUMIFS('CONTROL DE MATERIALES'!$U$11:$U$210,PRESUPUESTO!$V$7:$V$206,F30)/SUMIFS('CONTROL DE MATERIALES'!$V$11:$V$210,PRESUPUESTO!$V$7:$V$206,F30),0)),0)))))) -> 0 | P30: =IF(C30="","",IF(D30="Hito",IF(O30>=1,"Cumplido",IF(TODAY()>K30,"Vencido","Pendiente")),IF(O30>=1,"Terminada",IF(TODAY()>K30,"Atrasada",IF(OR(O30>0,L30<>""),"En curso",IF(TODAY()>=J30,"Debe iniciar","Por iniciar")))))) -> Pendiente | Q30: =IF(OR(C30="",N(O30)>=1),"",IF(TODAY()>K30,TODAY()-K30,0)) -> 0 | R30: =COUNTIF($D$8:D30,"Fase") -> 5 | S30: =IF(C30="","",J30) -> 46348 | T30: =IF(C30="","",K30) -> 46348 | U30: =IF(C30="","",MAX(N(I30),1)) -> 1 | V30: =IF(C30="","",U30*N(O30)) -> 0 | W30: =P30 -> Pendiente | X30: =IF(Q30="","",N(Q30)) -> 0 | Y30: =IF(AND($D30="Hito",ISNUMBER($K30)),IF(AND($K30>=Y$7,$K30<Y$7+7),"◆",""),"") | Z30: =IF(AND($D30="Hito",ISNUMBER($K30)),IF(AND($K30>=Z$7,$K30<Z$7+7),"◆",""),"") | AA30: =IF(AND($D30="Hito",ISNUMBER($K30)),IF(AND($K30>=AA$7,$K30<AA$7+7),"◆",""),"") | AB30: =IF(AND($D30="Hito",ISNUMBER($K30)),IF(AND($K30>=AB$7,$K30<AB$7+7),"◆",""),"") | AC30: =IF(AND($D30="Hito",ISNUMBER($K30)),IF(AND($K30>=AC$7,$K30<AC$7+7),"◆",""),"") | AD30: =IF(AND($D30="Hito",ISNUMBER($K30)),IF(AND($K30>=AD$7,$K30<AD$7+7),"◆",""),"") -> ◆ | AE30: =IF(AND($D30="Hito",ISNUMBER($K30)),IF(AND($K30>=AE$7,$K30<AE$7+7),"◆",""),"") | AF30: =IF(AND($D30="Hito",ISNUMBER($K30)),IF(AND($K30>=AF$7,$K30<AF$7+7),"◆",""),"") | ... BX30: =IF(AND($D30="Hito",ISNUMBER($K30)),IF(AND($K30>=BX$7,$K30<BX$7+7),"◆",""),"")
B31: 14 | C31: Liquidación del contrato | D31: Hito | E31: Gerencia | G31: 13 | I31: 0 | J31: =IF(C31="","",IF(L31<>"",L31,IF(H31<>"",H31,IF(G31<>"",IFERROR(INDEX($T$8:$T$36,MATCH(G31,$B$8:$B$36,0))+IF(D31="Hito",0,1),IF(n_FInicio="",TODAY(),n_FInicio)),IF(n_FInicio="",TODAY(),n_FInicio))))) -> 46348 | K31: =IF(C31="","",IF(M31<>"",M31,IF(D31="Hito",J31,J31+MAX(N(I31),1)-1))) -> 46348 | O31: =IF(C31="","",IF(N31<>"",N31,IF(M31<>"",1,IF(F31="",0,IF(D31="Instalación",MIN(1,IFERROR(SUMIFS('CORTES CLIENTE'!$O$20:$O$219,PRESUPUESTO!$V$7:$V$206,F31)/SUMIFS(PRESUPUESTO!$G$7:$G$206,PRESUPUESTO!$V$7:$V$206,F31),0)),IF(D31="Compra",MIN(1,IFERROR(SUMIFS('CONTROL DE MATERIALES'!$U$11:$U$210,PRESUPUESTO!$V$7:$V$206,F31)/SUMIFS('CONTROL DE MATERIALES'!$V$11:$V$210,PRESUPUESTO!$V$7:$V$206,F31),0)),0)))))) -> 0 | P31: =IF(C31="","",IF(D31="Hito",IF(O31>=1,"Cumplido",IF(TODAY()>K31,"Vencido","Pendiente")),IF(O31>=1,"Terminada",IF(TODAY()>K31,"Atrasada",IF(OR(O31>0,L31<>""),"En curso",IF(TODAY()>=J31,"Debe iniciar","Por iniciar")))))) -> Pendiente | Q31: =IF(OR(C31="",N(O31)>=1),"",IF(TODAY()>K31,TODAY()-K31,0)) -> 0 | R31: =COUNTIF($D$8:D31,"Fase") -> 5 | S31: =IF(C31="","",J31) -> 46348 | T31: =IF(C31="","",K31) -> 46348 | U31: =IF(C31="","",MAX(N(I31),1)) -> 1 | V31: =IF(C31="","",U31*N(O31)) -> 0 | W31: =P31 -> Pendiente | X31: =IF(Q31="","",N(Q31)) -> 0 | Y31: =IF(AND($D31="Hito",ISNUMBER($K31)),IF(AND($K31>=Y$7,$K31<Y$7+7),"◆",""),"") | Z31: =IF(AND($D31="Hito",ISNUMBER($K31)),IF(AND($K31>=Z$7,$K31<Z$7+7),"◆",""),"") | AA31: =IF(AND($D31="Hito",ISNUMBER($K31)),IF(AND($K31>=AA$7,$K31<AA$7+7),"◆",""),"") | AB31: =IF(AND($D31="Hito",ISNUMBER($K31)),IF(AND($K31>=AB$7,$K31<AB$7+7),"◆",""),"") | AC31: =IF(AND($D31="Hito",ISNUMBER($K31)),IF(AND($K31>=AC$7,$K31<AC$7+7),"◆",""),"") | AD31: =IF(AND($D31="Hito",ISNUMBER($K31)),IF(AND($K31>=AD$7,$K31<AD$7+7),"◆",""),"") -> ◆ | AE31: =IF(AND($D31="Hito",ISNUMBER($K31)),IF(AND($K31>=AE$7,$K31<AE$7+7),"◆",""),"") | AF31: =IF(AND($D31="Hito",ISNUMBER($K31)),IF(AND($K31>=AF$7,$K31<AF$7+7),"◆",""),"") | ... BX31: =IF(AND($D31="Hito",ISNUMBER($K31)),IF(AND($K31>=BX$7,$K31<BX$7+7),"◆",""),"")
B32: ="F"&R32 -> F6 | C32: OTRAS ACTIVIDADES | D32: Fase | I32: =IF(OR(J32="",K32=""),"",K32-J32+1) | J32: =IFERROR(1/(1/_xlfn.MINIFS($S$8:$S$36,$R$8:$R$36,R32)),"") | K32: =IFERROR(1/(1/_xlfn.MAXIFS($T$8:$T$36,$R$8:$R$36,R32)),"") | O32: =IFERROR(SUMIFS($V$8:$V$36,$R$8:$R$36,R32)/SUMIFS($U$8:$U$36,$R$8:$R$36,R32),"") | P32: =IF(COUNTIFS($R$8:$R$36,R32,$U$8:$U$36,">0")=0,"",IF(COUNTIFS($R$8:$R$36,R32,$W$8:$W$36,"Atrasada")+COUNTIFS($R$8:$R$36,R32,$W$8:$W$36,"Vencido")>0,"Con atraso",IF(N(O32)>=1,"Terminada",IF(N(O32)>0,"En curso","Por iniciar")))) | Q32: =IF(N(_xlfn.MAXIFS($X$8:$X$36,$R$8:$R$36,R32))>0,_xlfn.MAXIFS($X$8:$X$36,$R$8:$R$36,R32),"") | R32: =COUNTIF($D$8:D32,"Fase") -> 6
J33: =IF(C33="","",IF(L33<>"",L33,IF(H33<>"",H33,IF(G33<>"",IFERROR(INDEX($T$8:$T$36,MATCH(G33,$B$8:$B$36,0))+IF(D33="Hito",0,1),IF(n_FInicio="",TODAY(),n_FInicio)),IF(n_FInicio="",TODAY(),n_FInicio))))) | K33: =IF(C33="","",IF(M33<>"",M33,IF(D33="Hito",J33,J33+MAX(N(I33),1)-1))) | O33: =IF(C33="","",IF(N33<>"",N33,IF(M33<>"",1,IF(F33="",0,IF(D33="Instalación",MIN(1,IFERROR(SUMIFS('CORTES CLIENTE'!$O$20:$O$219,PRESUPUESTO!$V$7:$V$206,F33)/SUMIFS(PRESUPUESTO!$G$7:$G$206,PRESUPUESTO!$V$7:$V$206,F33),0)),IF(D33="Compra",MIN(1,IFERROR(SUMIFS('CONTROL DE MATERIALES'!$U$11:$U$210,PRESUPUESTO!$V$7:$V$206,F33)/SUMIFS('CONTROL DE MATERIALES'!$V$11:$V$210,PRESUPUESTO!$V$7:$V$206,F33),0)),0)))))) | P33: =IF(C33="","",IF(D33="Hito",IF(O33>=1,"Cumplido",IF(TODAY()>K33,"Vencido","Pendiente")),IF(O33>=1,"Terminada",IF(TODAY()>K33,"Atrasada",IF(OR(O33>0,L33<>""),"En curso",IF(TODAY()>=J33,"Debe iniciar","Por iniciar")))))) | Q33: =IF(OR(C33="",N(O33)>=1),"",IF(TODAY()>K33,TODAY()-K33,0)) | R33: =COUNTIF($D$8:D33,"Fase") -> 6 | S33: =IF(C33="","",J33) | T33: =IF(C33="","",K33) | U33: =IF(C33="","",MAX(N(I33),1)) | V33: =IF(C33="","",U33*N(O33)) | W33: =P33 | X33: =IF(Q33="","",N(Q33)) | Y33: =IF(AND($D33="Hito",ISNUMBER($K33)),IF(AND($K33>=Y$7,$K33<Y$7+7),"◆",""),"") | Z33: =IF(AND($D33="Hito",ISNUMBER($K33)),IF(AND($K33>=Z$7,$K33<Z$7+7),"◆",""),"") | AA33: =IF(AND($D33="Hito",ISNUMBER($K33)),IF(AND($K33>=AA$7,$K33<AA$7+7),"◆",""),"") | AB33: =IF(AND($D33="Hito",ISNUMBER($K33)),IF(AND($K33>=AB$7,$K33<AB$7+7),"◆",""),"") | AC33: =IF(AND($D33="Hito",ISNUMBER($K33)),IF(AND($K33>=AC$7,$K33<AC$7+7),"◆",""),"") | AD33: =IF(AND($D33="Hito",ISNUMBER($K33)),IF(AND($K33>=AD$7,$K33<AD$7+7),"◆",""),"") | AE33: =IF(AND($D33="Hito",ISNUMBER($K33)),IF(AND($K33>=AE$7,$K33<AE$7+7),"◆",""),"") | AF33: =IF(AND($D33="Hito",ISNUMBER($K33)),IF(AND($K33>=AF$7,$K33<AF$7+7),"◆",""),"") | ... BX33: =IF(AND($D33="Hito",ISNUMBER($K33)),IF(AND($K33>=BX$7,$K33<BX$7+7),"◆",""),"")
J34: =IF(C34="","",IF(L34<>"",L34,IF(H34<>"",H34,IF(G34<>"",IFERROR(INDEX($T$8:$T$36,MATCH(G34,$B$8:$B$36,0))+IF(D34="Hito",0,1),IF(n_FInicio="",TODAY(),n_FInicio)),IF(n_FInicio="",TODAY(),n_FInicio))))) | K34: =IF(C34="","",IF(M34<>"",M34,IF(D34="Hito",J34,J34+MAX(N(I34),1)-1))) | O34: =IF(C34="","",IF(N34<>"",N34,IF(M34<>"",1,IF(F34="",0,IF(D34="Instalación",MIN(1,IFERROR(SUMIFS('CORTES CLIENTE'!$O$20:$O$219,PRESUPUESTO!$V$7:$V$206,F34)/SUMIFS(PRESUPUESTO!$G$7:$G$206,PRESUPUESTO!$V$7:$V$206,F34),0)),IF(D34="Compra",MIN(1,IFERROR(SUMIFS('CONTROL DE MATERIALES'!$U$11:$U$210,PRESUPUESTO!$V$7:$V$206,F34)/SUMIFS('CONTROL DE MATERIALES'!$V$11:$V$210,PRESUPUESTO!$V$7:$V$206,F34),0)),0)))))) | P34: =IF(C34="","",IF(D34="Hito",IF(O34>=1,"Cumplido",IF(TODAY()>K34,"Vencido","Pendiente")),IF(O34>=1,"Terminada",IF(TODAY()>K34,"Atrasada",IF(OR(O34>0,L34<>""),"En curso",IF(TODAY()>=J34,"Debe iniciar","Por iniciar")))))) | Q34: =IF(OR(C34="",N(O34)>=1),"",IF(TODAY()>K34,TODAY()-K34,0)) | R34: =COUNTIF($D$8:D34,"Fase") -> 6 | S34: =IF(C34="","",J34) | T34: =IF(C34="","",K34) | U34: =IF(C34="","",MAX(N(I34),1)) | V34: =IF(C34="","",U34*N(O34)) | W34: =P34 | X34: =IF(Q34="","",N(Q34)) | Y34: =IF(AND($D34="Hito",ISNUMBER($K34)),IF(AND($K34>=Y$7,$K34<Y$7+7),"◆",""),"") | Z34: =IF(AND($D34="Hito",ISNUMBER($K34)),IF(AND($K34>=Z$7,$K34<Z$7+7),"◆",""),"") | AA34: =IF(AND($D34="Hito",ISNUMBER($K34)),IF(AND($K34>=AA$7,$K34<AA$7+7),"◆",""),"") | AB34: =IF(AND($D34="Hito",ISNUMBER($K34)),IF(AND($K34>=AB$7,$K34<AB$7+7),"◆",""),"") | AC34: =IF(AND($D34="Hito",ISNUMBER($K34)),IF(AND($K34>=AC$7,$K34<AC$7+7),"◆",""),"") | AD34: =IF(AND($D34="Hito",ISNUMBER($K34)),IF(AND($K34>=AD$7,$K34<AD$7+7),"◆",""),"") | AE34: =IF(AND($D34="Hito",ISNUMBER($K34)),IF(AND($K34>=AE$7,$K34<AE$7+7),"◆",""),"") | AF34: =IF(AND($D34="Hito",ISNUMBER($K34)),IF(AND($K34>=AF$7,$K34<AF$7+7),"◆",""),"") | ... BX34: =IF(AND($D34="Hito",ISNUMBER($K34)),IF(AND($K34>=BX$7,$K34<BX$7+7),"◆",""),"")
J35: =IF(C35="","",IF(L35<>"",L35,IF(H35<>"",H35,IF(G35<>"",IFERROR(INDEX($T$8:$T$36,MATCH(G35,$B$8:$B$36,0))+IF(D35="Hito",0,1),IF(n_FInicio="",TODAY(),n_FInicio)),IF(n_FInicio="",TODAY(),n_FInicio))))) | K35: =IF(C35="","",IF(M35<>"",M35,IF(D35="Hito",J35,J35+MAX(N(I35),1)-1))) | O35: =IF(C35="","",IF(N35<>"",N35,IF(M35<>"",1,IF(F35="",0,IF(D35="Instalación",MIN(1,IFERROR(SUMIFS('CORTES CLIENTE'!$O$20:$O$219,PRESUPUESTO!$V$7:$V$206,F35)/SUMIFS(PRESUPUESTO!$G$7:$G$206,PRESUPUESTO!$V$7:$V$206,F35),0)),IF(D35="Compra",MIN(1,IFERROR(SUMIFS('CONTROL DE MATERIALES'!$U$11:$U$210,PRESUPUESTO!$V$7:$V$206,F35)/SUMIFS('CONTROL DE MATERIALES'!$V$11:$V$210,PRESUPUESTO!$V$7:$V$206,F35),0)),0)))))) | P35: =IF(C35="","",IF(D35="Hito",IF(O35>=1,"Cumplido",IF(TODAY()>K35,"Vencido","Pendiente")),IF(O35>=1,"Terminada",IF(TODAY()>K35,"Atrasada",IF(OR(O35>0,L35<>""),"En curso",IF(TODAY()>=J35,"Debe iniciar","Por iniciar")))))) | Q35: =IF(OR(C35="",N(O35)>=1),"",IF(TODAY()>K35,TODAY()-K35,0)) | R35: =COUNTIF($D$8:D35,"Fase") -> 6 | S35: =IF(C35="","",J35) | T35: =IF(C35="","",K35) | U35: =IF(C35="","",MAX(N(I35),1)) | V35: =IF(C35="","",U35*N(O35)) | W35: =P35 | X35: =IF(Q35="","",N(Q35)) | Y35: =IF(AND($D35="Hito",ISNUMBER($K35)),IF(AND($K35>=Y$7,$K35<Y$7+7),"◆",""),"") | Z35: =IF(AND($D35="Hito",ISNUMBER($K35)),IF(AND($K35>=Z$7,$K35<Z$7+7),"◆",""),"") | AA35: =IF(AND($D35="Hito",ISNUMBER($K35)),IF(AND($K35>=AA$7,$K35<AA$7+7),"◆",""),"") | AB35: =IF(AND($D35="Hito",ISNUMBER($K35)),IF(AND($K35>=AB$7,$K35<AB$7+7),"◆",""),"") | AC35: =IF(AND($D35="Hito",ISNUMBER($K35)),IF(AND($K35>=AC$7,$K35<AC$7+7),"◆",""),"") | AD35: =IF(AND($D35="Hito",ISNUMBER($K35)),IF(AND($K35>=AD$7,$K35<AD$7+7),"◆",""),"") | AE35: =IF(AND($D35="Hito",ISNUMBER($K35)),IF(AND($K35>=AE$7,$K35<AE$7+7),"◆",""),"") | AF35: =IF(AND($D35="Hito",ISNUMBER($K35)),IF(AND($K35>=AF$7,$K35<AF$7+7),"◆",""),"") | ... BX35: =IF(AND($D35="Hito",ISNUMBER($K35)),IF(AND($K35>=BX$7,$K35<BX$7+7),"◆",""),"")
J36: =IF(C36="","",IF(L36<>"",L36,IF(H36<>"",H36,IF(G36<>"",IFERROR(INDEX($T$8:$T$36,MATCH(G36,$B$8:$B$36,0))+IF(D36="Hito",0,1),IF(n_FInicio="",TODAY(),n_FInicio)),IF(n_FInicio="",TODAY(),n_FInicio))))) | K36: =IF(C36="","",IF(M36<>"",M36,IF(D36="Hito",J36,J36+MAX(N(I36),1)-1))) | O36: =IF(C36="","",IF(N36<>"",N36,IF(M36<>"",1,IF(F36="",0,IF(D36="Instalación",MIN(1,IFERROR(SUMIFS('CORTES CLIENTE'!$O$20:$O$219,PRESUPUESTO!$V$7:$V$206,F36)/SUMIFS(PRESUPUESTO!$G$7:$G$206,PRESUPUESTO!$V$7:$V$206,F36),0)),IF(D36="Compra",MIN(1,IFERROR(SUMIFS('CONTROL DE MATERIALES'!$U$11:$U$210,PRESUPUESTO!$V$7:$V$206,F36)/SUMIFS('CONTROL DE MATERIALES'!$V$11:$V$210,PRESUPUESTO!$V$7:$V$206,F36),0)),0)))))) | P36: =IF(C36="","",IF(D36="Hito",IF(O36>=1,"Cumplido",IF(TODAY()>K36,"Vencido","Pendiente")),IF(O36>=1,"Terminada",IF(TODAY()>K36,"Atrasada",IF(OR(O36>0,L36<>""),"En curso",IF(TODAY()>=J36,"Debe iniciar","Por iniciar")))))) | Q36: =IF(OR(C36="",N(O36)>=1),"",IF(TODAY()>K36,TODAY()-K36,0)) | R36: =COUNTIF($D$8:D36,"Fase") -> 6 | S36: =IF(C36="","",J36) | T36: =IF(C36="","",K36) | U36: =IF(C36="","",MAX(N(I36),1)) | V36: =IF(C36="","",U36*N(O36)) | W36: =P36 | X36: =IF(Q36="","",N(Q36)) | Y36: =IF(AND($D36="Hito",ISNUMBER($K36)),IF(AND($K36>=Y$7,$K36<Y$7+7),"◆",""),"") | Z36: =IF(AND($D36="Hito",ISNUMBER($K36)),IF(AND($K36>=Z$7,$K36<Z$7+7),"◆",""),"") | AA36: =IF(AND($D36="Hito",ISNUMBER($K36)),IF(AND($K36>=AA$7,$K36<AA$7+7),"◆",""),"") | AB36: =IF(AND($D36="Hito",ISNUMBER($K36)),IF(AND($K36>=AB$7,$K36<AB$7+7),"◆",""),"") | AC36: =IF(AND($D36="Hito",ISNUMBER($K36)),IF(AND($K36>=AC$7,$K36<AC$7+7),"◆",""),"") | AD36: =IF(AND($D36="Hito",ISNUMBER($K36)),IF(AND($K36>=AD$7,$K36<AD$7+7),"◆",""),"") | AE36: =IF(AND($D36="Hito",ISNUMBER($K36)),IF(AND($K36>=AE$7,$K36<AE$7+7),"◆",""),"") | AF36: =IF(AND($D36="Hito",ISNUMBER($K36)),IF(AND($K36>=AF$7,$K36<AF$7+7),"◆",""),"") | ... BX36: =IF(AND($D36="Hito",ISNUMBER($K36)),IF(AND($K36>=BX$7,$K36<BX$7+7),"◆",""),"")
B38: CÓMO SE USA
B39: • Fila de color = FASE: sus fechas, % y estado se calculan solos con las actividades que tiene debajo.
B40: • Para agregar una actividad: copie una fila de actividad y use 'Insertar celdas copiadas' dentro de la fase.
B41: • Para una fase nueva: copie una fila de FASE (o use la fase 'OTRAS ACTIVIDADES' y cámbiele el nombre).
B42: • Compras por partes: agregue 'Compra lote 2, 3…' dentro de la fase; cada lote se cierra por separado.
B43: • Gantt: tono claro = programado · tono fuerte = ejecutado · rojo = atrasado · ◆ = hito · rosado = semana actual.

Sheet PRESUPUESTO
D1: PRESUPUESTO DEL PROYECTO | H1: Base de la cotización comercial: precio de venta y costos unitarios por tipo. Es la tabla madre del libro.
A2: INICIO | C2: TABLERO | D2: CRONOGRAMA | F2: ● PRESUPUESTO | G2: CORTES CLIENTE | H2: MANO DE OBRA | I2: GASTOS | J2: MATERIALES | L2: GUÍA
A3: =n_Proyecto&" · "&n_Cotizacion -> ·
C5: TOTALES | G5: =SUM(G7:G206) -> 0 | O5: =SUM(O7:O206) -> 0 | P5: =SUM(P7:P206) -> 0 | Q5: =SUM(Q7:Q206) -> 0 | R5: =SUM(R7:R206) -> 0 | S5: =SUM(S7:S206) -> 0 | T5: =SUM(T7:T206) -> 0 | U5: =IF(G5=0,"",T5/G5)
A6: Tipo | B6: Ítem | C6: Descripción | D6: Und | E6: Cant. | F6: PU venta | G6: Total venta | H6: C.U. material (sin IVA) | I6: C.U. material (con IVA) | J6: C.U. mano de obra | K6: C.U. transporte / otros | L6: Concepto alquiler | M6: C.U. alquiler | N6: C.U. total | O6: Total material | P6: Total mano de obra | Q6: Total transporte | R6: Total alquiler | S6: COSTO TOTAL | T6: Margen $ | U6: Margen % | V6: Frente (capítulo)
G7: =IF($A7<>"Ítem","",E7*F7) | I7: =IF($A7<>"Ítem","",N(H7)*IF(p_IVAMat="Sí",1+p_IVA,1)) | N7: =IF($A7<>"Ítem","",I7+N(J7)+N(K7)+N(M7)) | O7: =IF($A7<>"Ítem","",E7*I7) | P7: =IF($A7<>"Ítem","",E7*N(J7)) | Q7: =IF($A7<>"Ítem","",E7*N(K7)) | R7: =IF($A7<>"Ítem","",E7*N(M7)) | S7: =IF($A7<>"Ítem","",E7*N7) | T7: =IF($A7<>"Ítem","",G7-S7) | U7: =IF(OR($A7<>"Ítem",N(G7)=0),"",T7/G7) | V7: =IF(A7="Capítulo",C7,"") | W7: =IF(A7="Capítulo",C7,"")
G8: =IF($A8<>"Ítem","",E8*F8) | I8: =IF($A8<>"Ítem","",N(H8)*IF(p_IVAMat="Sí",1+p_IVA,1)) | N8: =IF($A8<>"Ítem","",I8+N(J8)+N(K8)+N(M8)) | O8: =IF($A8<>"Ítem","",E8*I8) | P8: =IF($A8<>"Ítem","",E8*N(J8)) | Q8: =IF($A8<>"Ítem","",E8*N(K8)) | R8: =IF($A8<>"Ítem","",E8*N(M8)) | S8: =IF($A8<>"Ítem","",E8*N8) | T8: =IF($A8<>"Ítem","",G8-S8) | U8: =IF(OR($A8<>"Ítem",N(G8)=0),"",T8/G8) | V8: =IF(A8="Capítulo",C8,V7) | W8: =IF(A8="Capítulo",C8,"")
G9: =IF($A9<>"Ítem","",E9*F9) | I9: =IF($A9<>"Ítem","",N(H9)*IF(p_IVAMat="Sí",1+p_IVA,1)) | N9: =IF($A9<>"Ítem","",I9+N(J9)+N(K9)+N(M9)) | O9: =IF($A9<>"Ítem","",E9*I9) | P9: =IF($A9<>"Ítem","",E9*N(J9)) | Q9: =IF($A9<>"Ítem","",E9*N(K9)) | R9: =IF($A9<>"Ítem","",E9*N(M9)) | S9: =IF($A9<>"Ítem","",E9*N9) | T9: =IF($A9<>"Ítem","",G9-S9) | U9: =IF(OR($A9<>"Ítem",N(G9)=0),"",T9/G9) | V9: =IF(A9="Capítulo",C9,V8) | W9: =IF(A9="Capítulo",C9,"")
G10: =IF($A10<>"Ítem","",E10*F10) | I10: =IF($A10<>"Ítem","",N(H10)*IF(p_IVAMat="Sí",1+p_IVA,1)) | N10: =IF($A10<>"Ítem","",I10+N(J10)+N(K10)+N(M10)) | O10: =IF($A10<>"Ítem","",E10*I10) | P10: =IF($A10<>"Ítem","",E10*N(J10)) | Q10: =IF($A10<>"Ítem","",E10*N(K10)) | R10: =IF($A10<>"Ítem","",E10*N(M10)) | S10: =IF($A10<>"Ítem","",E10*N10) | T10: =IF($A10<>"Ítem","",G10-S10) | U10: =IF(OR($A10<>"Ítem",N(G10)=0),"",T10/G10) | V10: =IF(A10="Capítulo",C10,V9) | W10: =IF(A10="Capítulo",C10,"")
G11: =IF($A11<>"Ítem","",E11*F11) | I11: =IF($A11<>"Ítem","",N(H11)*IF(p_IVAMat="Sí",1+p_IVA,1)) | N11: =IF($A11<>"Ítem","",I11+N(J11)+N(K11)+N(M11)) | O11: =IF($A11<>"Ítem","",E11*I11) | P11: =IF($A11<>"Ítem","",E11*N(J11)) | Q11: =IF($A11<>"Ítem","",E11*N(K11)) | R11: =IF($A11<>"Ítem","",E11*N(M11)) | S11: =IF($A11<>"Ítem","",E11*N11) | T11: =IF($A11<>"Ítem","",G11-S11) | U11: =IF(OR($A11<>"Ítem",N(G11)=0),"",T11/G11) | V11: =IF(A11="Capítulo",C11,V10) | W11: =IF(A11="Capítulo",C11,"")
G12: =IF($A12<>"Ítem","",E12*F12) | I12: =IF($A12<>"Ítem","",N(H12)*IF(p_IVAMat="Sí",1+p_IVA,1)) | N12: =IF($A12<>"Ítem","",I12+N(J12)+N(K12)+N(M12)) | O12: =IF($A12<>"Ítem","",E12*I12) | P12: =IF($A12<>"Ítem","",E12*N(J12)) | Q12: =IF($A12<>"Ítem","",E12*N(K12)) | R12: =IF($A12<>"Ítem","",E12*N(M12)) | S12: =IF($A12<>"Ítem","",E12*N12) | T12: =IF($A12<>"Ítem","",G12-S12) | U12: =IF(OR($A12<>"Ítem",N(G12)=0),"",T12/G12) | V12: =IF(A12="Capítulo",C12,V11) | W12: =IF(A12="Capítulo",C12,"")
G13: =IF($A13<>"Ítem","",E13*F13) | I13: =IF($A13<>"Ítem","",N(H13)*IF(p_IVAMat="Sí",1+p_IVA,1)) | N13: =IF($A13<>"Ítem","",I13+N(J13)+N(K13)+N(M13)) | O13: =IF($A13<>"Ítem","",E13*I13) | P13: =IF($A13<>"Ítem","",E13*N(J13)) | Q13: =IF($A13<>"Ítem","",E13*N(K13)) | R13: =IF($A13<>"Ítem","",E13*N(M13)) | S13: =IF($A13<>"Ítem","",E13*N13) | T13: =IF($A13<>"Ítem","",G13-S13) | U13: =IF(OR($A13<>"Ítem",N(G13)=0),"",T13/G13) | V13: =IF(A13="Capítulo",C13,V12) | W13: =IF(A13="Capítulo",C13,"")
G14: =IF($A14<>"Ítem","",E14*F14) | I14: =IF($A14<>"Ítem","",N(H14)*IF(p_IVAMat="Sí",1+p_IVA,1)) | N14: =IF($A14<>"Ítem","",I14+N(J14)+N(K14)+N(M14)) | O14: =IF($A14<>"Ítem","",E14*I14) | P14: =IF($A14<>"Ítem","",E14*N(J14)) | Q14: =IF($A14<>"Ítem","",E14*N(K14)) | R14: =IF($A14<>"Ítem","",E14*N(M14)) | S14: =IF($A14<>"Ítem","",E14*N14) | T14: =IF($A14<>"Ítem","",G14-S14) | U14: =IF(OR($A14<>"Ítem",N(G14)=0),"",T14/G14) | V14: =IF(A14="Capítulo",C14,V13) | W14: =IF(A14="Capítulo",C14,"")
G15: =IF($A15<>"Ítem","",E15*F15) | I15: =IF($A15<>"Ítem","",N(H15)*IF(p_IVAMat="Sí",1+p_IVA,1)) | N15: =IF($A15<>"Ítem","",I15+N(J15)+N(K15)+N(M15)) | O15: =IF($A15<>"Ítem","",E15*I15) | P15: =IF($A15<>"Ítem","",E15*N(J15)) | Q15: =IF($A15<>"Ítem","",E15*N(K15)) | R15: =IF($A15<>"Ítem","",E15*N(M15)) | S15: =IF($A15<>"Ítem","",E15*N15) | T15: =IF($A15<>"Ítem","",G15-S15) | U15: =IF(OR($A15<>"Ítem",N(G15)=0),"",T15/G15) | V15: =IF(A15="Capítulo",C15,V14) | W15: =IF(A15="Capítulo",C15,"")
G16: =IF($A16<>"Ítem","",E16*F16) | I16: =IF($A16<>"Ítem","",N(H16)*IF(p_IVAMat="Sí",1+p_IVA,1)) | N16: =IF($A16<>"Ítem","",I16+N(J16)+N(K16)+N(M16)) | O16: =IF($A16<>"Ítem","",E16*I16) | P16: =IF($A16<>"Ítem","",E16*N(J16)) | Q16: =IF($A16<>"Ítem","",E16*N(K16)) | R16: =IF($A16<>"Ítem","",E16*N(M16)) | S16: =IF($A16<>"Ítem","",E16*N16) | T16: =IF($A16<>"Ítem","",G16-S16) | U16: =IF(OR($A16<>"Ítem",N(G16)=0),"",T16/G16) | V16: =IF(A16="Capítulo",C16,V15) | W16: =IF(A16="Capítulo",C16,"")
G17: =IF($A17<>"Ítem","",E17*F17) | I17: =IF($A17<>"Ítem","",N(H17)*IF(p_IVAMat="Sí",1+p_IVA,1)) | N17: =IF($A17<>"Ítem","",I17+N(J17)+N(K17)+N(M17)) | O17: =IF($A17<>"Ítem","",E17*I17) | P17: =IF($A17<>"Ítem","",E17*N(J17)) | Q17: =IF($A17<>"Ítem","",E17*N(K17)) | R17: =IF($A17<>"Ítem","",E17*N(M17)) | S17: =IF($A17<>"Ítem","",E17*N17) | T17: =IF($A17<>"Ítem","",G17-S17) | U17: =IF(OR($A17<>"Ítem",N(G17)=0),"",T17/G17) | V17: =IF(A17="Capítulo",C17,V16) | W17: =IF(A17="Capítulo",C17,"")
G18: =IF($A18<>"Ítem","",E18*F18) | I18: =IF($A18<>"Ítem","",N(H18)*IF(p_IVAMat="Sí",1+p_IVA,1)) | N18: =IF($A18<>"Ítem","",I18+N(J18)+N(K18)+N(M18)) | O18: =IF($A18<>"Ítem","",E18*I18) | P18: =IF($A18<>"Ítem","",E18*N(J18)) | Q18: =IF($A18<>"Ítem","",E18*N(K18)) | R18: =IF($A18<>"Ítem","",E18*N(M18)) | S18: =IF($A18<>"Ítem","",E18*N18) | T18: =IF($A18<>"Ítem","",G18-S18) | U18: =IF(OR($A18<>"Ítem",N(G18)=0),"",T18/G18) | V18: =IF(A18="Capítulo",C18,V17) | W18: =IF(A18="Capítulo",C18,"")
G19: =IF($A19<>"Ítem","",E19*F19) | I19: =IF($A19<>"Ítem","",N(H19)*IF(p_IVAMat="Sí",1+p_IVA,1)) | N19: =IF($A19<>"Ítem","",I19+N(J19)+N(K19)+N(M19)) | O19: =IF($A19<>"Ítem","",E19*I19) | P19: =IF($A19<>"Ítem","",E19*N(J19)) | Q19: =IF($A19<>"Ítem","",E19*N(K19)) | R19: =IF($A19<>"Ítem","",E19*N(M19)) | S19: =IF($A19<>"Ítem","",E19*N19) | T19: =IF($A19<>"Ítem","",G19-S19) | U19: =IF(OR($A19<>"Ítem",N(G19)=0),"",T19/G19) | V19: =IF(A19="Capítulo",C19,V18) | W19: =IF(A19="Capítulo",C19,"")
... G206: =IF($A206<>"Ítem","",E206*F206) | I206: =IF($A206<>"Ítem","",N(H206)*IF(p_IVAMat="Sí",1+p_IVA,1)) | N206: =IF($A206<>"Ítem","",I206+N(J206)+N(K206)+N(M206)) | O206: =IF($A206<>"Ítem","",E206*I206) | P206: =IF($A206<>"Ítem","",E206*N(J206)) | Q206: =IF($A206<>"Ítem","",E206*N(K206)) | R206: =IF($A206<>"Ítem","",E206*N(M206)) | S206: =IF($A206<>"Ítem","",E206*N206) | T206: =IF($A206<>"Ítem","",G206-S206) | U206: =IF(OR($A206<>"Ítem",N(G206)=0),"",T206/G206) | V206: =IF(A206="Capítulo",C206,V205) | W206: =IF(A206="Capítulo",C206,"")

Sheet CORTES CLIENTE
C1: AVANCE DE OBRA Y CORTES AL CLIENTE | G1: Digite la cantidad ejecutada de cada ítem en la columna del corte. El acta, el AIU, la amortización del anticipo y lo pendiente se calculan solos.
A2: INICIO | C2: TABLERO | E2: CRONOGRAMA | F2: PRESUPUESTO | G2: ● CORTES CLIENTE | H2: MANO DE OBRA | I2: GASTOS | J2: MATERIALES | K2: GUÍA
A3: =n_Proyecto&" · Cliente: "&n_Cliente -> · Cliente:
A4: Corte N° | F4: Corte 1 | G4: Corte 2 | H4: Corte 3 | I4: Corte 4 | J4: Corte 5 | K4: Corte 6 | L4: ACUMULADO
A5: Fecha de corte
A6: Costo directo ejecutado (cant × PU venta) | F6: =SUMPRODUCT(F20:F219,$E$20:$E$219) -> 0 | G6: =SUMPRODUCT(G20:G219,$E$20:$E$219) -> 0 | H6: =SUMPRODUCT(H20:H219,$E$20:$E$219) -> 0 | I6: =SUMPRODUCT(I20:I219,$E$20:$E$219) -> 0 | J6: =SUMPRODUCT(J20:J219,$E$20:$E$219) -> 0 | K6: =SUMPRODUCT(K20:K219,$E$20:$E$219) -> 0 | L6: =SUM(F6:K6) -> 0
A7: Administración | F7: =F6*p_Admin -> 0 | G7: =G6*p_Admin -> 0 | H7: =H6*p_Admin -> 0 | I7: =I6*p_Admin -> 0 | J7: =J6*p_Admin -> 0 | K7: =K6*p_Admin -> 0 | L7: =SUM(F7:K7) -> 0
A8: Imprevistos | F8: =F6*p_Imprev -> 0 | G8: =G6*p_Imprev -> 0 | H8: =H6*p_Imprev -> 0 | I8: =I6*p_Imprev -> 0 | J8: =J6*p_Imprev -> 0 | K8: =K6*p_Imprev -> 0 | L8: =SUM(F8:K8) -> 0
A9: Utilidad | F9: =F6*p_Util -> 0 | G9: =G6*p_Util -> 0 | H9: =H6*p_Util -> 0 | I9: =I6*p_Util -> 0 | J9: =J6*p_Util -> 0 | K9: =K6*p_Util -> 0 | L9: =SUM(F9:K9) -> 0
A10: IVA sobre utilidad | F10: =F9*p_IVA -> 0 | G10: =G9*p_IVA -> 0 | H10: =H9*p_IVA -> 0 | I10: =I9*p_IVA -> 0 | J10: =J9*p_IVA -> 0 | K10: =K9*p_IVA -> 0 | L10: =SUM(F10:K10) -> 0
A11: TOTAL ACTA | F11: =SUM(F6:F10) -> 0 | G11: =SUM(G6:G10) -> 0 | H11: =SUM(H6:H10) -> 0 | I11: =SUM(I6:I10) -> 0 | J11: =SUM(J6:J10) -> 0 | K11: =SUM(K6:K10) -> 0 | L11: =SUM(F11:K11) -> 0
A12: Amortización anticipo | F12: =-F11*p_Anticipo -> 0 | G12: =-G11*p_Anticipo -> 0 | H12: =-H11*p_Anticipo -> 0 | I12: =-I11*p_Anticipo -> 0 | J12: =-J11*p_Anticipo -> 0 | K12: =-K11*p_Anticipo -> 0 | L12: =SUM(F12:K12) -> 0
A13: NETO A FACTURAR | F13: =F11+F12 -> 0 | G13: =G11+G12 -> 0 | H13: =H11+H12 -> 0 | I13: =I11+I12 -> 0 | J13: =J11+J12 -> 0 | K13: =K11+K12 -> 0 | L13: =SUM(F13:K13) -> 0
A14: N° de factura
A15: Fecha de factura
A16: Estado (Pendiente / Facturado / Pagado)
A17: Valor recaudado | L17: =SUM(F17:K17) -> 0
A18: AVANCE FÍSICO DEL PROYECTO (valor ejecutado / valor total) → | N18: =IF(v_CD=0,"",O18/v_CD) | O18: =SUM(O20:O219) -> 0 | P18: =SUM(P20:P219) -> 0
A19: Ítem | B19: Descripción | C19: Und | D19: Cant. contrato | E19: PU venta | F19: Corte 1 (cant.) | G19: Corte 2 (cant.) | H19: Corte 3 (cant.) | I19: Corte 4 (cant.) | J19: Corte 5 (cant.) | K19: Corte 6 (cant.) | L19: Cant. ejecutada | M19: Cant. pendiente | N19: % avance ítem | O19: Valor ejecutado | P19: Valor pendiente
A20: =IF(PRESUPUESTO!$A7="Ítem",PRESUPUESTO!B7,"") | B20: =IF(PRESUPUESTO!C7="","",PRESUPUESTO!C7) | C20: =IF(PRESUPUESTO!$A7="Ítem",PRESUPUESTO!D7,"") | D20: =IF(PRESUPUESTO!$A7="Ítem",PRESUPUESTO!E7,"") | E20: =IF(D20="","",PRESUPUESTO!F7) | L20: =IF(D20="","",SUM(F20:K20)) | M20: =IF(D20="","",D20-L20) | N20: =IF(OR(D20="",N(D20)=0),"",L20/D20) | O20: =IF(D20="","",L20*E20) | P20: =IF(D20="","",M20*E20)
A21: =IF(PRESUPUESTO!$A8="Ítem",PRESUPUESTO!B8,"") | B21: =IF(PRESUPUESTO!C8="","",PRESUPUESTO!C8) | C21: =IF(PRESUPUESTO!$A8="Ítem",PRESUPUESTO!D8,"") | D21: =IF(PRESUPUESTO!$A8="Ítem",PRESUPUESTO!E8,"") | E21: =IF(D21="","",PRESUPUESTO!F8) | L21: =IF(D21="","",SUM(F21:K21)) | M21: =IF(D21="","",D21-L21) | N21: =IF(OR(D21="",N(D21)=0),"",L21/D21) | O21: =IF(D21="","",L21*E21) | P21: =IF(D21="","",M21*E21)
A22: =IF(PRESUPUESTO!$A9="Ítem",PRESUPUESTO!B9,"") | B22: =IF(PRESUPUESTO!C9="","",PRESUPUESTO!C9) | C22: =IF(PRESUPUESTO!$A9="Ítem",PRESUPUESTO!D9,"") | D22: =IF(PRESUPUESTO!$A9="Ítem",PRESUPUESTO!E9,"") | E22: =IF(D22="","",PRESUPUESTO!F9) | L22: =IF(D22="","",SUM(F22:K22)) | M22: =IF(D22="","",D22-L22) | N22: =IF(OR(D22="",N(D22)=0),"",L22/D22) | O22: =IF(D22="","",L22*E22) | P22: =IF(D22="","",M22*E22)
A23: =IF(PRESUPUESTO!$A10="Ítem",PRESUPUESTO!B10,"") | B23: =IF(PRESUPUESTO!C10="","",PRESUPUESTO!C10) | C23: =IF(PRESUPUESTO!$A10="Ítem",PRESUPUESTO!D10,"") | D23: =IF(PRESUPUESTO!$A10="Ítem",PRESUPUESTO!E10,"") | E23: =IF(D23="","",PRESUPUESTO!F10) | L23: =IF(D23="","",SUM(F23:K23)) | M23: =IF(D23="","",D23-L23) | N23: =IF(OR(D23="",N(D23)=0),"",L23/D23) | O23: =IF(D23="","",L23*E23) | P23: =IF(D23="","",M23*E23)
A24: =IF(PRESUPUESTO!$A11="Ítem",PRESUPUESTO!B11,"") | B24: =IF(PRESUPUESTO!C11="","",PRESUPUESTO!C11) | C24: =IF(PRESUPUESTO!$A11="Ítem",PRESUPUESTO!D11,"") | D24: =IF(PRESUPUESTO!$A11="Ítem",PRESUPUESTO!E11,"") | E24: =IF(D24="","",PRESUPUESTO!F11) | L24: =IF(D24="","",SUM(F24:K24)) | M24: =IF(D24="","",D24-L24) | N24: =IF(OR(D24="",N(D24)=0),"",L24/D24) | O24: =IF(D24="","",L24*E24) | P24: =IF(D24="","",M24*E24)
A25: =IF(PRESUPUESTO!$A12="Ítem",PRESUPUESTO!B12,"") | B25: =IF(PRESUPUESTO!C12="","",PRESUPUESTO!C12) | C25: =IF(PRESUPUESTO!$A12="Ítem",PRESUPUESTO!D12,"") | D25: =IF(PRESUPUESTO!$A12="Ítem",PRESUPUESTO!E12,"") | E25: =IF(D25="","",PRESUPUESTO!F12) | L25: =IF(D25="","",SUM(F25:K25)) | M25: =IF(D25="","",D25-L25) | N25: =IF(OR(D25="",N(D25)=0),"",L25/D25) | O25: =IF(D25="","",L25*E25) | P25: =IF(D25="","",M25*E25)
A26: =IF(PRESUPUESTO!$A13="Ítem",PRESUPUESTO!B13,"") | B26: =IF(PRESUPUESTO!C13="","",PRESUPUESTO!C13) | C26: =IF(PRESUPUESTO!$A13="Ítem",PRESUPUESTO!D13,"") | D26: =IF(PRESUPUESTO!$A13="Ítem",PRESUPUESTO!E13,"") | E26: =IF(D26="","",PRESUPUESTO!F13) | L26: =IF(D26="","",SUM(F26:K26)) | M26: =IF(D26="","",D26-L26) | N26: =IF(OR(D26="",N(D26)=0),"",L26/D26) | O26: =IF(D26="","",L26*E26) | P26: =IF(D26="","",M26*E26)
A27: =IF(PRESUPUESTO!$A14="Ítem",PRESUPUESTO!B14,"") | B27: =IF(PRESUPUESTO!C14="","",PRESUPUESTO!C14) | C27: =IF(PRESUPUESTO!$A14="Ítem",PRESUPUESTO!D14,"") | D27: =IF(PRESUPUESTO!$A14="Ítem",PRESUPUESTO!E14,"") | E27: =IF(D27="","",PRESUPUESTO!F14) | L27: =IF(D27="","",SUM(F27:K27)) | M27: =IF(D27="","",D27-L27) | N27: =IF(OR(D27="",N(D27)=0),"",L27/D27) | O27: =IF(D27="","",L27*E27) | P27: =IF(D27="","",M27*E27)
A28: =IF(PRESUPUESTO!$A15="Ítem",PRESUPUESTO!B15,"") | B28: =IF(PRESUPUESTO!C15="","",PRESUPUESTO!C15) | C28: =IF(PRESUPUESTO!$A15="Ítem",PRESUPUESTO!D15,"") | D28: =IF(PRESUPUESTO!$A15="Ítem",PRESUPUESTO!E15,"") | E28: =IF(D28="","",PRESUPUESTO!F15) | L28: =IF(D28="","",SUM(F28:K28)) | M28: =IF(D28="","",D28-L28) | N28: =IF(OR(D28="",N(D28)=0),"",L28/D28) | O28: =IF(D28="","",L28*E28) | P28: =IF(D28="","",M28*E28)
A29: =IF(PRESUPUESTO!$A16="Ítem",PRESUPUESTO!B16,"") | B29: =IF(PRESUPUESTO!C16="","",PRESUPUESTO!C16) | C29: =IF(PRESUPUESTO!$A16="Ítem",PRESUPUESTO!D16,"") | D29: =IF(PRESUPUESTO!$A16="Ítem",PRESUPUESTO!E16,"") | E29: =IF(D29="","",PRESUPUESTO!F16) | L29: =IF(D29="","",SUM(F29:K29)) | M29: =IF(D29="","",D29-L29) | N29: =IF(OR(D29="",N(D29)=0),"",L29/D29) | O29: =IF(D29="","",L29*E29) | P29: =IF(D29="","",M29*E29)
A30: =IF(PRESUPUESTO!$A17="Ítem",PRESUPUESTO!B17,"") | B30: =IF(PRESUPUESTO!C17="","",PRESUPUESTO!C17) | C30: =IF(PRESUPUESTO!$A17="Ítem",PRESUPUESTO!D17,"") | D30: =IF(PRESUPUESTO!$A17="Ítem",PRESUPUESTO!E17,"") | E30: =IF(D30="","",PRESUPUESTO!F17) | L30: =IF(D30="","",SUM(F30:K30)) | M30: =IF(D30="","",D30-L30) | N30: =IF(OR(D30="",N(D30)=0),"",L30/D30) | O30: =IF(D30="","",L30*E30) | P30: =IF(D30="","",M30*E30)
A31: =IF(PRESUPUESTO!$A18="Ítem",PRESUPUESTO!B18,"") | B31: =IF(PRESUPUESTO!C18="","",PRESUPUESTO!C18) | C31: =IF(PRESUPUESTO!$A18="Ítem",PRESUPUESTO!D18,"") | D31: =IF(PRESUPUESTO!$A18="Ítem",PRESUPUESTO!E18,"") | E31: =IF(D31="","",PRESUPUESTO!F18) | L31: =IF(D31="","",SUM(F31:K31)) | M31: =IF(D31="","",D31-L31) | N31: =IF(OR(D31="",N(D31)=0),"",L31/D31) | O31: =IF(D31="","",L31*E31) | P31: =IF(D31="","",M31*E31)
... A219: =IF(PRESUPUESTO!$A206="Ítem",PRESUPUESTO!B206,"") | B219: =IF(PRESUPUESTO!C206="","",PRESUPUESTO!C206) | C219: =IF(PRESUPUESTO!$A206="Ítem",PRESUPUESTO!D206,"") | D219: =IF(PRESUPUESTO!$A206="Ítem",PRESUPUESTO!E206,"") | E219: =IF(D219="","",PRESUPUESTO!F206) | L219: =IF(D219="","",SUM(F219:K219)) | M219: =IF(D219="","",D219-L219) | N219: =IF(OR(D219="",N(D219)=0),"",L219/D219) | O219: =IF(D219="","",L219*E219) | P219: =IF(D219="","",M219*E219)

Sheet MANO DE OBRA
C1: MANO DE OBRA | H1: Izquierda: contrato y cortes del contratista (cantidades por ítem). Derecha: horas de técnicos propios. Los pagos al contratista se registran en GASTOS (Tipo 'Mano de obra contratista', Factura/OC = 'Corte 1', 'Corte 2'…).
A2: INICIO | C2: TABLERO | E2: CRONOGRAMA | G2: PRESUPUESTO | H2: CORTES CLIENTE | I2: ● MANO DE OBRA | J2: GASTOS | K2: MATERIALES | L2: GUÍA
A3: ="Contratista: "&n_Contratista&" · Contrato: "&TEXT(H11,"$#,##0")&" · Ejecutado: "&TEXT(S11,"$#,##0")&" · Pagado total: "&TEXT(SUMIFS(GASTOS!$J$7:$J$5000,GASTOS!$L$7:$L$5000,"Mano de obra contratista"),"$#,##0") -> Contratista: · Contrato: $0 · Ejecutado: $0 · Pagado total: $0
A4: Corte N° | J4: Corte 1 | K4: Corte 2 | L4: Corte 3 | M4: Corte 4 | N4: Corte 5 | O4: Corte 6 | P4: TOTAL | V4: TÉCNICOS PROPIOS PCTRONIC — total horas / costo → | AD4: =SUM(AD13:AD312) -> 0 | AE4: =SUM(AE13:AE312) -> 0
A5: Fecha de corte
A6: Valor corte (precio contratista) | J6: =SUMPRODUCT(J13:J212,$F$13:$F$212) -> 0 | K6: =SUMPRODUCT(K13:K212,$F$13:$F$212) -> 0 | L6: =SUMPRODUCT(L13:L212,$F$13:$F$212) -> 0 | M6: =SUMPRODUCT(M13:M212,$F$13:$F$212) -> 0 | N6: =SUMPRODUCT(N13:N212,$F$13:$F$212) -> 0 | O6: =SUMPRODUCT(O13:O212,$F$13:$F$212) -> 0 | P6: =SUM(J6:O6) -> 0 | V6: Una fila por técnico y día. El valor hora sale de las tarifas de INICIO; si deja 'Horas/día' vacío se usan las horas estándar del cargo.
A7: Valor corte (precio presupuesto) | J7: =SUMPRODUCT(J13:J212,$E$13:$E$212) -> 0 | K7: =SUMPRODUCT(K13:K212,$E$13:$E$212) -> 0 | L7: =SUMPRODUCT(L13:L212,$E$13:$E$212) -> 0 | M7: =SUMPRODUCT(M13:M212,$E$13:$E$212) -> 0 | N7: =SUMPRODUCT(N13:N212,$E$13:$E$212) -> 0 | O7: =SUMPRODUCT(O13:O212,$E$13:$E$212) -> 0 | P7: =SUM(J7:O7) -> 0
A8: N° cuenta de cobro
A9: Pagado (desde GASTOS) | J9: =SUMIFS(GASTOS!$J$7:$J$5000,GASTOS!$L$7:$L$5000,"Mano de obra contratista",GASTOS!$E$7:$E$5000,"Corte 1") -> 0 | K9: =SUMIFS(GASTOS!$J$7:$J$5000,GASTOS!$L$7:$L$5000,"Mano de obra contratista",GASTOS!$E$7:$E$5000,"Corte 2") -> 0 | L9: =SUMIFS(GASTOS!$J$7:$J$5000,GASTOS!$L$7:$L$5000,"Mano de obra contratista",GASTOS!$E$7:$E$5000,"Corte 3") -> 0 | M9: =SUMIFS(GASTOS!$J$7:$J$5000,GASTOS!$L$7:$L$5000,"Mano de obra contratista",GASTOS!$E$7:$E$5000,"Corte 4") -> 0 | N9: =SUMIFS(GASTOS!$J$7:$J$5000,GASTOS!$L$7:$L$5000,"Mano de obra contratista",GASTOS!$E$7:$E$5000,"Corte 5") -> 0 | O9: =SUMIFS(GASTOS!$J$7:$J$5000,GASTOS!$L$7:$L$5000,"Mano de obra contratista",GASTOS!$E$7:$E$5000,"Corte 6") -> 0 | P9: =SUM(J9:O9) -> 0
A10: SALDO POR PAGAR DEL CORTE | J10: =J6-J9 -> 0 | K10: =K6-K9 -> 0 | L10: =L6-L9 -> 0 | M10: =M6-M9 -> 0 | N10: =N6-N9 -> 0 | O10: =O6-O9 -> 0 | P10: =SUM(J10:O10) -> 0
A11: TOTALES → | G11: =SUM(G13:G212) -> 0 | H11: =SUM(H13:H212) -> 0 | I11: =SUM(I13:I212) -> 0 | R11: =IF(H11=0,"",S11/H11) | S11: =SUM(S13:S212) -> 0 | T11: =SUM(T13:T212) -> 0
A12: Ítem | B12: Descripción | C12: Und | D12: Cant. | E12: PU presupuesto | F12: PU contratista | G12: Total presupuesto | H12: Total contratista | I12: Ahorro vs presupuesto | J12: Corte 1 (cant.) | K12: Corte 2 (cant.) | L12: Corte 3 (cant.) | M12: Corte 4 (cant.) | N12: Corte 5 (cant.) | O12: Corte 6 (cant.) | P12: Cant. ejecutada | Q12: Cant. pendiente | R12: % avance | S12: Valor ejecutado | T12: Valor pendiente | V12: Fecha | W12: Técnico | X12: Cargo (tarifas de INICIO) | Y12: Ítem / actividad | Z12: Días | AA12: Horas/día (opcional) | AB12: Horas extra | AC12: Valor hora | AD12: Total horas | AE12: Valor total | AF12: Observaciones
A13: =IF(PRESUPUESTO!$A7="Ítem",PRESUPUESTO!B7,"") | B13: =IF(PRESUPUESTO!C7="","",PRESUPUESTO!C7) | C13: =IF(PRESUPUESTO!$A7="Ítem",PRESUPUESTO!D7,"") | D13: =IF(PRESUPUESTO!$A7="Ítem",PRESUPUESTO!E7,"") | E13: =IF(D13="","",N(PRESUPUESTO!J7)) | G13: =IF(D13="","",D13*E13) | H13: =IF(D13="","",D13*N(F13)) | I13: =IF(D13="","",G13-H13) | P13: =IF(D13="","",SUM(J13:O13)) | Q13: =IF(D13="","",D13-P13) | R13: =IF(OR(D13="",N(D13)=0),"",P13/D13) | S13: =IF(D13="","",P13*N(F13)) | T13: =IF(D13="","",Q13*N(F13)) | AC13: =IF(X13="","",IFERROR(INDEX(t_Hora,MATCH(X13,t_Cargo,0)),0)) | AD13: =IF(X13="","",N(Z13)*IF(AA13="",IFERROR(INDEX(t_Horas,MATCH(X13,t_Cargo,0)),8),AA13)+N(AB13)) | AE13: =IF(X13="","",AC13*(N(Z13)*IF(AA13="",IFERROR(INDEX(t_Horas,MATCH(X13,t_Cargo,0)),8),AA13)+N(AB13)*(1+p_Extra)))
A14: =IF(PRESUPUESTO!$A8="Ítem",PRESUPUESTO!B8,"") | B14: =IF(PRESUPUESTO!C8="","",PRESUPUESTO!C8) | C14: =IF(PRESUPUESTO!$A8="Ítem",PRESUPUESTO!D8,"") | D14: =IF(PRESUPUESTO!$A8="Ítem",PRESUPUESTO!E8,"") | E14: =IF(D14="","",N(PRESUPUESTO!J8)) | G14: =IF(D14="","",D14*E14) | H14: =IF(D14="","",D14*N(F14)) | I14: =IF(D14="","",G14-H14) | P14: =IF(D14="","",SUM(J14:O14)) | Q14: =IF(D14="","",D14-P14) | R14: =IF(OR(D14="",N(D14)=0),"",P14/D14) | S14: =IF(D14="","",P14*N(F14)) | T14: =IF(D14="","",Q14*N(F14)) | AC14: =IF(X14="","",IFERROR(INDEX(t_Hora,MATCH(X14,t_Cargo,0)),0)) | AD14: =IF(X14="","",N(Z14)*IF(AA14="",IFERROR(INDEX(t_Horas,MATCH(X14,t_Cargo,0)),8),AA14)+N(AB14)) | AE14: =IF(X14="","",AC14*(N(Z14)*IF(AA14="",IFERROR(INDEX(t_Horas,MATCH(X14,t_Cargo,0)),8),AA14)+N(AB14)*(1+p_Extra)))
A15: =IF(PRESUPUESTO!$A9="Ítem",PRESUPUESTO!B9,"") | B15: =IF(PRESUPUESTO!C9="","",PRESUPUESTO!C9) | C15: =IF(PRESUPUESTO!$A9="Ítem",PRESUPUESTO!D9,"") | D15: =IF(PRESUPUESTO!$A9="Ítem",PRESUPUESTO!E9,"") | E15: =IF(D15="","",N(PRESUPUESTO!J9)) | G15: =IF(D15="","",D15*E15) | H15: =IF(D15="","",D15*N(F15)) | I15: =IF(D15="","",G15-H15) | P15: =IF(D15="","",SUM(J15:O15)) | Q15: =IF(D15="","",D15-P15) | R15: =IF(OR(D15="",N(D15)=0),"",P15/D15) | S15: =IF(D15="","",P15*N(F15)) | T15: =IF(D15="","",Q15*N(F15)) | AC15: =IF(X15="","",IFERROR(INDEX(t_Hora,MATCH(X15,t_Cargo,0)),0)) | AD15: =IF(X15="","",N(Z15)*IF(AA15="",IFERROR(INDEX(t_Horas,MATCH(X15,t_Cargo,0)),8),AA15)+N(AB15)) | AE15: =IF(X15="","",AC15*(N(Z15)*IF(AA15="",IFERROR(INDEX(t_Horas,MATCH(X15,t_Cargo,0)),8),AA15)+N(AB15)*(1+p_Extra)))
A16: =IF(PRESUPUESTO!$A10="Ítem",PRESUPUESTO!B10,"") | B16: =IF(PRESUPUESTO!C10="","",PRESUPUESTO!C10) | C16: =IF(PRESUPUESTO!$A10="Ítem",PRESUPUESTO!D10,"") | D16: =IF(PRESUPUESTO!$A10="Ítem",PRESUPUESTO!E10,"") | E16: =IF(D16="","",N(PRESUPUESTO!J10)) | G16: =IF(D16="","",D16*E16) | H16: =IF(D16="","",D16*N(F16)) | I16: =IF(D16="","",G16-H16) | P16: =IF(D16="","",SUM(J16:O16)) | Q16: =IF(D16="","",D16-P16) | R16: =IF(OR(D16="",N(D16)=0),"",P16/D16) | S16: =IF(D16="","",P16*N(F16)) | T16: =IF(D16="","",Q16*N(F16)) | AC16: =IF(X16="","",IFERROR(INDEX(t_Hora,MATCH(X16,t_Cargo,0)),0)) | AD16: =IF(X16="","",N(Z16)*IF(AA16="",IFERROR(INDEX(t_Horas,MATCH(X16,t_Cargo,0)),8),AA16)+N(AB16)) | AE16: =IF(X16="","",AC16*(N(Z16)*IF(AA16="",IFERROR(INDEX(t_Horas,MATCH(X16,t_Cargo,0)),8),AA16)+N(AB16)*(1+p_Extra)))
A17: =IF(PRESUPUESTO!$A11="Ítem",PRESUPUESTO!B11,"") | B17: =IF(PRESUPUESTO!C11="","",PRESUPUESTO!C11) | C17: =IF(PRESUPUESTO!$A11="Ítem",PRESUPUESTO!D11,"") | D17: =IF(PRESUPUESTO!$A11="Ítem",PRESUPUESTO!E11,"") | E17: =IF(D17="","",N(PRESUPUESTO!J11)) | G17: =IF(D17="","",D17*E17) | H17: =IF(D17="","",D17*N(F17)) | I17: =IF(D17="","",G17-H17) | P17: =IF(D17="","",SUM(J17:O17)) | Q17: =IF(D17="","",D17-P17) | R17: =IF(OR(D17="",N(D17)=0),"",P17/D17) | S17: =IF(D17="","",P17*N(F17)) | T17: =IF(D17="","",Q17*N(F17)) | AC17: =IF(X17="","",IFERROR(INDEX(t_Hora,MATCH(X17,t_Cargo,0)),0)) | AD17: =IF(X17="","",N(Z17)*IF(AA17="",IFERROR(INDEX(t_Horas,MATCH(X17,t_Cargo,0)),8),AA17)+N(AB17)) | AE17: =IF(X17="","",AC17*(N(Z17)*IF(AA17="",IFERROR(INDEX(t_Horas,MATCH(X17,t_Cargo,0)),8),AA17)+N(AB17)*(1+p_Extra)))
A18: =IF(PRESUPUESTO!$A12="Ítem",PRESUPUESTO!B12,"") | B18: =IF(PRESUPUESTO!C12="","",PRESUPUESTO!C12) | C18: =IF(PRESUPUESTO!$A12="Ítem",PRESUPUESTO!D12,"") | D18: =IF(PRESUPUESTO!$A12="Ítem",PRESUPUESTO!E12,"") | E18: =IF(D18="","",N(PRESUPUESTO!J12)) | G18: =IF(D18="","",D18*E18) | H18: =IF(D18="","",D18*N(F18)) | I18: =IF(D18="","",G18-H18) | P18: =IF(D18="","",SUM(J18:O18)) | Q18: =IF(D18="","",D18-P18) | R18: =IF(OR(D18="",N(D18)=0),"",P18/D18) | S18: =IF(D18="","",P18*N(F18)) | T18: =IF(D18="","",Q18*N(F18)) | AC18: =IF(X18="","",IFERROR(INDEX(t_Hora,MATCH(X18,t_Cargo,0)),0)) | AD18: =IF(X18="","",N(Z18)*IF(AA18="",IFERROR(INDEX(t_Horas,MATCH(X18,t_Cargo,0)),8),AA18)+N(AB18)) | AE18: =IF(X18="","",AC18*(N(Z18)*IF(AA18="",IFERROR(INDEX(t_Horas,MATCH(X18,t_Cargo,0)),8),AA18)+N(AB18)*(1+p_Extra)))
A19: =IF(PRESUPUESTO!$A13="Ítem",PRESUPUESTO!B13,"") | B19: =IF(PRESUPUESTO!C13="","",PRESUPUESTO!C13) | C19: =IF(PRESUPUESTO!$A13="Ítem",PRESUPUESTO!D13,"") | D19: =IF(PRESUPUESTO!$A13="Ítem",PRESUPUESTO!E13,"") | E19: =IF(D19="","",N(PRESUPUESTO!J13)) | G19: =IF(D19="","",D19*E19) | H19: =IF(D19="","",D19*N(F19)) | I19: =IF(D19="","",G19-H19) | P19: =IF(D19="","",SUM(J19:O19)) | Q19: =IF(D19="","",D19-P19) | R19: =IF(OR(D19="",N(D19)=0),"",P19/D19) | S19: =IF(D19="","",P19*N(F19)) | T19: =IF(D19="","",Q19*N(F19)) | AC19: =IF(X19="","",IFERROR(INDEX(t_Hora,MATCH(X19,t_Cargo,0)),0)) | AD19: =IF(X19="","",N(Z19)*IF(AA19="",IFERROR(INDEX(t_Horas,MATCH(X19,t_Cargo,0)),8),AA19)+N(AB19)) | AE19: =IF(X19="","",AC19*(N(Z19)*IF(AA19="",IFERROR(INDEX(t_Horas,MATCH(X19,t_Cargo,0)),8),AA19)+N(AB19)*(1+p_Extra)))
A20: =IF(PRESUPUESTO!$A14="Ítem",PRESUPUESTO!B14,"") | B20: =IF(PRESUPUESTO!C14="","",PRESUPUESTO!C14) | C20: =IF(PRESUPUESTO!$A14="Ítem",PRESUPUESTO!D14,"") | D20: =IF(PRESUPUESTO!$A14="Ítem",PRESUPUESTO!E14,"") | E20: =IF(D20="","",N(PRESUPUESTO!J14)) | G20: =IF(D20="","",D20*E20) | H20: =IF(D20="","",D20*N(F20)) | I20: =IF(D20="","",G20-H20) | P20: =IF(D20="","",SUM(J20:O20)) | Q20: =IF(D20="","",D20-P20) | R20: =IF(OR(D20="",N(D20)=0),"",P20/D20) | S20: =IF(D20="","",P20*N(F20)) | T20: =IF(D20="","",Q20*N(F20)) | AC20: =IF(X20="","",IFERROR(INDEX(t_Hora,MATCH(X20,t_Cargo,0)),0)) | AD20: =IF(X20="","",N(Z20)*IF(AA20="",IFERROR(INDEX(t_Horas,MATCH(X20,t_Cargo,0)),8),AA20)+N(AB20)) | AE20: =IF(X20="","",AC20*(N(Z20)*IF(AA20="",IFERROR(INDEX(t_Horas,MATCH(X20,t_Cargo,0)),8),AA20)+N(AB20)*(1+p_Extra)))
A21: =IF(PRESUPUESTO!$A15="Ítem",PRESUPUESTO!B15,"") | B21: =IF(PRESUPUESTO!C15="","",PRESUPUESTO!C15) | C21: =IF(PRESUPUESTO!$A15="Ítem",PRESUPUESTO!D15,"") | D21: =IF(PRESUPUESTO!$A15="Ítem",PRESUPUESTO!E15,"") | E21: =IF(D21="","",N(PRESUPUESTO!J15)) | G21: =IF(D21="","",D21*E21) | H21: =IF(D21="","",D21*N(F21)) | I21: =IF(D21="","",G21-H21) | P21: =IF(D21="","",SUM(J21:O21)) | Q21: =IF(D21="","",D21-P21) | R21: =IF(OR(D21="",N(D21)=0),"",P21/D21) | S21: =IF(D21="","",P21*N(F21)) | T21: =IF(D21="","",Q21*N(F21)) | AC21: =IF(X21="","",IFERROR(INDEX(t_Hora,MATCH(X21,t_Cargo,0)),0)) | AD21: =IF(X21="","",N(Z21)*IF(AA21="",IFERROR(INDEX(t_Horas,MATCH(X21,t_Cargo,0)),8),AA21)+N(AB21)) | AE21: =IF(X21="","",AC21*(N(Z21)*IF(AA21="",IFERROR(INDEX(t_Horas,MATCH(X21,t_Cargo,0)),8),AA21)+N(AB21)*(1+p_Extra)))
A22: =IF(PRESUPUESTO!$A16="Ítem",PRESUPUESTO!B16,"") | B22: =IF(PRESUPUESTO!C16="","",PRESUPUESTO!C16) | C22: =IF(PRESUPUESTO!$A16="Ítem",PRESUPUESTO!D16,"") | D22: =IF(PRESUPUESTO!$A16="Ítem",PRESUPUESTO!E16,"") | E22: =IF(D22="","",N(PRESUPUESTO!J16)) | G22: =IF(D22="","",D22*E22) | H22: =IF(D22="","",D22*N(F22)) | I22: =IF(D22="","",G22-H22) | P22: =IF(D22="","",SUM(J22:O22)) | Q22: =IF(D22="","",D22-P22) | R22: =IF(OR(D22="",N(D22)=0),"",P22/D22) | S22: =IF(D22="","",P22*N(F22)) | T22: =IF(D22="","",Q22*N(F22)) | AC22: =IF(X22="","",IFERROR(INDEX(t_Hora,MATCH(X22,t_Cargo,0)),0)) | AD22: =IF(X22="","",N(Z22)*IF(AA22="",IFERROR(INDEX(t_Horas,MATCH(X22,t_Cargo,0)),8),AA22)+N(AB22)) | AE22: =IF(X22="","",AC22*(N(Z22)*IF(AA22="",IFERROR(INDEX(t_Horas,MATCH(X22,t_Cargo,0)),8),AA22)+N(AB22)*(1+p_Extra)))
A23: =IF(PRESUPUESTO!$A17="Ítem",PRESUPUESTO!B17,"") | B23: =IF(PRESUPUESTO!C17="","",PRESUPUESTO!C17) | C23: =IF(PRESUPUESTO!$A17="Ítem",PRESUPUESTO!D17,"") | D23: =IF(PRESUPUESTO!$A17="Ítem",PRESUPUESTO!E17,"") | E23: =IF(D23="","",N(PRESUPUESTO!J17)) | G23: =IF(D23="","",D23*E23) | H23: =IF(D23="","",D23*N(F23)) | I23: =IF(D23="","",G23-H23) | P23: =IF(D23="","",SUM(J23:O23)) | Q23: =IF(D23="","",D23-P23) | R23: =IF(OR(D23="",N(D23)=0),"",P23/D23) | S23: =IF(D23="","",P23*N(F23)) | T23: =IF(D23="","",Q23*N(F23)) | AC23: =IF(X23="","",IFERROR(INDEX(t_Hora,MATCH(X23,t_Cargo,0)),0)) | AD23: =IF(X23="","",N(Z23)*IF(AA23="",IFERROR(INDEX(t_Horas,MATCH(X23,t_Cargo,0)),8),AA23)+N(AB23)) | AE23: =IF(X23="","",AC23*(N(Z23)*IF(AA23="",IFERROR(INDEX(t_Horas,MATCH(X23,t_Cargo,0)),8),AA23)+N(AB23)*(1+p_Extra)))
A24: =IF(PRESUPUESTO!$A18="Ítem",PRESUPUESTO!B18,"") | B24: =IF(PRESUPUESTO!C18="","",PRESUPUESTO!C18) | C24: =IF(PRESUPUESTO!$A18="Ítem",PRESUPUESTO!D18,"") | D24: =IF(PRESUPUESTO!$A18="Ítem",PRESUPUESTO!E18,"") | E24: =IF(D24="","",N(PRESUPUESTO!J18)) | G24: =IF(D24="","",D24*E24) | H24: =IF(D24="","",D24*N(F24)) | I24: =IF(D24="","",G24-H24) | P24: =IF(D24="","",SUM(J24:O24)) | Q24: =IF(D24="","",D24-P24) | R24: =IF(OR(D24="",N(D24)=0),"",P24/D24) | S24: =IF(D24="","",P24*N(F24)) | T24: =IF(D24="","",Q24*N(F24)) | AC24: =IF(X24="","",IFERROR(INDEX(t_Hora,MATCH(X24,t_Cargo,0)),0)) | AD24: =IF(X24="","",N(Z24)*IF(AA24="",IFERROR(INDEX(t_Horas,MATCH(X24,t_Cargo,0)),8),AA24)+N(AB24)) | AE24: =IF(X24="","",AC24*(N(Z24)*IF(AA24="",IFERROR(INDEX(t_Horas,MATCH(X24,t_Cargo,0)),8),AA24)+N(AB24)*(1+p_Extra)))
... A212: =IF(PRESUPUESTO!$A206="Ítem",PRESUPUESTO!B206,"") | B212: =IF(PRESUPUESTO!C206="","",PRESUPUESTO!C206) | C212: =IF(PRESUPUESTO!$A206="Ítem",PRESUPUESTO!D206,"") | D212: =IF(PRESUPUESTO!$A206="Ítem",PRESUPUESTO!E206,"") | E212: =IF(D212="","",N(PRESUPUESTO!J206)) | G212: =IF(D212="","",D212*E212) | H212: =IF(D212="","",D212*N(F212)) | I212: =IF(D212="","",G212-H212) | P212: =IF(D212="","",SUM(J212:O212)) | Q212: =IF(D212="","",D212-P212) | R212: =IF(OR(D212="",N(D212)=0),"",P212/D212) | S212: =IF(D212="","",P212*N(F212)) | T212: =IF(D212="","",Q212*N(F212)) | AC212: =IF(X212="","",IFERROR(INDEX(t_Hora,MATCH(X212,t_Cargo,0)),0)) | AD212: =IF(X212="","",N(Z212)*IF(AA212="",IFERROR(INDEX(t_Horas,MATCH(X212,t_Cargo,0)),8),AA212)+N(AB212)) | AE212: =IF(X212="","",AC212*(N(Z212)*IF(AA212="",IFERROR(INDEX(t_Horas,MATCH(X212,t_Cargo,0)),8),AA212)+N(AB212)*(1+p_Extra)))
AC213: =IF(X213="","",IFERROR(INDEX(t_Hora,MATCH(X213,t_Cargo,0)),0)) | AD213: =IF(X213="","",N(Z213)*IF(AA213="",IFERROR(INDEX(t_Horas,MATCH(X213,t_Cargo,0)),8),AA213)+N(AB213)) | AE213: =IF(X213="","",AC213*(N(Z213)*IF(AA213="",IFERROR(INDEX(t_Horas,MATCH(X213,t_Cargo,0)),8),AA213)+N(AB213)*(1+p_Extra)))
AC214: =IF(X214="","",IFERROR(INDEX(t_Hora,MATCH(X214,t_Cargo,0)),0)) | AD214: =IF(X214="","",N(Z214)*IF(AA214="",IFERROR(INDEX(t_Horas,MATCH(X214,t_Cargo,0)),8),AA214)+N(AB214)) | AE214: =IF(X214="","",AC214*(N(Z214)*IF(AA214="",IFERROR(INDEX(t_Horas,MATCH(X214,t_Cargo,0)),8),AA214)+N(AB214)*(1+p_Extra)))
AC215: =IF(X215="","",IFERROR(INDEX(t_Hora,MATCH(X215,t_Cargo,0)),0)) | AD215: =IF(X215="","",N(Z215)*IF(AA215="",IFERROR(INDEX(t_Horas,MATCH(X215,t_Cargo,0)),8),AA215)+N(AB215)) | AE215: =IF(X215="","",AC215*(N(Z215)*IF(AA215="",IFERROR(INDEX(t_Horas,MATCH(X215,t_Cargo,0)),8),AA215)+N(AB215)*(1+p_Extra)))
AC216: =IF(X216="","",IFERROR(INDEX(t_Hora,MATCH(X216,t_Cargo,0)),0)) | AD216: =IF(X216="","",N(Z216)*IF(AA216="",IFERROR(INDEX(t_Horas,MATCH(X216,t_Cargo,0)),8),AA216)+N(AB216)) | AE216: =IF(X216="","",AC216*(N(Z216)*IF(AA216="",IFERROR(INDEX(t_Horas,MATCH(X216,t_Cargo,0)),8),AA216)+N(AB216)*(1+p_Extra)))
AC217: =IF(X217="","",IFERROR(INDEX(t_Hora,MATCH(X217,t_Cargo,0)),0)) | AD217: =IF(X217="","",N(Z217)*IF(AA217="",IFERROR(INDEX(t_Horas,MATCH(X217,t_Cargo,0)),8),AA217)+N(AB217)) | AE217: =IF(X217="","",AC217*(N(Z217)*IF(AA217="",IFERROR(INDEX(t_Horas,MATCH(X217,t_Cargo,0)),8),AA217)+N(AB217)*(1+p_Extra)))
AC218: =IF(X218="","",IFERROR(INDEX(t_Hora,MATCH(X218,t_Cargo,0)),0)) | AD218: =IF(X218="","",N(Z218)*IF(AA218="",IFERROR(INDEX(t_Horas,MATCH(X218,t_Cargo,0)),8),AA218)+N(AB218)) | AE218: =IF(X218="","",AC218*(N(Z218)*IF(AA218="",IFERROR(INDEX(t_Horas,MATCH(X218,t_Cargo,0)),8),AA218)+N(AB218)*(1+p_Extra)))
AC219: =IF(X219="","",IFERROR(INDEX(t_Hora,MATCH(X219,t_Cargo,0)),0)) | AD219: =IF(X219="","",N(Z219)*IF(AA219="",IFERROR(INDEX(t_Horas,MATCH(X219,t_Cargo,0)),8),AA219)+N(AB219)) | AE219: =IF(X219="","",AC219*(N(Z219)*IF(AA219="",IFERROR(INDEX(t_Horas,MATCH(X219,t_Cargo,0)),8),AA219)+N(AB219)*(1+p_Extra)))
AC220: =IF(X220="","",IFERROR(INDEX(t_Hora,MATCH(X220,t_Cargo,0)),0)) | AD220: =IF(X220="","",N(Z220)*IF(AA220="",IFERROR(INDEX(t_Horas,MATCH(X220,t_Cargo,0)),8),AA220)+N(AB220)) | AE220: =IF(X220="","",AC220*(N(Z220)*IF(AA220="",IFERROR(INDEX(t_Horas,MATCH(X220,t_Cargo,0)),8),AA220)+N(AB220)*(1+p_Extra)))
AC221: =IF(X221="","",IFERROR(INDEX(t_Hora,MATCH(X221,t_Cargo,0)),0)) | AD221: =IF(X221="","",N(Z221)*IF(AA221="",IFERROR(INDEX(t_Horas,MATCH(X221,t_Cargo,0)),8),AA221)+N(AB221)) | AE221: =IF(X221="","",AC221*(N(Z221)*IF(AA221="",IFERROR(INDEX(t_Horas,MATCH(X221,t_Cargo,0)),8),AA221)+N(AB221)*(1+p_Extra)))
AC222: =IF(X222="","",IFERROR(INDEX(t_Hora,MATCH(X222,t_Cargo,0)),0)) | AD222: =IF(X222="","",N(Z222)*IF(AA222="",IFERROR(INDEX(t_Horas,MATCH(X222,t_Cargo,0)),8),AA222)+N(AB222)) | AE222: =IF(X222="","",AC222*(N(Z222)*IF(AA222="",IFERROR(INDEX(t_Horas,MATCH(X222,t_Cargo,0)),8),AA222)+N(AB222)*(1+p_Extra)))
AC223: =IF(X223="","",IFERROR(INDEX(t_Hora,MATCH(X223,t_Cargo,0)),0)) | AD223: =IF(X223="","",N(Z223)*IF(AA223="",IFERROR(INDEX(t_Horas,MATCH(X223,t_Cargo,0)),8),AA223)+N(AB223)) | AE223: =IF(X223="","",AC223*(N(Z223)*IF(AA223="",IFERROR(INDEX(t_Horas,MATCH(X223,t_Cargo,0)),8),AA223)+N(AB223)*(1+p_Extra)))
AC224: =IF(X224="","",IFERROR(INDEX(t_Hora,MATCH(X224,t_Cargo,0)),0)) | AD224: =IF(X224="","",N(Z224)*IF(AA224="",IFERROR(INDEX(t_Horas,MATCH(X224,t_Cargo,0)),8),AA224)+N(AB224)) | AE224: =IF(X224="","",AC224*(N(Z224)*IF(AA224="",IFERROR(INDEX(t_Horas,MATCH(X224,t_Cargo,0)),8),AA224)+N(AB224)*(1+p_Extra)))
... AC312: =IF(X312="","",IFERROR(INDEX(t_Hora,MATCH(X312,t_Cargo,0)),0)) | AD312: =IF(X312="","",N(Z312)*IF(AA312="",IFERROR(INDEX(t_Horas,MATCH(X312,t_Cargo,0)),8),AA312)+N(AB312)) | AE312: =IF(X312="","",AC312*(N(Z312)*IF(AA312="",IFERROR(INDEX(t_Horas,MATCH(X312,t_Cargo,0)),8),AA312)+N(AB312)*(1+p_Extra)))

Sheet GASTOS
D1: GASTOS DEL PROYECTO | F1: Aquí se escribe TODO lo que sale, una sola vez: una fila por ítem comprado o por pago. Con el código de 'Ítem' lo cuenta CONTROL DE MATERIALES; sin ítem queda como gasto general.
A2: INICIO | C2: TABLERO | D2: CRONOGRAMA | E2: PRESUPUESTO | F2: CORTES CLIENTE | H2: MANO DE OBRA | J2: ● GASTOS | K2: MATERIALES | L2: GUÍA
A4: TOTAL REGISTRADO → | J4: =SUM(J7:J5000) -> 0
A6: N° | B6: Fecha | C6: Tipo de gasto | D6: Proveedor / contratista | E6: Factura / OC (o 'Corte N') | F6: Ítem (opcional) | G6: Descripción | H6: Cantidad | I6: Valor unitario (precio real) | J6: Valor total | K6: Observaciones | L6: cat
A7: =IF(AND(B7="",C7=""),"",ROW()-6) | J7: =IF(I7="","",IF(H7="",1,H7)*I7) | L7: =IF(C7="","",IF(OR(C7="Material",C7="Equipo",C7="Suministro"),"Materiales y equipos",IF(C7="Mano de obra contratista","Mano de obra contratista",IF(C7="Transporte","Transporte y otros","Alquileres"))))
A8: =IF(AND(B8="",C8=""),"",ROW()-6) | J8: =IF(I8="","",IF(H8="",1,H8)*I8) | L8: =IF(C8="","",IF(OR(C8="Material",C8="Equipo",C8="Suministro"),"Materiales y equipos",IF(C8="Mano de obra contratista","Mano de obra contratista",IF(C8="Transporte","Transporte y otros","Alquileres"))))
A9: =IF(AND(B9="",C9=""),"",ROW()-6) | J9: =IF(I9="","",IF(H9="",1,H9)*I9) | L9: =IF(C9="","",IF(OR(C9="Material",C9="Equipo",C9="Suministro"),"Materiales y equipos",IF(C9="Mano de obra contratista","Mano de obra contratista",IF(C9="Transporte","Transporte y otros","Alquileres"))))
A10: =IF(AND(B10="",C10=""),"",ROW()-6) | J10: =IF(I10="","",IF(H10="",1,H10)*I10) | L10: =IF(C10="","",IF(OR(C10="Material",C10="Equipo",C10="Suministro"),"Materiales y equipos",IF(C10="Mano de obra contratista","Mano de obra contratista",IF(C10="Transporte","Transporte y otros","Alquileres"))))
A11: =IF(AND(B11="",C11=""),"",ROW()-6) | J11: =IF(I11="","",IF(H11="",1,H11)*I11) | L11: =IF(C11="","",IF(OR(C11="Material",C11="Equipo",C11="Suministro"),"Materiales y equipos",IF(C11="Mano de obra contratista","Mano de obra contratista",IF(C11="Transporte","Transporte y otros","Alquileres"))))
A12: =IF(AND(B12="",C12=""),"",ROW()-6) | J12: =IF(I12="","",IF(H12="",1,H12)*I12) | L12: =IF(C12="","",IF(OR(C12="Material",C12="Equipo",C12="Suministro"),"Materiales y equipos",IF(C12="Mano de obra contratista","Mano de obra contratista",IF(C12="Transporte","Transporte y otros","Alquileres"))))
A13: =IF(AND(B13="",C13=""),"",ROW()-6) | J13: =IF(I13="","",IF(H13="",1,H13)*I13) | L13: =IF(C13="","",IF(OR(C13="Material",C13="Equipo",C13="Suministro"),"Materiales y equipos",IF(C13="Mano de obra contratista","Mano de obra contratista",IF(C13="Transporte","Transporte y otros","Alquileres"))))
A14: =IF(AND(B14="",C14=""),"",ROW()-6) | J14: =IF(I14="","",IF(H14="",1,H14)*I14) | L14: =IF(C14="","",IF(OR(C14="Material",C14="Equipo",C14="Suministro"),"Materiales y equipos",IF(C14="Mano de obra contratista","Mano de obra contratista",IF(C14="Transporte","Transporte y otros","Alquileres"))))
A15: =IF(AND(B15="",C15=""),"",ROW()-6) | J15: =IF(I15="","",IF(H15="",1,H15)*I15) | L15: =IF(C15="","",IF(OR(C15="Material",C15="Equipo",C15="Suministro"),"Materiales y equipos",IF(C15="Mano de obra contratista","Mano de obra contratista",IF(C15="Transporte","Transporte y otros","Alquileres"))))
A16: =IF(AND(B16="",C16=""),"",ROW()-6) | J16: =IF(I16="","",IF(H16="",1,H16)*I16) | L16: =IF(C16="","",IF(OR(C16="Material",C16="Equipo",C16="Suministro"),"Materiales y equipos",IF(C16="Mano de obra contratista","Mano de obra contratista",IF(C16="Transporte","Transporte y otros","Alquileres"))))
A17: =IF(AND(B17="",C17=""),"",ROW()-6) | J17: =IF(I17="","",IF(H17="",1,H17)*I17) | L17: =IF(C17="","",IF(OR(C17="Material",C17="Equipo",C17="Suministro"),"Materiales y equipos",IF(C17="Mano de obra contratista","Mano de obra contratista",IF(C17="Transporte","Transporte y otros","Alquileres"))))
A18: =IF(AND(B18="",C18=""),"",ROW()-6) | J18: =IF(I18="","",IF(H18="",1,H18)*I18) | L18: =IF(C18="","",IF(OR(C18="Material",C18="Equipo",C18="Suministro"),"Materiales y equipos",IF(C18="Mano de obra contratista","Mano de obra contratista",IF(C18="Transporte","Transporte y otros","Alquileres"))))
... A1506: =IF(AND(B1506="",C1506=""),"",ROW()-6) | J1506: =IF(I1506="","",IF(H1506="",1,H1506)*I1506) | L1506: =IF(C1506="","",IF(OR(C1506="Material",C1506="Equipo",C1506="Suministro"),"Materiales y equipos",IF(C1506="Mano de obra contratista","Mano de obra contratista",IF(C1506="Transporte","Transporte y otros","Alquileres"))))

Sheet CONTROL DE MATERIALES
C1: CONTROL DE MATERIALES | H1: Hoja de solo lectura: se calcula desde GASTOS. Cantidad comprada, faltante, precio promedio real, último precio y alertas. Para que una compra cuente en un ítem, regístrela en GASTOS con su código de ítem y cantidad.
A2: INICIO | C2: TABLERO | E2: CRONOGRAMA | G2: PRESUPUESTO | I2: CORTES CLIENTE | K2: MANO DE OBRA | L2: GASTOS | N2: ● MATERIALES | P2: GUÍA
A4: FALTANTE POR COMPRAR ($) | C4: COMPRADO EN GASTOS ($) | F4: ÍTEMS COMPRADOS | I4: PARCIALES | L4: SIN COMPRAR | O4: ALERTAS DE PRECIO
A5: =SUM(R11:R210) -> 0 | C5: =SUMIFS(GASTOS!$J$7:$J$5000,GASTOS!$L$7:$L$5000,"Materiales y equipos") -> 0 | F5: =COUNTIF(S11:S210,"Comprado") -> 0 | I5: =COUNTIF(S11:S210,"Parcial") -> 0 | L5: =COUNTIF(S11:S210,"Sin comprar") -> 0 | O5: =COUNTIF(T11:T210,"Precio*") -> 0
A7: Única columna que se digita aquí: 'Cant. inicial' = lo comprado ANTES de usar GASTOS (viene prellenada con lo ejecutado en actas; corríjala si compró más). Toda compra nueva se escribe en GASTOS con su ítem, cantidad y precio real.
A9: Ítem | B9: Descripción | C9: Und | D9: Cant. necesaria | E9: Cant. inicial | F9: Cant. en GASTOS | G9: TOTAL comprado | H9: FALTANTE | I9: % comprado | J9: Ppto material | K9: Valor en GASTOS | L9: N° compras | M9: Precio promedio | N9: Último precio | O9: Último proveedor | P9: C.U. ppto (con IVA) | Q9: Var. precio | R9: Faltante valorizado | S9: Estado | T9: Alerta
A10: Materiales/equipos/suministros registrados en GASTOS SIN ítem asignado (suman valor, no cantidad) → | K10: =SUMIFS(GASTOS!$J$7:$J$5000,GASTOS!$L$7:$L$5000,"Materiales y equipos")-SUM(K11:K210) -> 0
A11: =IF(PRESUPUESTO!$A7="Ítem",PRESUPUESTO!B7,"") | B11: =IF(PRESUPUESTO!C7="","",PRESUPUESTO!C7) | C11: =IF(PRESUPUESTO!$A7="Ítem",PRESUPUESTO!D7,"") | D11: =IF(PRESUPUESTO!$A7<>"Ítem","",MAX(N(PRESUPUESTO!E7),N('CORTES CLIENTE'!L20))) | F11: =IF(D11="","",SUMIFS(GASTOS!$H$7:$H$5000,GASTOS!$F$7:$F$5000,$A11,GASTOS!$L$7:$L$5000,"Materiales y equipos")) | G11: =IF(D11="","",N(E11)+F11) | H11: =IF(OR(D11="",S11="Servicio"),"",MAX(0,D11-G11)) | I11: =IF(OR(D11="",S11="Servicio",N(D11)=0),"",MIN(1,G11/D11)) | J11: =IF(D11="","",PRESUPUESTO!O7) | K11: =IF(D11="","",SUMIFS(GASTOS!$J$7:$J$5000,GASTOS!$F$7:$F$5000,$A11,GASTOS!$L$7:$L$5000,"Materiales y equipos")) | L11: =IF(D11="","",COUNTIFS(GASTOS!$F$7:$F$5000,$A11,GASTOS!$L$7:$L$5000,"Materiales y equipos")) | M11: =IF(OR(D11="",N(F11)=0),"",K11/F11) | N11: =IF(OR(D11="",N(L11)=0),"",IFERROR(LOOKUP(2,1/((GASTOS!$F$7:$F$5000=$A11)*(GASTOS!$L$7:$L$5000="Materiales y equipos")*(GASTOS!$I$7:$I$5000<>"")),GASTOS!$I$7:$I$5000),"")) | O11: =IF(OR(D11="",N(L11)=0),"",IFERROR(LOOKUP(2,1/((GASTOS!$F$7:$F$5000=$A11)*(GASTOS!$L$7:$L$5000="Materiales y equipos")*(GASTOS!$I$7:$I$5000<>"")),GASTOS!$D$7:$D$5000),"")) | P11: =IF(D11="","",N(PRESUPUESTO!I7)) | Q11: =IF(OR(D11="",N11="",N(P11)=0),"",N11/P11-1) | R11: =IF(OR(D11="",S11="Servicio"),"",H11*IF(N11<>"",N11,P11)) | S11: =IF(D11="","",IF(N(PRESUPUESTO!H7)=0,"Servicio",IF(G11=0,"Sin comprar",IF(G11>=D11,"Comprado","Parcial")))) | T11: =IF(AND(ISNUMBER(Q11),N(Q11)>0.1),"Precio +"&TEXT(Q11,"0%"),"") | U11: =IF(OR(D11="",S11="Servicio"),"",MIN(G11,D11)*P11) | V11: =IF(OR(D11="",S11="Servicio"),"",D11*P11)
A12: =IF(PRESUPUESTO!$A8="Ítem",PRESUPUESTO!B8,"") | B12: =IF(PRESUPUESTO!C8="","",PRESUPUESTO!C8) | C12: =IF(PRESUPUESTO!$A8="Ítem",PRESUPUESTO!D8,"") | D12: =IF(PRESUPUESTO!$A8<>"Ítem","",MAX(N(PRESUPUESTO!E8),N('CORTES CLIENTE'!L21))) | F12: =IF(D12="","",SUMIFS(GASTOS!$H$7:$H$5000,GASTOS!$F$7:$F$5000,$A12,GASTOS!$L$7:$L$5000,"Materiales y equipos")) | G12: =IF(D12="","",N(E12)+F12) | H12: =IF(OR(D12="",S12="Servicio"),"",MAX(0,D12-G12)) | I12: =IF(OR(D12="",S12="Servicio",N(D12)=0),"",MIN(1,G12/D12)) | J12: =IF(D12="","",PRESUPUESTO!O8) | K12: =IF(D12="","",SUMIFS(GASTOS!$J$7:$J$5000,GASTOS!$F$7:$F$5000,$A12,GASTOS!$L$7:$L$5000,"Materiales y equipos")) | L12: =IF(D12="","",COUNTIFS(GASTOS!$F$7:$F$5000,$A12,GASTOS!$L$7:$L$5000,"Materiales y equipos")) | M12: =IF(OR(D12="",N(F12)=0),"",K12/F12) | N12: =IF(OR(D12="",N(L12)=0),"",IFERROR(LOOKUP(2,1/((GASTOS!$F$7:$F$5000=$A12)*(GASTOS!$L$7:$L$5000="Materiales y equipos")*(GASTOS!$I$7:$I$5000<>"")),GASTOS!$I$7:$I$5000),"")) | O12: =IF(OR(D12="",N(L12)=0),"",IFERROR(LOOKUP(2,1/((GASTOS!$F$7:$F$5000=$A12)*(GASTOS!$L$7:$L$5000="Materiales y equipos")*(GASTOS!$I$7:$I$5000<>"")),GASTOS!$D$7:$D$5000),"")) | P12: =IF(D12="","",N(PRESUPUESTO!I8)) | Q12: =IF(OR(D12="",N12="",N(P12)=0),"",N12/P12-1) | R12: =IF(OR(D12="",S12="Servicio"),"",H12*IF(N12<>"",N12,P12)) | S12: =IF(D12="","",IF(N(PRESUPUESTO!H8)=0,"Servicio",IF(G12=0,"Sin comprar",IF(G12>=D12,"Comprado","Parcial")))) | T12: =IF(AND(ISNUMBER(Q12),N(Q12)>0.1),"Precio +"&TEXT(Q12,"0%"),"") | U12: =IF(OR(D12="",S12="Servicio"),"",MIN(G12,D12)*P12) | V12: =IF(OR(D12="",S12="Servicio"),"",D12*P12)
A13: =IF(PRESUPUESTO!$A9="Ítem",PRESUPUESTO!B9,"") | B13: =IF(PRESUPUESTO!C9="","",PRESUPUESTO!C9) | C13: =IF(PRESUPUESTO!$A9="Ítem",PRESUPUESTO!D9,"") | D13: =IF(PRESUPUESTO!$A9<>"Ítem","",MAX(N(PRESUPUESTO!E9),N('CORTES CLIENTE'!L22))) | F13: =IF(D13="","",SUMIFS(GASTOS!$H$7:$H$5000,GASTOS!$F$7:$F$5000,$A13,GASTOS!$L$7:$L$5000,"Materiales y equipos")) | G13: =IF(D13="","",N(E13)+F13) | H13: =IF(OR(D13="",S13="Servicio"),"",MAX(0,D13-G13)) | I13: =IF(OR(D13="",S13="Servicio",N(D13)=0),"",MIN(1,G13/D13)) | J13: =IF(D13="","",PRESUPUESTO!O9) | K13: =IF(D13="","",SUMIFS(GASTOS!$J$7:$J$5000,GASTOS!$F$7:$F$5000,$A13,GASTOS!$L$7:$L$5000,"Materiales y equipos")) | L13: =IF(D13="","",COUNTIFS(GASTOS!$F$7:$F$5000,$A13,GASTOS!$L$7:$L$5000,"Materiales y equipos")) | M13: =IF(OR(D13="",N(F13)=0),"",K13/F13) | N13: =IF(OR(D13="",N(L13)=0),"",IFERROR(LOOKUP(2,1/((GASTOS!$F$7:$F$5000=$A13)*(GASTOS!$L$7:$L$5000="Materiales y equipos")*(GASTOS!$I$7:$I$5000<>"")),GASTOS!$I$7:$I$5000),"")) | O13: =IF(OR(D13="",N(L13)=0),"",IFERROR(LOOKUP(2,1/((GASTOS!$F$7:$F$5000=$A13)*(GASTOS!$L$7:$L$5000="Materiales y equipos")*(GASTOS!$I$7:$I$5000<>"")),GASTOS!$D$7:$D$5000),"")) | P13: =IF(D13="","",N(PRESUPUESTO!I9)) | Q13: =IF(OR(D13="",N13="",N(P13)=0),"",N13/P13-1) | R13: =IF(OR(D13="",S13="Servicio"),"",H13*IF(N13<>"",N13,P13)) | S13: =IF(D13="","",IF(N(PRESUPUESTO!H9)=0,"Servicio",IF(G13=0,"Sin comprar",IF(G13>=D13,"Comprado","Parcial")))) | T13: =IF(AND(ISNUMBER(Q13),N(Q13)>0.1),"Precio +"&TEXT(Q13,"0%"),"") | U13: =IF(OR(D13="",S13="Servicio"),"",MIN(G13,D13)*P13) | V13: =IF(OR(D13="",S13="Servicio"),"",D13*P13)
A14: =IF(PRESUPUESTO!$A10="Ítem",PRESUPUESTO!B10,"") | B14: =IF(PRESUPUESTO!C10="","",PRESUPUESTO!C10) | C14: =IF(PRESUPUESTO!$A10="Ítem",PRESUPUESTO!D10,"") | D14: =IF(PRESUPUESTO!$A10<>"Ítem","",MAX(N(PRESUPUESTO!E10),N('CORTES CLIENTE'!L23))) | F14: =IF(D14="","",SUMIFS(GASTOS!$H$7:$H$5000,GASTOS!$F$7:$F$5000,$A14,GASTOS!$L$7:$L$5000,"Materiales y equipos")) | G14: =IF(D14="","",N(E14)+F14) | H14: =IF(OR(D14="",S14="Servicio"),"",MAX(0,D14-G14)) | I14: =IF(OR(D14="",S14="Servicio",N(D14)=0),"",MIN(1,G14/D14)) | J14: =IF(D14="","",PRESUPUESTO!O10) | K14: =IF(D14="","",SUMIFS(GASTOS!$J$7:$J$5000,GASTOS!$F$7:$F$5000,$A14,GASTOS!$L$7:$L$5000,"Materiales y equipos")) | L14: =IF(D14="","",COUNTIFS(GASTOS!$F$7:$F$5000,$A14,GASTOS!$L$7:$L$5000,"Materiales y equipos")) | M14: =IF(OR(D14="",N(F14)=0),"",K14/F14) | N14: =IF(OR(D14="",N(L14)=0),"",IFERROR(LOOKUP(2,1/((GASTOS!$F$7:$F$5000=$A14)*(GASTOS!$L$7:$L$5000="Materiales y equipos")*(GASTOS!$I$7:$I$5000<>"")),GASTOS!$I$7:$I$5000),"")) | O14: =IF(OR(D14="",N(L14)=0),"",IFERROR(LOOKUP(2,1/((GASTOS!$F$7:$F$5000=$A14)*(GASTOS!$L$7:$L$5000="Materiales y equipos")*(GASTOS!$I$7:$I$5000<>"")),GASTOS!$D$7:$D$5000),"")) | P14: =IF(D14="","",N(PRESUPUESTO!I10)) | Q14: =IF(OR(D14="",N14="",N(P14)=0),"",N14/P14-1) | R14: =IF(OR(D14="",S14="Servicio"),"",H14*IF(N14<>"",N14,P14)) | S14: =IF(D14="","",IF(N(PRESUPUESTO!H10)=0,"Servicio",IF(G14=0,"Sin comprar",IF(G14>=D14,"Comprado","Parcial")))) | T14: =IF(AND(ISNUMBER(Q14),N(Q14)>0.1),"Precio +"&TEXT(Q14,"0%"),"") | U14: =IF(OR(D14="",S14="Servicio"),"",MIN(G14,D14)*P14) | V14: =IF(OR(D14="",S14="Servicio"),"",D14*P14)
A15: =IF(PRESUPUESTO!$A11="Ítem",PRESUPUESTO!B11,"") | B15: =IF(PRESUPUESTO!C11="","",PRESUPUESTO!C11) | C15: =IF(PRESUPUESTO!$A11="Ítem",PRESUPUESTO!D11,"") | D15: =IF(PRESUPUESTO!$A11<>"Ítem","",MAX(N(PRESUPUESTO!E11),N('CORTES CLIENTE'!L24))) | F15: =IF(D15="","",SUMIFS(GASTOS!$H$7:$H$5000,GASTOS!$F$7:$F$5000,$A15,GASTOS!$L$7:$L$5000,"Materiales y equipos")) | G15: =IF(D15="","",N(E15)+F15) | H15: =IF(OR(D15="",S15="Servicio"),"",MAX(0,D15-G15)) | I15: =IF(OR(D15="",S15="Servicio",N(D15)=0),"",MIN(1,G15/D15)) | J15: =IF(D15="","",PRESUPUESTO!O11) | K15: =IF(D15="","",SUMIFS(GASTOS!$J$7:$J$5000,GASTOS!$F$7:$F$5000,$A15,GASTOS!$L$7:$L$5000,"Materiales y equipos")) | L15: =IF(D15="","",COUNTIFS(GASTOS!$F$7:$F$5000,$A15,GASTOS!$L$7:$L$5000,"Materiales y equipos")) | M15: =IF(OR(D15="",N(F15)=0),"",K15/F15) | N15: =IF(OR(D15="",N(L15)=0),"",IFERROR(LOOKUP(2,1/((GASTOS!$F$7:$F$5000=$A15)*(GASTOS!$L$7:$L$5000="Materiales y equipos")*(GASTOS!$I$7:$I$5000<>"")),GASTOS!$I$7:$I$5000),"")) | O15: =IF(OR(D15="",N(L15)=0),"",IFERROR(LOOKUP(2,1/((GASTOS!$F$7:$F$5000=$A15)*(GASTOS!$L$7:$L$5000="Materiales y equipos")*(GASTOS!$I$7:$I$5000<>"")),GASTOS!$D$7:$D$5000),"")) | P15: =IF(D15="","",N(PRESUPUESTO!I11)) | Q15: =IF(OR(D15="",N15="",N(P15)=0),"",N15/P15-1) | R15: =IF(OR(D15="",S15="Servicio"),"",H15*IF(N15<>"",N15,P15)) | S15: =IF(D15="","",IF(N(PRESUPUESTO!H11)=0,"Servicio",IF(G15=0,"Sin comprar",IF(G15>=D15,"Comprado","Parcial")))) | T15: =IF(AND(ISNUMBER(Q15),N(Q15)>0.1),"Precio +"&TEXT(Q15,"0%"),"") | U15: =IF(OR(D15="",S15="Servicio"),"",MIN(G15,D15)*P15) | V15: =IF(OR(D15="",S15="Servicio"),"",D15*P15)
A16: =IF(PRESUPUESTO!$A12="Ítem",PRESUPUESTO!B12,"") | B16: =IF(PRESUPUESTO!C12="","",PRESUPUESTO!C12) | C16: =IF(PRESUPUESTO!$A12="Ítem",PRESUPUESTO!D12,"") | D16: =IF(PRESUPUESTO!$A12<>"Ítem","",MAX(N(PRESUPUESTO!E12),N('CORTES CLIENTE'!L25))) | F16: =IF(D16="","",SUMIFS(GASTOS!$H$7:$H$5000,GASTOS!$F$7:$F$5000,$A16,GASTOS!$L$7:$L$5000,"Materiales y equipos")) | G16: =IF(D16="","",N(E16)+F16) | H16: =IF(OR(D16="",S16="Servicio"),"",MAX(0,D16-G16)) | I16: =IF(OR(D16="",S16="Servicio",N(D16)=0),"",MIN(1,G16/D16)) | J16: =IF(D16="","",PRESUPUESTO!O12) | K16: =IF(D16="","",SUMIFS(GASTOS!$J$7:$J$5000,GASTOS!$F$7:$F$5000,$A16,GASTOS!$L$7:$L$5000,"Materiales y equipos")) | L16: =IF(D16="","",COUNTIFS(GASTOS!$F$7:$F$5000,$A16,GASTOS!$L$7:$L$5000,"Materiales y equipos")) | M16: =IF(OR(D16="",N(F16)=0),"",K16/F16) | N16: =IF(OR(D16="",N(L16)=0),"",IFERROR(LOOKUP(2,1/((GASTOS!$F$7:$F$5000=$A16)*(GASTOS!$L$7:$L$5000="Materiales y equipos")*(GASTOS!$I$7:$I$5000<>"")),GASTOS!$I$7:$I$5000),"")) | O16: =IF(OR(D16="",N(L16)=0),"",IFERROR(LOOKUP(2,1/((GASTOS!$F$7:$F$5000=$A16)*(GASTOS!$L$7:$L$5000="Materiales y equipos")*(GASTOS!$I$7:$I$5000<>"")),GASTOS!$D$7:$D$5000),"")) | P16: =IF(D16="","",N(PRESUPUESTO!I12)) | Q16: =IF(OR(D16="",N16="",N(P16)=0),"",N16/P16-1) | R16: =IF(OR(D16="",S16="Servicio"),"",H16*IF(N16<>"",N16,P16)) | S16: =IF(D16="","",IF(N(PRESUPUESTO!H12)=0,"Servicio",IF(G16=0,"Sin comprar",IF(G16>=D16,"Comprado","Parcial")))) | T16: =IF(AND(ISNUMBER(Q16),N(Q16)>0.1),"Precio +"&TEXT(Q16,"0%"),"") | U16: =IF(OR(D16="",S16="Servicio"),"",MIN(G16,D16)*P16) | V16: =IF(OR(D16="",S16="Servicio"),"",D16*P16)
A17: =IF(PRESUPUESTO!$A13="Ítem",PRESUPUESTO!B13,"") | B17: =IF(PRESUPUESTO!C13="","",PRESUPUESTO!C13) | C17: =IF(PRESUPUESTO!$A13="Ítem",PRESUPUESTO!D13,"") | D17: =IF(PRESUPUESTO!$A13<>"Ítem","",MAX(N(PRESUPUESTO!E13),N('CORTES CLIENTE'!L26))) | F17: =IF(D17="","",SUMIFS(GASTOS!$H$7:$H$5000,GASTOS!$F$7:$F$5000,$A17,GASTOS!$L$7:$L$5000,"Materiales y equipos")) | G17: =IF(D17="","",N(E17)+F17) | H17: =IF(OR(D17="",S17="Servicio"),"",MAX(0,D17-G17)) | I17: =IF(OR(D17="",S17="Servicio",N(D17)=0),"",MIN(1,G17/D17)) | J17: =IF(D17="","",PRESUPUESTO!O13) | K17: =IF(D17="","",SUMIFS(GASTOS!$J$7:$J$5000,GASTOS!$F$7:$F$5000,$A17,GASTOS!$L$7:$L$5000,"Materiales y equipos")) | L17: =IF(D17="","",COUNTIFS(GASTOS!$F$7:$F$5000,$A17,GASTOS!$L$7:$L$5000,"Materiales y equipos")) | M17: =IF(OR(D17="",N(F17)=0),"",K17/F17) | N17: =IF(OR(D17="",N(L17)=0),"",IFERROR(LOOKUP(2,1/((GASTOS!$F$7:$F$5000=$A17)*(GASTOS!$L$7:$L$5000="Materiales y equipos")*(GASTOS!$I$7:$I$5000<>"")),GASTOS!$I$7:$I$5000),"")) | O17: =IF(OR(D17="",N(L17)=0),"",IFERROR(LOOKUP(2,1/((GASTOS!$F$7:$F$5000=$A17)*(GASTOS!$L$7:$L$5000="Materiales y equipos")*(GASTOS!$I$7:$I$5000<>"")),GASTOS!$D$7:$D$5000),"")) | P17: =IF(D17="","",N(PRESUPUESTO!I13)) | Q17: =IF(OR(D17="",N17="",N(P17)=0),"",N17/P17-1) | R17: =IF(OR(D17="",S17="Servicio"),"",H17*IF(N17<>"",N17,P17)) | S17: =IF(D17="","",IF(N(PRESUPUESTO!H13)=0,"Servicio",IF(G17=0,"Sin comprar",IF(G17>=D17,"Comprado","Parcial")))) | T17: =IF(AND(ISNUMBER(Q17),N(Q17)>0.1),"Precio +"&TEXT(Q17,"0%"),"") | U17: =IF(OR(D17="",S17="Servicio"),"",MIN(G17,D17)*P17) | V17: =IF(OR(D17="",S17="Servicio"),"",D17*P17)
A18: =IF(PRESUPUESTO!$A14="Ítem",PRESUPUESTO!B14,"") | B18: =IF(PRESUPUESTO!C14="","",PRESUPUESTO!C14) | C18: =IF(PRESUPUESTO!$A14="Ítem",PRESUPUESTO!D14,"") | D18: =IF(PRESUPUESTO!$A14<>"Ítem","",MAX(N(PRESUPUESTO!E14),N('CORTES CLIENTE'!L27))) | F18: =IF(D18="","",SUMIFS(GASTOS!$H$7:$H$5000,GASTOS!$F$7:$F$5000,$A18,GASTOS!$L$7:$L$5000,"Materiales y equipos")) | G18: =IF(D18="","",N(E18)+F18) | H18: =IF(OR(D18="",S18="Servicio"),"",MAX(0,D18-G18)) | I18: =IF(OR(D18="",S18="Servicio",N(D18)=0),"",MIN(1,G18/D18)) | J18: =IF(D18="","",PRESUPUESTO!O14) | K18: =IF(D18="","",SUMIFS(GASTOS!$J$7:$J$5000,GASTOS!$F$7:$F$5000,$A18,GASTOS!$L$7:$L$5000,"Materiales y equipos")) | L18: =IF(D18="","",COUNTIFS(GASTOS!$F$7:$F$5000,$A18,GASTOS!$L$7:$L$5000,"Materiales y equipos")) | M18: =IF(OR(D18="",N(F18)=0),"",K18/F18) | N18: =IF(OR(D18="",N(L18)=0),"",IFERROR(LOOKUP(2,1/((GASTOS!$F$7:$F$5000=$A18)*(GASTOS!$L$7:$L$5000="Materiales y equipos")*(GASTOS!$I$7:$I$5000<>"")),GASTOS!$I$7:$I$5000),"")) | O18: =IF(OR(D18="",N(L18)=0),"",IFERROR(LOOKUP(2,1/((GASTOS!$F$7:$F$5000=$A18)*(GASTOS!$L$7:$L$5000="Materiales y equipos")*(GASTOS!$I$7:$I$5000<>"")),GASTOS!$D$7:$D$5000),"")) | P18: =IF(D18="","",N(PRESUPUESTO!I14)) | Q18: =IF(OR(D18="",N18="",N(P18)=0),"",N18/P18-1) | R18: =IF(OR(D18="",S18="Servicio"),"",H18*IF(N18<>"",N18,P18)) | S18: =IF(D18="","",IF(N(PRESUPUESTO!H14)=0,"Servicio",IF(G18=0,"Sin comprar",IF(G18>=D18,"Comprado","Parcial")))) | T18: =IF(AND(ISNUMBER(Q18),N(Q18)>0.1),"Precio +"&TEXT(Q18,"0%"),"") | U18: =IF(OR(D18="",S18="Servicio"),"",MIN(G18,D18)*P18) | V18: =IF(OR(D18="",S18="Servicio"),"",D18*P18)
A19: =IF(PRESUPUESTO!$A15="Ítem",PRESUPUESTO!B15,"") | B19: =IF(PRESUPUESTO!C15="","",PRESUPUESTO!C15) | C19: =IF(PRESUPUESTO!$A15="Ítem",PRESUPUESTO!D15,"") | D19: =IF(PRESUPUESTO!$A15<>"Ítem","",MAX(N(PRESUPUESTO!E15),N('CORTES CLIENTE'!L28))) | F19: =IF(D19="","",SUMIFS(GASTOS!$H$7:$H$5000,GASTOS!$F$7:$F$5000,$A19,GASTOS!$L$7:$L$5000,"Materiales y equipos")) | G19: =IF(D19="","",N(E19)+F19) | H19: =IF(OR(D19="",S19="Servicio"),"",MAX(0,D19-G19)) | I19: =IF(OR(D19="",S19="Servicio",N(D19)=0),"",MIN(1,G19/D19)) | J19: =IF(D19="","",PRESUPUESTO!O15) | K19: =IF(D19="","",SUMIFS(GASTOS!$J$7:$J$5000,GASTOS!$F$7:$F$5000,$A19,GASTOS!$L$7:$L$5000,"Materiales y equipos")) | L19: =IF(D19="","",COUNTIFS(GASTOS!$F$7:$F$5000,$A19,GASTOS!$L$7:$L$5000,"Materiales y equipos")) | M19: =IF(OR(D19="",N(F19)=0),"",K19/F19) | N19: =IF(OR(D19="",N(L19)=0),"",IFERROR(LOOKUP(2,1/((GASTOS!$F$7:$F$5000=$A19)*(GASTOS!$L$7:$L$5000="Materiales y equipos")*(GASTOS!$I$7:$I$5000<>"")),GASTOS!$I$7:$I$5000),"")) | O19: =IF(OR(D19="",N(L19)=0),"",IFERROR(LOOKUP(2,1/((GASTOS!$F$7:$F$5000=$A19)*(GASTOS!$L$7:$L$5000="Materiales y equipos")*(GASTOS!$I$7:$I$5000<>"")),GASTOS!$D$7:$D$5000),"")) | P19: =IF(D19="","",N(PRESUPUESTO!I15)) | Q19: =IF(OR(D19="",N19="",N(P19)=0),"",N19/P19-1) | R19: =IF(OR(D19="",S19="Servicio"),"",H19*IF(N19<>"",N19,P19)) | S19: =IF(D19="","",IF(N(PRESUPUESTO!H15)=0,"Servicio",IF(G19=0,"Sin comprar",IF(G19>=D19,"Comprado","Parcial")))) | T19: =IF(AND(ISNUMBER(Q19),N(Q19)>0.1),"Precio +"&TEXT(Q19,"0%"),"") | U19: =IF(OR(D19="",S19="Servicio"),"",MIN(G19,D19)*P19) | V19: =IF(OR(D19="",S19="Servicio"),"",D19*P19)
A20: =IF(PRESUPUESTO!$A16="Ítem",PRESUPUESTO!B16,"") | B20: =IF(PRESUPUESTO!C16="","",PRESUPUESTO!C16) | C20: =IF(PRESUPUESTO!$A16="Ítem",PRESUPUESTO!D16,"") | D20: =IF(PRESUPUESTO!$A16<>"Ítem","",MAX(N(PRESUPUESTO!E16),N('CORTES CLIENTE'!L29))) | F20: =IF(D20="","",SUMIFS(GASTOS!$H$7:$H$5000,GASTOS!$F$7:$F$5000,$A20,GASTOS!$L$7:$L$5000,"Materiales y equipos")) | G20: =IF(D20="","",N(E20)+F20) | H20: =IF(OR(D20="",S20="Servicio"),"",MAX(0,D20-G20)) | I20: =IF(OR(D20="",S20="Servicio",N(D20)=0),"",MIN(1,G20/D20)) | J20: =IF(D20="","",PRESUPUESTO!O16) | K20: =IF(D20="","",SUMIFS(GASTOS!$J$7:$J$5000,GASTOS!$F$7:$F$5000,$A20,GASTOS!$L$7:$L$5000,"Materiales y equipos")) | L20: =IF(D20="","",COUNTIFS(GASTOS!$F$7:$F$5000,$A20,GASTOS!$L$7:$L$5000,"Materiales y equipos")) | M20: =IF(OR(D20="",N(F20)=0),"",K20/F20) | N20: =IF(OR(D20="",N(L20)=0),"",IFERROR(LOOKUP(2,1/((GASTOS!$F$7:$F$5000=$A20)*(GASTOS!$L$7:$L$5000="Materiales y equipos")*(GASTOS!$I$7:$I$5000<>"")),GASTOS!$I$7:$I$5000),"")) | O20: =IF(OR(D20="",N(L20)=0),"",IFERROR(LOOKUP(2,1/((GASTOS!$F$7:$F$5000=$A20)*(GASTOS!$L$7:$L$5000="Materiales y equipos")*(GASTOS!$I$7:$I$5000<>"")),GASTOS!$D$7:$D$5000),"")) | P20: =IF(D20="","",N(PRESUPUESTO!I16)) | Q20: =IF(OR(D20="",N20="",N(P20)=0),"",N20/P20-1) | R20: =IF(OR(D20="",S20="Servicio"),"",H20*IF(N20<>"",N20,P20)) | S20: =IF(D20="","",IF(N(PRESUPUESTO!H16)=0,"Servicio",IF(G20=0,"Sin comprar",IF(G20>=D20,"Comprado","Parcial")))) | T20: =IF(AND(ISNUMBER(Q20),N(Q20)>0.1),"Precio +"&TEXT(Q20,"0%"),"") | U20: =IF(OR(D20="",S20="Servicio"),"",MIN(G20,D20)*P20) | V20: =IF(OR(D20="",S20="Servicio"),"",D20*P20)
A21: =IF(PRESUPUESTO!$A17="Ítem",PRESUPUESTO!B17,"") | B21: =IF(PRESUPUESTO!C17="","",PRESUPUESTO!C17) | C21: =IF(PRESUPUESTO!$A17="Ítem",PRESUPUESTO!D17,"") | D21: =IF(PRESUPUESTO!$A17<>"Ítem","",MAX(N(PRESUPUESTO!E17),N('CORTES CLIENTE'!L30))) | F21: =IF(D21="","",SUMIFS(GASTOS!$H$7:$H$5000,GASTOS!$F$7:$F$5000,$A21,GASTOS!$L$7:$L$5000,"Materiales y equipos")) | G21: =IF(D21="","",N(E21)+F21) | H21: =IF(OR(D21="",S21="Servicio"),"",MAX(0,D21-G21)) | I21: =IF(OR(D21="",S21="Servicio",N(D21)=0),"",MIN(1,G21/D21)) | J21: =IF(D21="","",PRESUPUESTO!O17) | K21: =IF(D21="","",SUMIFS(GASTOS!$J$7:$J$5000,GASTOS!$F$7:$F$5000,$A21,GASTOS!$L$7:$L$5000,"Materiales y equipos")) | L21: =IF(D21="","",COUNTIFS(GASTOS!$F$7:$F$5000,$A21,GASTOS!$L$7:$L$5000,"Materiales y equipos")) | M21: =IF(OR(D21="",N(F21)=0),"",K21/F21) | N21: =IF(OR(D21="",N(L21)=0),"",IFERROR(LOOKUP(2,1/((GASTOS!$F$7:$F$5000=$A21)*(GASTOS!$L$7:$L$5000="Materiales y equipos")*(GASTOS!$I$7:$I$5000<>"")),GASTOS!$I$7:$I$5000),"")) | O21: =IF(OR(D21="",N(L21)=0),"",IFERROR(LOOKUP(2,1/((GASTOS!$F$7:$F$5000=$A21)*(GASTOS!$L$7:$L$5000="Materiales y equipos")*(GASTOS!$I$7:$I$5000<>"")),GASTOS!$D$7:$D$5000),"")) | P21: =IF(D21="","",N(PRESUPUESTO!I17)) | Q21: =IF(OR(D21="",N21="",N(P21)=0),"",N21/P21-1) | R21: =IF(OR(D21="",S21="Servicio"),"",H21*IF(N21<>"",N21,P21)) | S21: =IF(D21="","",IF(N(PRESUPUESTO!H17)=0,"Servicio",IF(G21=0,"Sin comprar",IF(G21>=D21,"Comprado","Parcial")))) | T21: =IF(AND(ISNUMBER(Q21),N(Q21)>0.1),"Precio +"&TEXT(Q21,"0%"),"") | U21: =IF(OR(D21="",S21="Servicio"),"",MIN(G21,D21)*P21) | V21: =IF(OR(D21="",S21="Servicio"),"",D21*P21)
A22: =IF(PRESUPUESTO!$A18="Ítem",PRESUPUESTO!B18,"") | B22: =IF(PRESUPUESTO!C18="","",PRESUPUESTO!C18) | C22: =IF(PRESUPUESTO!$A18="Ítem",PRESUPUESTO!D18,"") | D22: =IF(PRESUPUESTO!$A18<>"Ítem","",MAX(N(PRESUPUESTO!E18),N('CORTES CLIENTE'!L31))) | F22: =IF(D22="","",SUMIFS(GASTOS!$H$7:$H$5000,GASTOS!$F$7:$F$5000,$A22,GASTOS!$L$7:$L$5000,"Materiales y equipos")) | G22: =IF(D22="","",N(E22)+F22) | H22: =IF(OR(D22="",S22="Servicio"),"",MAX(0,D22-G22)) | I22: =IF(OR(D22="",S22="Servicio",N(D22)=0),"",MIN(1,G22/D22)) | J22: =IF(D22="","",PRESUPUESTO!O18) | K22: =IF(D22="","",SUMIFS(GASTOS!$J$7:$J$5000,GASTOS!$F$7:$F$5000,$A22,GASTOS!$L$7:$L$5000,"Materiales y equipos")) | L22: =IF(D22="","",COUNTIFS(GASTOS!$F$7:$F$5000,$A22,GASTOS!$L$7:$L$5000,"Materiales y equipos")) | M22: =IF(OR(D22="",N(F22)=0),"",K22/F22) | N22: =IF(OR(D22="",N(L22)=0),"",IFERROR(LOOKUP(2,1/((GASTOS!$F$7:$F$5000=$A22)*(GASTOS!$L$7:$L$5000="Materiales y equipos")*(GASTOS!$I$7:$I$5000<>"")),GASTOS!$I$7:$I$5000),"")) | O22: =IF(OR(D22="",N(L22)=0),"",IFERROR(LOOKUP(2,1/((GASTOS!$F$7:$F$5000=$A22)*(GASTOS!$L$7:$L$5000="Materiales y equipos")*(GASTOS!$I$7:$I$5000<>"")),GASTOS!$D$7:$D$5000),"")) | P22: =IF(D22="","",N(PRESUPUESTO!I18)) | Q22: =IF(OR(D22="",N22="",N(P22)=0),"",N22/P22-1) | R22: =IF(OR(D22="",S22="Servicio"),"",H22*IF(N22<>"",N22,P22)) | S22: =IF(D22="","",IF(N(PRESUPUESTO!H18)=0,"Servicio",IF(G22=0,"Sin comprar",IF(G22>=D22,"Comprado","Parcial")))) | T22: =IF(AND(ISNUMBER(Q22),N(Q22)>0.1),"Precio +"&TEXT(Q22,"0%"),"") | U22: =IF(OR(D22="",S22="Servicio"),"",MIN(G22,D22)*P22) | V22: =IF(OR(D22="",S22="Servicio"),"",D22*P22)
... A210: =IF(PRESUPUESTO!$A206="Ítem",PRESUPUESTO!B206,"") | B210: =IF(PRESUPUESTO!C206="","",PRESUPUESTO!C206) | C210: =IF(PRESUPUESTO!$A206="Ítem",PRESUPUESTO!D206,"") | D210: =IF(PRESUPUESTO!$A206<>"Ítem","",MAX(N(PRESUPUESTO!E206),N('CORTES CLIENTE'!L219))) | F210: =IF(D210="","",SUMIFS(GASTOS!$H$7:$H$5000,GASTOS!$F$7:$F$5000,$A210,GASTOS!$L$7:$L$5000,"Materiales y equipos")) | G210: =IF(D210="","",N(E210)+F210) | H210: =IF(OR(D210="",S210="Servicio"),"",MAX(0,D210-G210)) | I210: =IF(OR(D210="",S210="Servicio",N(D210)=0),"",MIN(1,G210/D210)) | J210: =IF(D210="","",PRESUPUESTO!O206) | K210: =IF(D210="","",SUMIFS(GASTOS!$J$7:$J$5000,GASTOS!$F$7:$F$5000,$A210,GASTOS!$L$7:$L$5000,"Materiales y equipos")) | L210: =IF(D210="","",COUNTIFS(GASTOS!$F$7:$F$5000,$A210,GASTOS!$L$7:$L$5000,"Materiales y equipos")) | M210: =IF(OR(D210="",N(F210)=0),"",K210/F210) | N210: =IF(OR(D210="",N(L210)=0),"",IFERROR(LOOKUP(2,1/((GASTOS!$F$7:$F$5000=$A210)*(GASTOS!$L$7:$L$5000="Materiales y equipos")*(GASTOS!$I$7:$I$5000<>"")),GASTOS!$I$7:$I$5000),"")) | O210: =IF(OR(D210="",N(L210)=0),"",IFERROR(LOOKUP(2,1/((GASTOS!$F$7:$F$5000=$A210)*(GASTOS!$L$7:$L$5000="Materiales y equipos")*(GASTOS!$I$7:$I$5000<>"")),GASTOS!$D$7:$D$5000),"")) | P210: =IF(D210="","",N(PRESUPUESTO!I206)) | Q210: =IF(OR(D210="",N210="",N(P210)=0),"",N210/P210-1) | R210: =IF(OR(D210="",S210="Servicio"),"",H210*IF(N210<>"",N210,P210)) | S210: =IF(D210="","",IF(N(PRESUPUESTO!H206)=0,"Servicio",IF(G210=0,"Sin comprar",IF(G210>=D210,"Comprado","Parcial")))) | T210: =IF(AND(ISNUMBER(Q210),N(Q210)>0.1),"Precio +"&TEXT(Q210,"0%"),"") | U210: =IF(OR(D210="",S210="Servicio"),"",MIN(G210,D210)*P210) | V210: =IF(OR(D210="",S210="Servicio"),"",D210*P210)

Sheet GUÍA APP
D1: GUÍA PARA EL DESARROLLO WEB | E1: Cada hoja de este libro equivale a un módulo/tabla de la aplicación. Las fórmulas son las reglas de negocio.
B2: INICIO | C2: TABLERO | D2: CRONOGRAMA | E2: PRESUPUESTO | F2: CORTES CLIENTE | G2: MANO DE OBRA | H2: GASTOS | I2: MATERIALES | J2: ● GUÍA
B4: Hoja Excel | C4: Tabla / entidad (BD) | D4: Campos principales | E4: Reglas de negocio (fórmulas)
B5: INICIO | C5: proyectos parametros_proyecto tarifas_tecnicos | D5: nombre, cliente, ciudad, cotización, fechas, director, comercial, contratista, estado · %A, %I, %U, IVA, IVA a materiales, %anticipo, %impuestos, %pólizas, %legales · cargo, valor_hora, horas_dia | E5: Total contrato = CD + CD·A + CD·I + CD·U + CD·U·IVA. Ingreso sin IVA = CD·(1+A+I+U). Anticipo = Total·%anticipo.
B6: PRESUPUESTO | C6: items_presupuesto | D6: proyecto_id, tipo (capítulo/ítem), código, descripción, und, cantidad, pu_venta, cu_material, cu_mano_obra, cu_transporte, concepto_alquiler, cu_alquiler, orden | E6: CU material c/IVA = CU·(1+IVA) si aplica. Costo total = cant·(mat c/IVA + MO + transp + alq). Margen = venta − costo.
B7: CORTES CLIENTE | C7: cortes_cliente (cabecera) cortes_cliente_detalle | D7: Cabecera: n_corte, fecha, n_factura, fecha_factura, estado, valor_recaudado. Detalle: corte_id, item_id, cantidad | E7: Costo directo corte = Σ cant·PU venta. Acta = CD·(1+A+I+U) + CD·U·IVA. Amortización = −Acta·%anticipo. Pendiente ítem = cant contrato − Σ cortes (negativo = mayor cantidad).
B8: MANO DE OBRA | C8: contratos_mo (pu por ítem) cortes_mo + cortes_mo_detalle registro_mo_propia | D8: Contratista: item_id, pu_contratista · n_corte, fecha, n_cuenta_cobro, cantidades. Propia: fecha, técnico, cargo_id, item_id (opc.), días, horas_dia (opc.), horas_extra | E8: Ahorro = cant·(PU ppto − PU contratista). Valor corte = Σ cant·PU contratista. Pagado = Σ gastos tipo MO con 'Corte N'. MO propia = valor_hora·(días·horas_día + extra·(1+%recargo)).
B9: GASTOS | C9: gastos | D9: fecha, tipo (material/equipo/suministro/alquiler/transporte/MO contratista), proveedor, documento (factura/OC/corte), item_id (opc.), descripción, cantidad, valor_unitario | E9: Fuente única de todo el dinero que sale. Una fila por ítem comprado o pago, con su precio real; no se corrigen compras viejas. Categoría de costo = f(tipo).
B10: CONTROL DE MATERIALES | C10: (vista por ítem) | D10: cant_necesaria, cant_inicial, cant_registrada, faltante, precio_promedio, último_precio, último_proveedor | E10: Necesaria = MAX(contrato, ejecutado). Faltante = necesaria − (inicial + registrada). Precio promedio = Σvalor/Σcant. Faltante se valoriza al último precio (o al ppto). Alerta si último precio > ppto +10%.
B11: CRONOGRAMA | C11: actividades_cronograma | D11: id, fase, actividad, tipo (hito/gestión/compra/instalación/pruebas), responsable, frente (capítulo), predecesora_id, inicio_fijo, duración, inicio_real, fin_real, %_manual | E11: Inicio = real › fijo › fin predecesora + 1 › inicio proyecto. Fin = real › inicio + duración − 1. % instalación = valor cortes del frente / valor frente; % compra = comprado / ppto material del frente. Atrasada si hoy > fin y % < 100.
B12: TABLERO | C12: (dashboard) | D12: KPIs: valor contrato, avance físico, facturado, costo real, margen proyectado | E12: Avance físico = valor ejecutado / CD. Proyección = MAX(real, ppto); MO = MAX(real, contrato contratista + MO propia). Alerta 'Atención' si % consumido > avance + 15 pts.

Sheet LISTAS
A1: Tipo | B1: TipoAct | C1: TipoGasto | D1: EstActa | E1: SiNo | F1: EstProy
A2: Capítulo | B2: Fase | C2: Material | D2: Pendiente | E2: Sí | F2: En planeación
A3: Subcapítulo | B3: Hito | C3: Equipo | D3: Facturado | E3: No | F3: En ejecución
A4: Ítem | B4: Gestión | C4: Suministro | D4: Pagado | F4: Suspendido
B5: Compra | C5: Alquiler | F5: Terminado
B6: Instalación | C6: Transporte | F6: Liquidado
B7: Pruebas | C7: Mano de obra contratista
